Workbook

Sheet KKLEAD_SPIP
C3: PENJAMINAN KUALITAS HASIL PENILAIAN MANDIRI MATURITAS PENYELENGGARAAN SPIP TERINTEGRASI KEMENTERIAN KOMUNIKASI DAN DIGITAL Periode Penilaian sampai dengan 20 Agustus 2025
C4: PENYIMPULAN NILAI MATURITAS PENYELENGGARAAN SPIP TERINTEGRASI
C6: Komponen, Unsur, dan Subunsur | D6: Skor PM | E6: Skor PK | F6: Bobot Unsur | G6: Bobot Komponen | H6: Nilai Unsur | I6: Nilai Komponen | J6: Nilai Akhir
C8: PENETAPAN TUJUAN
C9: Kualitas Sasaran Strategis | E9: ='KKlead I KL'!I20 -> 4 | F9: 0.5 | H9: =E9*F9 -> 2
C10: Kualitas Strategi Pencapaian Sasaran Strategis | E10: ='KKlead I KL'!I44 -> 5 | F10: 0.5 | H10: =E10*F10 -> 2.5
C11: SUB JUMLAH PERENCANAAN | F11: =SUM(F9:F10) -> 1 | H11: =SUM(H9:H10) -> 4.5
C12: BOBOT PERENCANAAN | G12: 0.4 | I12: =$G$12*$H$11 -> 1.8
C14: STRUKTUR DAN PROSES
C15: Lingkungan Pengendalian
C16: Penegakan Integritas dan Nilai Etika (1.1) | E16: ='KKLEAD II'!L6 -> 4.09375 | F16: =30%/8 -> 0.0375 | H16: =E16*F16 -> 0.15351562
C17: Komitmen terhadap Kompetensi (1.2) | E17: ='KKLEAD II'!L15 -> 3.5 | F17: =30%/8 -> 0.0375 | H17: =E17*F17 -> 0.13125
C18: Kepemimpinan yang Kondusif (1.3) | E18: ='KKLEAD II'!L17 -> 3 | F18: =30%/8 -> 0.0375 | H18: =E18*F18 -> 0.1125
C19: Pembentukan Struktur Organisasi yang Sesuai dengan Kebutuhan (1.4) | E19: ='KKLEAD II'!L25 -> 3.75 | F19: =30%/8 -> 0.0375 | H19: =E19*F19 -> 0.140625
C20: Pendelegasian Wewenang dan Tanggung Jawab yang Tepat (1.5) | E20: ='KKLEAD II'!L27 -> 4.75 | F20: =30%/8 -> 0.0375 | H20: =E20*F20 -> 0.178125
C21: Penyusunan dan Penerapan Kebijakan yang Sehat tentang Pembinaan SDM (1.6) | E21: ='KKLEAD II'!L29 -> 2.75 | F21: =30%/8 -> 0.0375 | H21: =E21*F21 -> 0.103125
C22: Perwujudan Peran APIP yang Efektif (1.7) | E22: ='KKLEAD II'!L33 -> 3 | F22: =30%/8 -> 0.0375 | H22: =E22*F22 -> 0.1125
C23: Hubungan Kerja yang Baik dengan Instansi Pemerintah Terkait (1.8) | E23: ='KKLEAD II'!L35 -> 3.625 | F23: =30%/8 -> 0.0375 | H23: =E23*F23 -> 0.1359375
C24: Penilaian Risiko
C25: Identifikasi Risiko (2.1) | E25: ='KKLEAD II'!L38 -> 2.8333333 | F25: 0.1 | H25: =E25*F25 -> 0.28333333
C26: Analisis Risiko (2.2) | E26: ='KKLEAD II'!L42 -> 2.95 | F26: 0.1 | H26: =E26*F26 -> 0.295
C27: Kegiatan Pengendalian
C28: Reviu atas Kinerja Instansi Pemerintah (3.1) | E28: ='KKLEAD II'!L49 -> 3 | F28: =25%/11 -> 0.022727273 | H28: =E28*F28 -> 0.068181818
C29: Pembinaan Sumber Daya Manusia (3.2) | E29: ='KKLEAD II'!L51 -> 4 | F29: =25%/11 -> 0.022727273 | H29: =E29*F29 -> 0.090909091
C30: Pengendalian atas Pengelolaan Sistem Informasi (3.3) | E30: ='KKLEAD II'!L53 -> 3.5 | F30: =25%/11 -> 0.022727273 | H30: =E30*F30 -> 0.079545455
C31: Pengendalian Fisik atas Aset (3.4) | E31: ='KKLEAD II'!L55 -> 4 | F31: =25%/11 -> 0.022727273 | H31: =E31*F31 -> 0.090909091
C32: Penetapan dan Reviu atas Indikator dan Ukuran Kinerja (3.5) | E32: ='KKLEAD II'!L57 -> 3.5 | F32: =25%/11 -> 0.022727273 | H32: =E32*F32 -> 0.079545455
C33: Pemisahan Fungsi (3.6) | E33: ='KKLEAD II'!L59 -> 3.25 | F33: =25%/11 -> 0.022727273 | H33: =E33*F33 -> 0.073863636
C34: Otorisasi atas Transaksi dan Kejadian yang Penting (3.7) | E34: ='KKLEAD II'!L61 -> 3.25 | F34: =25%/11 -> 0.022727273 | H34: =E34*F34 -> 0.073863636
C35: Pencatatan yang Akurat dan Tepat Waktu atas Transaksi dan Kejadian (3.8) | E35: ='KKLEAD II'!L63 -> 4 | F35: =25%/11 -> 0.022727273 | H35: =E35*F35 -> 0.090909091
C36: Pembatasan Akses atas Sumber Daya dan Pencatatannya (3.9) | E36: ='KKLEAD II'!L65 -> 3.5 | F36: =25%/11 -> 0.022727273 | H36: =E36*F36 -> 0.079545455
C37: Akuntabilitas terhadap Sumber Daya dan Pencatatannya (3.10) | E37: ='KKLEAD II'!L67 -> 3.75 | F37: =25%/11 -> 0.022727273 | H37: =E37*F37 -> 0.085227273
C38: Dokumentasi yang Baik atas SPI serta Transaksi dan Kejadian Penting (3.11) | E38: ='KKLEAD II'!L69 -> 3.5 | F38: =25%/11 -> 0.022727273 | H38: =E38*F38 -> 0.079545455
C39: Informasi dan Komunikasi
C40: Informasi yang Relevan (4.1) | E40: ='KKLEAD II'!L71 -> 3.05 | F40: 0.05 | H40: =E40*F40 -> 0.1525
C41: Komunikasi yang Efektif (4.2) | E41: ='KKLEAD II'!L77 -> 3 | F41: 0.05 | H41: =E41*F41 -> 0.15
C42: Pemantauan
C43: Pemantauan Berkelanjutan (5.1) | E43: ='KKLEAD II'!L79 -> 3.0833333 | F43: 0.075 | H43: =E43*F43 -> 0.23125
C44: Evaluasi Terpisah (5.2) | E44: ='KKLEAD II'!L83 -> 2.625 | F44: 0.075 | H44: =E44*F44 -> 0.196875
C45: SUB JUMLAH STRUKTUR DAN PROSES | H45: =SUM(H16:H44) -> 3.2685819
C46: BOBOT STRUKTUR DAN PROSES | G46: 0.3 | I46: =$H$45*$G$46 -> 0.98057457
C48: PENCAPAIAN TUJUAN SPIP
C49: Efektivitas dan Efisiensi
C50: Capaian Outcome | E50: =('KKLEAD III'!G6+'KKLEAD III'!G7)/2 -> 5 | F50: 0.2 | H50: =E50*F50 -> 1
C51: Capaian Output | E51: ='KKLEAD III'!G8*1 -> 5 | F51: 0.1 | H51: =E51*F51 -> 0.5
C52: Keandalan Laporan Keuangan
C53: Opini LK | E53: ='KKLEAD III'!G10*1 -> 3 | F53: 0.25 | H53: =E53*F53 -> 0.75
C54: Pengamanan atas Aset
C55: Catatan Pengamanan Aset | E55: ='KKLEAD III'!G12*1 -> 3 | F55: 0.25 | H55: =E55*F55 -> 0.75
C56: Ketaatan pada Peraturan
C57: Temuan Ketaatan - BPK | E57: ='KKLEAD III'!G14*1 -> 2 | F57: 0.2 | H57: =E57*F57 -> 0.4
C58: IEPK | D58: 3
C59: SUB JUMLAH HASIL | F59: =SUM(F50:F58) -> 1 | H59: =SUM(H50:H57) -> 3.4
C60: BOBOT HASIL | G60: 0.3 | I60: =$G$60*$H$59 -> 1.02
C61: NILAI MATURITAS PENYELENGGARAAN SPIP | J61: =I12+I46+I60 -> 3.8005746
C62: LEVEL MATURITAS PENYELENGGARAAN SPIP | J62: =IF(AND(J61>=4.5),"5",(IF(AND(J61>=4),"4",(IF(AND(J61>=3),"3",(IF(AND(J61>=2),"2","1"))))))) -> 3
C65: NILAI INDEKS PENERAPAN MANAJEMEN RISIKO (MRI) | J65: =G80 -> 3.6671875
C68: AREA/KOMPONEN | D68: BOBOT | E68: SKOR PM | F68: SKOR PK | G68: NILAI
C69: PERENCANAAN | D69: =D70 -> 0.4 | G69: =G70 -> 1.8
C70: KUALITAS PERENCANAAN | D70: 0.4 | F70: =H11 -> 4.5 | G70: =D70*F70 -> 1.8
C71: KAPABILITAS | D71: =SUM(D72:D76) -> 0.3 | G71: =SUM(G72:G76) -> 0.859375
C72: KEPEMIMPINAN | D72: 0.05 | F72: =('KKLEAD II'!N19+'KKLEAD II'!N20+'KKLEAD II'!N21+'KKLEAD II'!N73)/4 -> 2.875 | G72: =D72*F72 -> 0.14375
C73: KEBIJAKAN MANAJEMEN RISIKO | D73: 0.05 | F73: ='KKLEAD II'!N39 -> 3 | G73: =D73*F73 -> 0.15
C74: SUMBER DAYA MANUSIA | D74: 0.05 | F74: =('KKLEAD II'!N31+'KKLEAD II'!N32)/2 -> 2.5 | G74: =D74*F74 -> 0.125
C75: KEMITRAAN | D75: 0.025 | F75: ='KKLEAD II'!N37 -> 3 | G75: =D75*F75 -> 0.075
C76: PROSES MANAJEMEN RISIKO | D76: 0.125 | F76: =('KKLEAD II'!N40+'KKLEAD II'!N41+'KKLEAD II'!N43+'KKLEAD II'!N44+'KKLEAD II'!N45+'KKLEAD II'!N74+'KKLEAD II'!N75+'KKLEAD II'!N81+'KKLEAD II'!N82+'KKLEAD II'!N85)/10 -> 2.925 | G76: =D76*F76 -> 0.365625
C77: HASIL | D77: =D78+D79 -> 0.3 | G77: =G78+G79 -> 1.0078125
C78: AKTIVITAS PENANGANAN RISIKO | D78: 0.1875 | F78: =('KKLEAD II'!N46+'KKLEAD II'!N47)/2 -> 2.375 | G78: =D78*F78 -> 0.4453125
C79: OUTCOMES | D79: 0.1125 | F79: =E50 -> 5 | G79: =D79*F79 -> 0.5625
C80: TOTAL | D80: =D69+D71+D77 -> 1 | G80: =G69+G71+G77 -> 3.6671875
C82: NILAI INDEKS EFEKTIVITAS PENCEGAHAN KORUPSI (IEPK) | J82: =G101 -> 3.08
C85: PILAR | D85: BOBOT | E85: SKOR PM | F85: SKOR PK | G85: NILAI
C86: KAPABILITAS PENGELOLAAN RISIKO KORUPSI | D86: =SUM(D87:D91) -> 0.48 | G86: =SUM(G87:G91) -> 1.44
C87: KEBIJAKAN ANTIKORUPSI | D87: 0.096 | F87: ='KKLEAD II'!N8 -> 3 | G87: =D87*F87 -> 0.288
C88: SEPERANGKAT SISTEM ANTIKORUPSI | D88: 0.072 | F88: ='KKLEAD II'!N9 -> 3 | G88: =D88*F88 -> 0.216
C89: DUKUNGAN SUMBER DAYA | D89: 0.072 | F89: ='KKLEAD II'!N22 -> 3 | G89: =D89*F89 -> 0.216
C90: POWER (KUASA & WEWEWANG) | D90: 0.144 | F90: ='KKLEAD II'!N23 -> 3 | G90: =D90*F90 -> 0.432
C91: PEMBELAJARAN ANTIKORUPSI | D91: 0.096 | F91: ='KKLEAD II'!N10 -> 3 | G91: =D91*F91 -> 0.288
C92: PENERAPAN STRATEGI PENCEGAHAN | D92: =SUM(D93:D97) -> 0.36 | G92: =SUM(G93:G97) -> 1.08
C93: ASESMEN DAN MITIGASI RISIKO KORUPSI | D93: 0.09 | F93: ='KKLEAD II'!N48 -> 3 | G93: =D93*F93 -> 0.27
C94: SALURAN PELAPORAN INTERNAL YANG EFEKTIF DAN KREDIBEL | D94: 0.036 | F94: ='KKLEAD II'!N76 -> 3 | G94: =D94*F94 -> 0.108
C95: KEPEMIMPINAN ETIS | D95: 0.09 | F95: ='KKLEAD II'!N24 -> 3 | G95: =D95*F95 -> 0.27
C96: INTEGRITAS ORGANISASIONAL | D96: 0.072 | F96: ='KKLEAD II'!N11 -> 3 | G96: =D96*F96 -> 0.216
C97: IKLIM ETIS PRINSIP | D97: 0.072 | F97: ='KKLEAD II'!N12 -> 3 | G97: =D97*F97 -> 0.216
C98: PENANGANAN KEJADIAN KORUPSI | D98: =SUM(D99:D100) -> 0.16 | G98: =SUM(G99:G100) -> 0.56
C99: INVESTIGASI | D99: 0.08 | F99: ='KKLEAD II'!N13 -> 4 | G99: =D99*F99 -> 0.32
C100: TINDAKAN KOREKTIF | D100: 0.08 | F100: ='KKLEAD II'!N14 -> 3 | G100: =D100*F100 -> 0.24
C101: TOTAL | D101: =D86+D92+D98 -> 1 | G101: =G86+G92+G98 -> 3.08
C103: KAPABILITAS APIP | J103: =E22 -> 3
C107: STRUKTUR DAN PROSES
C108: Lingkungan Pengendalian | D108: 0.3 | E108: 3.559 | F108: 1.067
C109: Penilain Risiko | D109: 0.2 | E109: 2.892 | F109: 0.578
C110: Kegiatan Pengendalian | D110: 0.25 | E110: 3.568 | F110: 0.892
C111: Informasi dan Komunikasi | D111: 0.1 | E111: 3.031 | F111: 0.303
C112: Pemantauan | D112: 0.15 | E112: 2.854 | F112: 0.428
C113: SUB JUMLAH STRUKTUR DAN PROSES | D113: 1 | F113: 3.268
C114: BOBO STRUKTUR DAN PROSES | D114: 0.3 | F114: 0.981

Sheet KKLEAD II
A1: PENJAMINAN KUALITAS HASIL PENILAIAN MANDIRI MATURITAS PENYELENGGARAAN SPIP PEMERINTAH DAERAH … Periode Penilaian 01 Juli 20XX-1 sampai dengan 30 Juni 20XX
A2: KERTAS KERJA PENILAIAN STRUKTUR DAN PROSES KK LEAD II - STRUKTUR DAN PROSES | L2: Indeks KK No. Disusun oleh/Tanggal Direviu oleh/Tanggal Disetujui oleh/Tanggal | M2: : : : :
A3: Kode | B3: Uraian Subunsur | C3: No | D3: Uraian Parameter | E3: Kode Parameter | H3: 2E NILAI | I3: KEUANGAN NILAI | J3: ASET NILAI | K3: KETAATAN NILAI | L3: KESIMPULAN NILAI | M3: VETO (YA/TIDAK) | N3: NILAI AKHIR | O3: KETERANGAN / CATATAN
E4: SPIP | F4: MRI | G4: IEPK
A6: 1.1 | B6: Penegakan Integritas dan Nilai Etika | H6: =AVERAGE(H7:H14) -> 3 | I6: =AVERAGE(I7:I14) -> 5 | J6: =AVERAGE(J7:J14) -> 5 | K6: =AVERAGE(K7:K14) -> 3.375 | L6: ='Uraian NIlai Setiap Unsur'!I5 -> 4.09375 | M6: =KK4_PENALTI!C5 -> TIDAK | N6: =IF(M6="YA",KK4_PENALTI!D5,L6) -> 4.09375
A7: 1.1 | C7: 1 | D7: Organisasi menegakkan integritas dan nilai etika dalam melaksanakan tugas dan fungsi organisasi Organisasi menegakkan integritas dan nilai etika dalam pengelolaan keuangan Organisasi menegakkan integritas dan nilai etika dalam pengelolaan aset Organisasi menegakkan integritas dan nilai etika dalam pelaksanaan tugasnya sesuai peraturan yang berlaku | E7: SPIP | F7: - | G7: - | H7: =KK3.1!S6 -> 3 | I7: =KK3.2!N7 -> 5 | J7: =KK3.3!N6 -> 5 | K7: =KK3.4!N6 -> 5 | L7: =AVERAGE(H7:K7) -> 4.5 | N7: =IF(AND($M$6="YA",L7>$N$6),$N$6,L7) -> 4.5
A8: 1.1 | C8: 2 | D8: Kebijakan eksplisit atas pengendalian korupsi yang mencakup pernyataan kebijakan, penetapan struktur pengelola risiko korupsi, serta standar perilaku antikorupsi | E8: SPIP | F8: - | G8: IEPK | K8: =KK3.4!N11 -> 3 | L8: =AVERAGE(H8:K8) -> 3 | N8: =IF(AND($M$6="YA",L8>$N$6),$N$6,L8) -> 3
A9: 1.1 | C9: 3 | D9: Organisasi menetapkan dan melaksanakan SOP antikorupsi yang mencakup tiga proses prinsip dalam pengelolaan risiko korupsi, yakni cegah, deteksi, dan respons. | E9: SPIP | F9: - | G9: IEPK | K9: =KK3.4!N16 -> 3 | L9: =AVERAGE(H9:K9) -> 3 | N9: =IF(AND($M$6="YA",L9>$N$6),$N$6,L9) -> 3
A10: 1.1 | C10: 4 | D10: Unit kerja sebagai lingkungan belajar dikelola untuk memungkinkan pegawai di semua level berpartisipasi dalam program antikorupsi dengan menghindari perilaku koruptif dan menunjukkan sikap lugas ketika berhadapan dengan situasi yang memicu perilaku korupsi | E10: SPIP | F10: - | G10: IEPK | K10: =KK3.4!N21 -> 3 | L10: =AVERAGE(H10:K10) -> 3 | N10: =IF(AND($M$6="YA",L10>$N$6),$N$6,L10) -> 3
A11: 1.1 | C11: 5 | D11: Integritas organisasional yang terwujud dalam transparansi dan akuntabilitas telah tercermin dalam visi, misi, tujuan, dan nilai-nilai organisasi/unit kerja | E11: SPIP | F11: - | G11: IEPK | K11: =KK3.4!N26 -> 3 | L11: =AVERAGE(H11:K11) -> 3 | N11: =IF(AND($M$6="YA",L11>$N$6),$N$6,L11) -> 3
A12: 1.1 | C12: 6 | D12: Terdapat persepsi bersama bahwa yang dijadikan acuan utama sebagai perilaku etis adalah peraturan, SOP, hukum, atau standar profesional | E12: SPIP | F12: - | G12: IEPK | K12: =KK3.4!N31 -> 3 | L12: =AVERAGE(H12:K12) -> 3 | N12: =IF(AND($M$6="YA",L12>$N$6),$N$6,L12) -> 3
A13: 1.1 | C13: 7 | D13: Kejadian korupsi/perilaku koruptif telah ditindaklanjuti oleh orang yang kompeten dan independen | E13: SPIP | F13: - | G13: IEPK | K13: =KK3.4!N36 -> 4 | L13: =AVERAGE(H13:K13) -> 4 | N13: =IF(AND($M$6="YA",L13>$N$6),$N$6,L13) -> 4
A14: 1.1 | C14: 8 | D14: Atas hasil audit atau investigasi telah diambil langkah dalam rangka memperbaiki kerusakan yang ditimbulkan oleh praktik korupsi di dalam organisasi berupa pemastian pengenaan sanksi dan perbaikan melalui pemulihan kerugian dan peningkatan pengendalian. | E14: SPIP | F14: - | G14: IEPK | K14: =KK3.4!N41 -> 3 | L14: =AVERAGE(H14:K14) -> 3 | N14: =IF(AND($M$6="YA",L14>$N$6),$N$6,L14) -> 3
A15: 1.2 | B15: Komitmen terhadap Kompetensi | H15: =H16 -> 4 | I15: =I16 -> 3 | J15: =J16 -> 3 | K15: =K16 -> 4 | L15: =AVERAGE(H15:K15) -> 3.5 | M15: =KK4_PENALTI!C6 -> TIDAK | N15: =IF(M15="YA",KK4_PENALTI!D6,L15) -> 3.5
A16: 1.2 | C16: 1 | D16: Tugas dan jabatan dalam organisasi dilaksanakan dan diisi oleh SDM yang kompeten | E16: SPIP | F16: - | G16: - | H16: =KK3.1!V12 -> 4 | I16: =KK3.2!N13 -> 3 | J16: =KK3.3!N12 -> 3 | K16: =KK3.4!N47 -> 4 | L16: =AVERAGE(H16:K16) -> 3.5 | N16: =IF($M$15="YA",$N$15,L16) -> 3.5
A17: 1.3 | B17: Kepemimpinan yang Kondusif | H17: =AVERAGE(H18:H24) -> 3.25 | I17: =AVERAGE(I18:I24) -> 3 | J17: =AVERAGE(J18:J24) -> 2.75 | K17: =AVERAGE(K18:K24) -> 3 | L17: =AVERAGE(H17:K17) -> 3 | M17: =KK4_PENALTI!C7 -> TIDAK | N17: =IF(M17="YA",KK4_PENALTI!D7,L17) -> 3
A18: 1.3 | C18: 1 | D18: Pimpinan organisasi menciptakan lingkungan kerja yang kondusif untuk pencapaian tujuan organisasi. | E18: SPIP | F18: - | G18: - | H18: =KK3.1!S18 -> 4 | I18: =KK3.2!N19 -> 4 | J18: =KK3.3!N18 -> 3 | K18: =KK3.4!N53 -> 3 | L18: =AVERAGE(H18:K18) -> 3.5 | N18: =IF($M$17="YA",$N$17,L18) -> 3.5
A19: 1.3 | C19: 2 | D19: Pimpinan Instansi Pemerintah mengalokasikan sumber daya untuk penerapan manajemen risiko. | E19: SPIP | F19: MRI | G19: - | H19: =KK3.1!S23 -> 3 | I19: =KK3.2!N24 -> 3 | J19: =KK3.3!N23 -> 3 | K19: =KK3.4!N58 -> 3 | L19: =AVERAGE(H19:K19) -> 3 | N19: =IF($M$17="YA",$N$17,L19) -> 3 | P19: KEPEMIMPINAN
A20: 1.3 | C20: 3 | D20: Pimpinan Instansi Pemerintah menggunakan informasi terkait risiko dalam pengambilan keputusan | E20: SPIP | F20: MRI | G20: - | H20: =KK3.1!S28 -> 3 | I20: =KK3.2!N29 -> 2 | J20: =KK3.3!N28 -> 2 | K20: =KK3.4!N63 -> 3 | L20: =AVERAGE(H20:K20) -> 2.5 | N20: =IF($M$17="YA",$N$17,L20) -> 2.5 | P20: KEPEMIMPINAN
A21: 1.3 | C21: 4 | D21: Pimpinan Instansi Pemerintah mendorong penerapan manajemen risiko, melalui Penggunaan kinerja penerapan manajemen risiko sebagai indikator penilaian kinerja | E21: SPIP | F21: MRI | G21: - | H21: =KK3.1!S33 -> 3 | I21: =KK3.2!N34 -> 3 | J21: =KK3.3!N33 -> 3 | K21: =KK3.4!N68 -> 3 | L21: =AVERAGE(H21:K21) -> 3 | N21: =IF($M$17="YA",$N$17,L21) -> 3 | P21: KEPEMIMPINAN
C22: 5 | D22: Program antikorupsi didukung dengan penyediaan alokasi sumberdaya secara eksplisit secara memadai, baik anggaran, personil, dan sarana prasarana | E22: SPIP | F22: - | G22: IEPK | K22: =KK3.4!N73 -> 3 | L22: =AVERAGE(H22:K22) -> 3 | N22: =IF($M$17="YA",$N$17,L22) -> 3
C23: 6 | D23: Faktor kekuasaan dan wewenang yang melekat pada pimpinan unit kerja dipakai untuk tujuan mengelola risiko korupsi secara efektif (tidak membiarkan/ mengabaikan) | E23: SPIP | F23: - | G23: IEPK | K23: =KK3.4!N78 -> 3 | L23: =AVERAGE(H23:K23) -> 3 | N23: =IF($M$17="YA",$N$17,L23) -> 3
C24: 7 | D24: Pimpinan mendorong bawahan untuk mengikutinya melalui atensi yang diberikan di berbagai kesempatan, keterbukaan dan transparansi, reinforcement, perlakuan adil, dan pengambilan keputusan yang menyertakan pertimbangan etis. | E24: SPIP | F24: - | G24: IEPK | K24: =KK3.4!N83 -> 3 | L24: =AVERAGE(H24:K24) -> 3 | N24: =IF($M$17="YA",$N$17,L24) -> 3
A25: 1.4 | B25: Struktur Organisasi Sesuai Kebutuhan | H25: =H26 -> 4 | I25: =I26 -> 4 | J25: =J26 -> 4 | K25: =K26 -> 3 | L25: =AVERAGE(H25:K25) -> 3.75 | M25: =KK4_PENALTI!C8 -> TIDAK | N25: =IF(M25="YA",KK4_PENALTI!D8,L25) -> 3.75
A26: 1.4 | C26: 1 | D26: Struktur organisasi dibentuk dalam rangka mendukung pencapaian sasaran strategis organisasi. Struktur organisasi dibentuk dalam rangka mendukung pencapaian keandalan laporan keuangan Struktur organisasi dibentuk dalam rangka mendukung pencapaian keamanan aset Dalam Struktur organisasi terdapat unit yang melaksanakan fungsi kepatuhan internal. | E26: SPIP | F26: - | G26: - | H26: =KK3.1!S39 -> 4 | I26: =KK3.2!N40 -> 4 | J26: =KK3.3!N39 -> 4 | K26: =KK3.4!N89 -> 3 | L26: =AVERAGE(H26:K26) -> 3.75 | N26: =IF($M$25="YA",$N$25,L26) -> 3.75
A27: 1.5 | B27: Pendelegasian Wewenang dan Tanggung Jawab yang Tepat | H27: =H28 -> 5 | I27: =I28 -> 5 | J27: =J28 -> 5 | K27: =K28 -> 4 | L27: =AVERAGE(H27:K27) -> 4.75 | M27: =KK4_PENALTI!C9 -> TIDAK | N27: =IF(M27="YA",KK4_PENALTI!D9,L27) -> 4.75
A28: 1.5 | C28: 1 | D28: Wewenang dan tanggung jawab diberikan kepada pegawai yang tepat sesuai tingkatannya untuk mendukung efektivitas dan efisiensi pelaksanaan kegiatan dalam rangka percepatan pencapaian tujuan organisasi. Pendelegasian Wewenang dan Tanggung Jawab memperhatikan benturan kepentingan | E28: SPIP | F28: - | G28: - | H28: =KK3.1!S45 -> 5 | I28: =KK3.2!N46 -> 5 | J28: =KK3.3!N45 -> 5 | K28: =KK3.4!N95 -> 4 | L28: =AVERAGE(H28:K28) -> 4.75 | N28: =IF($M$27="YA",$N$27,L28) -> 4.75
A29: 1.6 | B29: Penyusunan dan Penerapan Kebijakan yang Sehat tentang Pembinaan SDM | H29: =AVERAGE(H30:H32) -> 3 | I29: =AVERAGE(I30:I32) -> 2 | J29: =AVERAGE(J30:J32) -> 3 | K29: =AVERAGE(K30:K32) -> 3 | L29: =AVERAGE(H29:K29) -> 2.75 | M29: =KK4_PENALTI!C10 -> TIDAK | N29: =IF(M29="YA",KK4_PENALTI!D10,L29) -> 2.75
A30: 1.6 | C30: 1 | D30: Penerapan kebijakan manajemen dan praktik pembinaan SDM sehingga dapat digunakan secara maksimal untuk mencapai tujuan organisasi | E30: SPIP | F30: - | G30: - | H30: =KK3.1!S51 -> 3 | I30: =KK3.2!N52 -> 2 | J30: =KK3.3!N51 -> 5 | K30: =KK3.4!N101 -> 3 | L30: =AVERAGE(H30:K30) -> 3.25 | N30: =IF($M$29="YA",$N$29,L30) -> 3.25
A31: 1.6 | C31: 2 | D31: Pegawai telah mendapatkan fasilitas untuk meningkatkan kompetensi dan keterampilan terkait manajemen risiko | E31: SPIP | F31: MRI | G31: - | H31: =KK3.1!S56 -> 3 | I31: =KK3.2!N57 -> 2 | J31: =KK3.3!N56 -> 2 | K31: =KK3.4!N106 -> 3 | L31: =AVERAGE(H31:K31) -> 2.5 | N31: =IF($M$29="YA",$N$29,L31) -> 2.5 | P31: SDM
A32: 1.6 | C32: 3 | D32: Pegawai memiliki kesadaran terkait manajemen risiko | E32: SPIP | F32: MRI | G32: - | H32: =KK3.1!S61 -> 3 | I32: =KK3.2!N62 -> 2 | J32: =KK3.3!N61 -> 2 | K32: =KK3.4!N111 -> 3 | L32: =AVERAGE(H32:K32) -> 2.5 | N32: =IF($M$29="YA",$N$29,L32) -> 2.5 | P32: SDM
A33: 1.7 | B33: Perwujudan Peran APIP yang Efektif | H33: =H34 -> 3 | I33: =I34 -> 3 | J33: =J34 -> 3 | K33: =K34 -> 3 | L33: =AVERAGE(H33:K33) -> 3 | M33: =KK4_PENALTI!C11 -> TIDAK | N33: =IF(M33="YA",KK4_PENALTI!D11,L33) -> 3
A34: 1.7 | C34: 1 | D34: Pengawasan APIP telah dapat memberikan nilai tambah pada perbaikan pengendalian organisasi | E34: SPIP | F34: - | G34: - | H34: =KK3.1!S67 -> 3 | I34: =KK3.2!N68 -> 3 | J34: =KK3.3!N67 -> 3 | K34: =KK3.4!N117 -> 3 | L34: =AVERAGE(H34:K34) -> 3 | N34: =IF($M$33="YA",$N$33,L34) -> 3
A35: 1.8 | B35: Hubungan Kerja yang Baik dengan Instansi Pemerintah Terkait | H35: =AVERAGE(H36:H37) -> 3 | I35: =AVERAGE(I36:I37) -> 4 | J35: =AVERAGE(J36:J37) -> 4 | K35: =AVERAGE(K36:K37) -> 3.5 | L35: =AVERAGE(H35:K35) -> 3.625 | M35: =KK4_PENALTI!C12 -> TIDAK | N35: =IF(M35="YA",KK4_PENALTI!D12,L35) -> 3.625
A36: 1.8 | C36: 1 | D36: Pimpinan organisasi menjalin hubungan kerja yang baik (kemitraan) dengan instansi lain terkait dengan upaya pencapaian tujuan organisasi. | E36: SPIP | F36: - | G36: - | H36: =KK3.1!S73 -> 3 | I36: =KK3.2!N74 -> 5 | J36: =KK3.3!N73 -> 5 | K36: =KK3.4!N123 -> 4 | L36: =AVERAGE(H36:K36) -> 4.25 | N36: =IF($M$35="YA",$N$35,L36) -> 4.25
A37: 1.8 | C37: 2 | D37: Dalam rangka menciptakan hubungan kerja yang baik, instansi Pemerintah telah mengidentifikasi, menilai, dan mengelola risiko (termasuk implikasi dari transfer risiko) terkait kemitraan | E37: SPIP | F37: MRI | G37: - | H37: =KK3.1!S78 -> 3 | I37: =KK3.2!N79 -> 3 | J37: =KK3.3!N78 -> 3 | K37: =KK3.4!N128 -> 3 | L37: =AVERAGE(H37:K37) -> 3 | N37: =IF($M$35="YA",$N$35,L37) -> 3 | P37: KEMITRAAN
A38: 2.1 | B38: Identifikasi Risiko | H38: =AVERAGE(H39:H41) -> 4 | I38: =AVERAGE(I39:I41) -> 2.3333333 | J38: =AVERAGE(J39:J41) -> 2.3333333 | K38: =AVERAGE(K39:K41) -> 2.6666667 | L38: =AVERAGE(H38:K38) -> 2.8333333 | M38: =KK4_PENALTI!C14 -> TIDAK | N38: =IF(M38="YA",KK4_PENALTI!D14,L38) -> 2.8333333
A39: 2.1 | C39: 1 | D39: Pemerintah Daerah telah memiliki Kebijakan Manajemen Risiko. | E39: SPIP | F39: MRI | G39: - | H39: =KK3.1!S84 -> 4 | I39: =KK3.2!N85 -> 2 | J39: =KK3.3!N84 -> 2 | K39: =KK3.4!N134 -> 4 | L39: =AVERAGE(H39:K39) -> 3 | N39: =IF($M$38="YA",$N$38,L39) -> 3 | P39: KEBIJAKAN
A40: 2.1 | C40: 2 | D40: Risiko telah teridentifikasi dan dituangkan dalam register risiko | E40: SPIP | F40: MRI | G40: - | H40: =KK3.1!S89 -> 4 | I40: =KK3.2!N90 -> 3 | J40: =KK3.3!N89 -> 3 | K40: =KK3.4!N139 -> 2 | L40: =AVERAGE(H40:K40) -> 3 | N40: =IF($M$38="YA",$N$38,L40) -> 3 | P40: PROSES
A41: 2.1 | C41: 3 | D41: Proses manajemen risiko telah melekat pada proses bisnis Instansi Pemerintah | E41: SPIP | F41: MRI | G41: - | H41: =KK3.1!S94 -> 4 | I41: =KK3.2!N95 -> 2 | J41: =KK3.3!N94 -> 2 | K41: =KK3.4!N144 -> 2 | L41: =AVERAGE(H41:K41) -> 2.5 | N41: =IF($M$38="YA",$N$38,L41) -> 2.5 | P41: PROSES
A42: 2.2 | B42: Analisis Risiko | H42: =AVERAGE(H43:H48) -> 3.6 | I42: =AVERAGE(I43:I48) -> 2.6 | J42: =AVERAGE(J43:J48) -> 2.6 | K42: =AVERAGE(K43:K48) -> 3 | L42: =AVERAGE(H42:K42) -> 2.95 | M42: =KK4_PENALTI!C15 -> TIDAK | N42: =IF(M42="YA",KK4_PENALTI!D15,L42) -> 2.95
A43: 2.2 | C43: 1 | D43: Seluruh risiko telah dianalisis dampak dan tingkat keterjadiannya | E43: SPIP | F43: MRI | G43: - | H43: =KK3.1!S100 -> 4 | I43: =KK3.2!N101 -> 3 | J43: =KK3.3!N100 -> 3 | K43: =KK3.4!N150 -> 3 | L43: =AVERAGE(H43:K43) -> 3.25 | N43: =IF($M$42="YA",$N$42,L43) -> 3.25 | P43: PROSES
A44: 2.2 | C44: 2 | D44: Instansi pemerintah telah menentukan prioritas risiko | E44: SPIP | F44: MRI | G44: - | H44: =KK3.1!S105 -> 4 | I44: =KK3.2!N106 -> 3 | J44: =KK3.3!N105 -> 3 | K44: =KK3.4!N155 -> 4 | L44: =AVERAGE(H44:K44) -> 3.5 | N44: =IF($M$42="YA",$N$42,L44) -> 3.5 | P44: PROSES
A45: 2.2 | C45: 3 | D45: Instansi Pemerintah telah menentukan rencana tindak pengendalian | E45: SPIP | F45: MRI | G45: - | H45: =KK3.1!S110 -> 4 | I45: =KK3.2!N111 -> 3 | J45: =KK3.3!N110 -> 3 | K45: =KK3.4!N160 -> 3 | L45: =AVERAGE(H45:K45) -> 3.25 | N45: =IF($M$42="YA",$N$42,L45) -> 3.25 | P45: PROSES
A46: 2.2 | C46: 4 | D46: Tindak pengendalian telah diimplementasikan | E46: SPIP | F46: MRI | G46: - | H46: =KK3.1!S115 -> 3 | I46: =KK3.2!N116 -> 3 | J46: =KK3.3!N115 -> 3 | K46: =KK3.4!N165 -> 3 | L46: =AVERAGE(H46:K46) -> 3 | N46: =IF($M$42="YA",$N$42,L46) -> 3 | P46: HASIL
A47: 2.2 | C47: 5 | D47: Tindak pengendalian efektif menurunkan risiko | E47: SPIP | F47: MRI | G47: - | H47: =KK3.1!S120 -> 3 | I47: =KK3.2!N121 -> 1 | J47: =KK3.3!N120 -> 1 | K47: =KK3.4!N170 -> 2 | L47: =AVERAGE(H47:K47) -> 1.75 | N47: =IF($M$42="YA",$N$42,L47) -> 1.75 | P47: HASIL
C48: 6 | D48: Analisis dan asesmen risiko telah dilakukan dan menghasilkan rancangan tindak pengendalian untuk memitigasi risiko korupsi yang sudah terpetakan | E48: SPIP | F48: - | G48: IEPK | K48: =KK3.4!N175 -> 3 | L48: =AVERAGE(H48:K48) -> 3 | N48: =IF($M$42="YA",$N$42,L48) -> 3
A49: 3.1 | B49: Reviu atas Kinerja | H49: =H50 -> 3 | I49: =I50 -> 3 | J49: =J50 -> 3 | K49: =K50 -> 3 | L49: =AVERAGE(H49:K49) -> 3 | M49: =KK4_PENALTI!C17 -> TIDAK | N49: =IF(M49="YA",KK4_PENALTI!D17,L49) -> 3
A50: 3.1 | C50: 1 | D50: Pimpinan organisasi membandingkan tolok ukur kinerja dengan capaian kinerja secara berkala untuk mengatasi hambatan kinerja, menetapkan strategi perbaikan, dan menilai kinerja suatu unit sampai dengan periode tertentu dalam rangka mengawal pencapaian tujuan organisasi. | E50: SPIP | F50: - | G50: - | H50: =KK3.1!S126 -> 3 | I50: =KK3.2!N127 -> 3 | J50: =KK3.3!N126 -> 3 | K50: =KK3.4!N181 -> 3 | L50: =AVERAGE(H50:K50) -> 3 | N50: =IF($M$49="YA",$N$49,L50) -> 3
A51: 3.2 | B51: Pembinaan SDM | H51: =H52 -> 4 | I51: =I52 -> 5 | J51: =J52 -> 4 | K51: =K52 -> 3 | L51: =AVERAGE(H51:K51) -> 4 | M51: =KK4_PENALTI!C18 -> TIDAK | N51: =IF(M51="YA",KK4_PENALTI!D18,L51) -> 4
A52: 3.2 | C52: 1 | D52: Pembinaan SDM dilakukan sehingga setiap pegawai dapat memberikan manfaat optimal dalam pencapaian tujuan organisasi | E52: SPIP | F52: - | G52: - | H52: =KK3.1!S132 -> 4 | I52: =KK3.2!N133 -> 5 | J52: =KK3.3!N132 -> 4 | K52: =KK3.4!N187 -> 3 | L52: =AVERAGE(H52:K52) -> 4 | N52: =IF($M$51="YA",$N$51,L52) -> 4
A53: 3.3 | B53: Pengendalian atas Pengelolaan Sistem Informasi | H53: =H54 -> 4 | I53: =I54 -> 3 | J53: =J54 -> 3 | K53: =K54 -> 4 | L53: =AVERAGE(H53:K53) -> 3.5 | M53: =KK4_PENALTI!C19 -> TIDAK | N53: =IF(M53="YA",KK4_PENALTI!D19,L53) -> 3.5
A54: 3.3 | C54: 1 | D54: Pengendalian atas pengelolaan sistem informasi dilakukan untuk memastikan sistem informasi dapat menyajikan data yang akurat dan tepat waktu untuk digunakan oleh pengguna. | E54: SPIP | F54: - | G54: - | H54: =KK3.1!S138 -> 4 | I54: =KK3.2!N139 -> 3 | J54: =KK3.3!N138 -> 3 | K54: =KK3.4!N193 -> 4 | L54: =AVERAGE(H54:K54) -> 3.5 | N54: =IF($M$53="YA",$N$53,L54) -> 3.5
A55: 3.4 | B55: Pengendalian Fisik atas Aset | H55: =H56 -> 4 | I55: =I56 -> 4 | J55: =J56 -> 5 | K55: =K56 -> 3 | L55: =AVERAGE(H55:K55) -> 4 | M55: =KK4_PENALTI!C20 -> TIDAK | N55: =IF(M55="YA",KK4_PENALTI!D20,L55) -> 4
A56: 3.4 | C56: 1 | D56: Pengelolaan BMN/D dilakukan untuk menjamin aset tersedia dan dapat digunakan dengan baik oleh pengguna dalam rangka mendukung kinerja organisasi. | E56: SPIP | F56: - | G56: - | H56: =KK3.1!S144 -> 4 | I56: =KK3.2!N145 -> 4 | J56: =KK3.3!N144 -> 5 | K56: =KK3.4!N199 -> 3 | L56: =AVERAGE(H56:K56) -> 4 | N56: =IF($M$55="YA",$N$55,L56) -> 4
A57: 3.5 | B57: Penetapan dan Reviu atas Indikator dan Ukuran Kinerja | H57: =H58 -> 4 | I57: =I58 -> 3 | J57: =J58 -> 3 | K57: =K58 -> 4 | L57: =AVERAGE(H57:K57) -> 3.5 | M57: =KK4_PENALTI!C21 -> TIDAK | N57: =IF(M57="YA",KK4_PENALTI!D21,L57) -> 3.5
A58: 3.5 | C58: 1 | D58: Kegiatan pengendalian atas penetapan dan reviu atas indikator dan ukuran kinerja dilakukan untuk menjamin keandalan ukuran dan ketepatan penetapan indikator masing-masing unit secara berjenjang dibandingkan dengan IKU organisasi. | E58: SPIP | F58: - | G58: - | H58: =KK3.1!S150 -> 4 | I58: =KK3.2!N151 -> 3 | J58: =KK3.3!N150 -> 3 | K58: =KK3.4!N205 -> 4 | L58: =AVERAGE(H58:K58) -> 3.5 | N58: =IF($M$57="YA",$N$57,L58) -> 3.5
A59: 3.6 | B59: Pemisahan Fungsi | H59: =H60 -> 4 | I59: =I60 -> 3 | J59: =J60 -> 3 | K59: =K60 -> 3 | L59: =AVERAGE(H59:K59) -> 3.25 | M59: =KK4_PENALTI!C22 -> TIDAK | N59: =IF(M59="YA",KK4_PENALTI!D22,L59) -> 3.25
A60: 3.6 | C60: 1 | D60: Terdapat pemisahan fungsi sehingga seluruh aspek utama transaksi dan kejadian tidak dikendalikan hanya oleh satu orang | E60: SPIP | F60: - | G60: - | H60: =KK3.1!S156 -> 4 | I60: =KK3.2!N157 -> 3 | J60: =KK3.3!N156 -> 3 | K60: =KK3.4!N211 -> 3 | L60: =AVERAGE(H60:K60) -> 3.25 | N60: =IF($M$59="YA",$N$59,L60) -> 3.25
A61: 3.7 | B61: Otorisasi atas Transaksi dan Kejadian yang Penting | H61: =H62 -> 4 | I61: =I62 -> 3 | J61: =J62 -> 3 | K61: =K62 -> 3 | L61: =AVERAGE(H61:K61) -> 3.25 | M61: =KK4_PENALTI!C23 -> TIDAK | N61: =IF(M61="YA",KK4_PENALTI!D23,L61) -> 3.25
A62: 3.7 | C62: 1 | D62: Terdapat proses untuk memastikan transaksi dan kejadian penting hanya dapat diotorisasi ketika memenuhi persyaratan dan dilakukan oleh pihak yang memiliki kewenangan | E62: SPIP | F62: - | G62: - | H62: =KK3.1!S162 -> 4 | I62: =KK3.2!N163 -> 3 | J62: =KK3.3!N162 -> 3 | K62: =KK3.4!N217 -> 3 | L62: =AVERAGE(H62:K62) -> 3.25 | N62: =IF($M$61="YA",$N$61,L62) -> 3.25
A63: 3.8 | B63: Pencatatan yang Akurat dan Tepat Waktu atas Transaksi dan Kejadian | H63: =H64 -> 5 | I63: =I64 -> 4 | J63: =J64 -> 3 | K63: =K64 -> 4 | L63: =AVERAGE(H63:K63) -> 4 | M63: =KK4_PENALTI!C24 -> TIDAK | N63: =IF(M63="YA",KK4_PENALTI!D24,L63) -> 4
A64: 3.8 | C64: 1 | D64: Terdapat proses untuk memastikan transaksi telah diklasifikasikan dengan layak dan dikelompokkan dengan benar serta dicatat dengan segera sehingga relevan, bernilai, dan berguna bagi manajemen | E64: SPIP | F64: - | G64: - | H64: =KK3.1!S168 -> 5 | I64: =KK3.2!N169 -> 4 | J64: =KK3.3!N168 -> 3 | K64: =KK3.4!N223 -> 4 | L64: =AVERAGE(H64:K64) -> 4 | N64: =IF($M$63="YA",$N$63,L64) -> 4
A65: 3.9 | B65: Pembatasan Akses atas Sumber Daya dan Pencatatannya | H65: =H66 -> 3 | I65: =I66 -> 3 | J65: =J66 -> 4 | K65: =K66 -> 4 | L65: =AVERAGE(H65:K65) -> 3.5 | M65: =KK4_PENALTI!C25 -> TIDAK | N65: =IF(M65="YA",KK4_PENALTI!D25,L65) -> 3.5
A66: 3.9 | C66: 1 | D66: Terdapat pembatasan atas kesempatan dan hak untuk menggunakan, atau memperoleh sumber daya dan mengakses pencatatannya | E66: SPIP | F66: - | G66: - | H66: =KK3.1!S174 -> 3 | I66: =KK3.2!N175 -> 3 | J66: =KK3.3!N174 -> 4 | K66: =KK3.4!N229 -> 4 | L66: =AVERAGE(H66:K66) -> 3.5 | N66: =IF($M$65="YA",$N$65,L66) -> 3.5
A67: 3.10 | B67: Akuntabilitas terhadap Sumber Daya dan Pencatatannya | H67: =H68 -> 5 | I67: =I68 -> 3 | J67: =J68 -> 3 | K67: =K68 -> 4 | L67: =AVERAGE(H67:K67) -> 3.75 | M67: =KK4_PENALTI!C26 -> TIDAK | N67: =IF(M67="YA",KK4_PENALTI!D26,L67) -> 3.75
A68: 3.10 | C68: 1 | D68: Terdapat pertanggungjawaban seseorang atau unit organisasi dalam mengelola sumber daya yang diberikan/dikuasakan kepadanya dalam rangka pencapaian tujuan organisasi | E68: SPIP | F68: - | G68: - | H68: =KK3.1!S180 -> 5 | I68: =KK3.2!N181 -> 3 | J68: =KK3.3!N180 -> 3 | K68: =KK3.4!N235 -> 4 | L68: =AVERAGE(H68:K68) -> 3.75 | N68: =IF($M$67="YA",$N$67,L68) -> 3.75
A69: 3.11 | B69: Dokumentasi yang Baik atas SPI serta Transaksi dan Kejadian Penting | H69: =H70 -> 3 | I69: =I70 -> 4 | J69: =J70 -> 4 | K69: =K70 -> 3 | L69: =AVERAGE(H69:K69) -> 3.5 | M69: =KK4_PENALTI!C27 -> TIDAK | N69: =IF(M69="YA",KK4_PENALTI!D27,L69) -> 3.5
A70: 3.11 | C70: 1 | D70: Terdapat pengelolaan, pemeliharaan, dan pendokumentasian secara berkala yang mencakup seluruh SPI serta transaksi dan kejadian penting yang dilaksanakan secara lengkap dan akurat untuk memfasilitasi penelusuran transaksi, kejadian, dan informasi terkait | E70: SPIP | F70: - | G70: - | H70: =KK3.1!S186 -> 3 | I70: =KK3.2!N187 -> 4 | J70: =KK3.3!N186 -> 4 | K70: =KK3.4!N241 -> 3 | L70: =AVERAGE(H70:K70) -> 3.5 | N70: =IF($M$69="YA",$N$69,L70) -> 3.5
A71: 4.1 | B71: Informasi yang Relevan | H71: =AVERAGE(H72:H76) -> 3 | I71: =AVERAGE(I72:I76) -> 3 | J71: =AVERAGE(J72:J76) -> 3 | K71: =AVERAGE(K72:K76) -> 3.2 | L71: =AVERAGE(H71:K71) -> 3.05 | M71: =KK4_PENALTI!C29 -> TIDAK | N71: =IF(M71="YA",KK4_PENALTI!D29,L71) -> 3.05
A72: 4.1 | C72: 1 | D72: Tersedianya informasi yang relevan untuk kebutuhan internal dan eksternal. | E72: SPIP | F72: - | G72: - | H72: =KK3.1!S192 -> 3 | I72: =KK3.2!N193 -> 3 | J72: =KK3.3!N192 -> 3 | K72: =KK3.4!N247 -> 4 | L72: =AVERAGE(H72:K72) -> 3.25 | N72: =IF($M$71="YA",$N$71,L72) -> 3.25
A73: 4.1 | C73: 2 | D73: Pimpinan Instansi Pemerintah membangun sistem pengaduan | E73: SPIP | F73: MRI | G73: - | H73: =KK3.1!S197 -> 3 | I73: =KK3.2!N198 -> 3 | J73: =KK3.3!N197 -> 3 | K73: =KK3.4!N252 -> 3 | L73: =AVERAGE(H73:K73) -> 3 | N73: =IF($M$71="YA",$N$71,L73) -> 3 | P73: KEPEMIMPINAN
A74: 4.1 | C74: 3 | D74: Strategi dan kebijakan manajemen risiko telah dikomunikasikan. | E74: SPIP | F74: MRI | G74: - | H74: =KK3.1!S202 -> 3 | I74: =KK3.2!N203 -> 3 | J74: =KK3.3!N202 -> 3 | K74: =KK3.4!N257 -> 3 | L74: =AVERAGE(H74:K74) -> 3 | N74: =IF($M$71="YA",$N$71,L74) -> 3 | P74: PROSES
A75: 4.1 | C75: 4 | D75: Register risiko dan rencana tindak pengendalian telah dikomunikasikan ke pihak terkait | E75: SPIP | F75: MRI | G75: - | H75: =KK3.1!S207 -> 3 | I75: =KK3.2!N208 -> 3 | J75: =KK3.3!N207 -> 3 | K75: =KK3.4!N262 -> 3 | L75: =AVERAGE(H75:K75) -> 3 | N75: =IF($M$71="YA",$N$71,L75) -> 3 | P75: PROSES
C76: 5 | D76: Saluran pelaporan internal dikelola secara kredibel dalam menerima pelaporan dan memberikan perlindungan kepada pelapor sehingga kepedulian meningkat dan memberikan efek penggentar yang efektif. | E76: SPIP | F76: - | G76: IEPK | K76: =KK3.4!N267 -> 3 | L76: =AVERAGE(H76:K76) -> 3 | N76: =IF($M$71="YA",$N$71,L76) -> 3
A77: 4.2 | B77: Komunikasi yang Efektif | H77: =H78 -> 4 | I77: =I78 -> 2 | J77: =J78 -> 2 | K77: =K78 -> 4 | L77: =AVERAGE(H77:K77) -> 3 | M77: =KK4_PENALTI!C30 -> TIDAK | N77: =IF(M77="YA",KK4_PENALTI!D30,L77) -> 3
A78: 4.2 | C78: 1 | D78: Terlaksananya komunikasi yang efektif dengan internal dan eksternal | E78: SPIP | F78: - | G78: - | H78: =KK3.1!S213 -> 4 | I78: =KK3.2!N214 -> 2 | J78: =KK3.3!N213 -> 2 | K78: =KK3.4!N273 -> 4 | L78: =AVERAGE(H78:K78) -> 3 | N78: =IF($M$77="YA",$N$77,L78) -> 3
A79: 5.1 | B79: Pemantauan Berkelanjutan | H79: =AVERAGE(H80:H82) -> 3.3333333 | I79: =AVERAGE(I80:I82) -> 3 | J79: =AVERAGE(J80:J82) -> 3 | K79: =AVERAGE(K80:K82) -> 3 | L79: =AVERAGE(H79:K79) -> 3.0833333 | M79: =KK4_PENALTI!C32 -> TIDAK | N79: =IF(M79="YA",KK4_PENALTI!D32,L79) -> 3.0833333
A80: 5.1 | C80: 1 | D80: Pimpinan organisasi/penanggungjawab program dan kegiatan/penanggungjawab operasional mengevaluasi secara berkala pengendalian intern yang telah dilakukan dalam rangka mencapai tujuan organisasi. | E80: SPIP | F80: - | G80: - | H80: =KK3.1!S219 -> 4 | I80: =KK3.2!N220 -> 4 | J80: =KK3.3!N219 -> 4 | K80: =KK3.4!N279 -> 3 | L80: =AVERAGE(H80:K80) -> 3.75 | N80: =IF($M$79="YA",$N$79,L80) -> 3.75
A81: 5.1 | C81: 2 | D81: Proses manajemen risiko telah direviu | E81: SPIP | F81: MRI | G81: - | H81: =KK3.1!S224 -> 3 | I81: =KK3.2!N225 -> 2 | J81: =KK3.3!N224 -> 2 | K81: =KK3.4!N284 -> 3 | L81: =AVERAGE(H81:K81) -> 2.5 | N81: =IF($M$79="YA",$N$79,L81) -> 2.5 | P81: PROSES
A82: 5.1 | C82: 3 | D82: Pemantauan/monitoring terhadap risiko telah dilakukan | E82: SPIP | F82: MRI | G82: - | H82: =KK3.1!S229 -> 3 | I82: =KK3.2!N230 -> 3 | J82: =KK3.3!N229 -> 3 | K82: =KK3.4!N289 -> 3 | L82: =AVERAGE(H82:K82) -> 3 | N82: =IF($M$79="YA",$N$79,L82) -> 3 | P82: PROSES
A83: 5.2 | B83: Evaluasi Terpisah | H83: =AVERAGE(H84:H85) -> 3.5 | I83: =AVERAGE(I84:I85) -> 2.5 | J83: =AVERAGE(J84:J85) -> 2.5 | K83: =AVERAGE(K84:K85) -> 2 | L83: =AVERAGE(H83:K83) -> 2.625 | M83: =KK4_PENALTI!C33 -> TIDAK | N83: =IF(M83="YA",KK4_PENALTI!D33,L83) -> 2.625
A84: 5.2 | C84: 1 | D84: Evaluasi terpisah dilakukan oleh pegawai dengan keahlian tertentu yang disyaratkan dan dapat melibatkan APIP atau auditor eksternal untuk menilai kinerja sistem pengendalian intern, mengidentifikasi kelemahan pengendalian, menentukan penyebab dari kegagalan aktivitas pengendalian, serta pengaruhnya terhadap pencapaian tujuan instansi. | E84: SPIP | F84: - | G84: - | H84: =KK3.1!S235 -> 4 | I84: =KK3.2!N236 -> 3 | J84: =KK3.3!N235 -> 3 | K84: =KK3.4!N295 -> 2 | L84: =AVERAGE(H84:K84) -> 3 | N84: =IF($M$83="YA",$N$83,L84) -> 3
A85: 5.2 | C85: 2 | D85: Terdapat reviu independen terhadap proses manajemen risiko | E85: SPIP | F85: MRI | G85: - | H85: =KK3.1!S240 -> 3 | I85: =KK3.2!N241 -> 2 | J85: =KK3.3!N240 -> 2 | K85: =KK3.4!N300 -> 2 | L85: =AVERAGE(H85:K85) -> 2.25 | N85: =IF($M$83="YA",$N$83,L85) -> 2.25 | P85: PROSES

Sheet Uraian NIlai Setiap Unsur
A2: Kode | B2: Uraian Subunsur | C2: No | D2: Uraian Parameter | E2: 2E NILAI | F2: KEUANGAN NILAI | G2: ASET NILAI | H2: KETAATAN NILAI | I2: KESIMPULAN NILAI
A5: 1.1 | B5: Penegakan Integritas dan Nilai Etika | E5: 3 | F5: 5 | G5: 5 | H5: 3.375 | I5: =AVERAGE(E5:H5) -> 4.09375 | J5: =AVERAGE(I5:I21) -> 3.5585938
A6: 1.2 | B6: Komitmen terhadap Kompetensi | E6: 4 | F6: 3 | G6: 3 | H6: 4 | I6: =AVERAGE(E6:H6) -> 3.5
A7: 1.3 | B7: Kepemimpinan yang Kondusif | E7: =AVERAGE(E8:E11) -> 3.25 | F7: =AVERAGE(F8:F11) -> 3 | G7: =AVERAGE(G8:G11) -> 2.75 | H7: =AVERAGE(H8:H11) -> 3 | I7: =AVERAGE(E7:H7) -> 3
A8: 1.3 | C8: 1 | D8: Pimpinan organisasi menciptakan lingkungan kerja yang kondusif untuk pencapaian tujuan organisasi. | E8: 4 | F8: 4 | G8: 3 | H8: 3
A9: 1.3 | C9: 2 | D9: Pimpinan Instansi Pemerintah mengalokasikan sumber daya untuk penerapan manajemen risiko. | E9: 3 | F9: 3 | G9: 3 | H9: 3
A10: 1.3 | C10: 3 | D10: Pimpinan Instansi Pemerintah menggunakan informasi terkait risiko dalam pengambilan keputusan | E10: 3 | F10: 2 | G10: 2 | H10: 3 | M10: Lingkungan Pengendalian | N10: =J5 -> 3.5585938
A11: 1.3 | C11: 4 | D11: Pimpinan Instansi Pemerintah mendorong penerapan manajemen risiko, melalui Penggunaan kinerja penerapan manajemen risiko sebagai indikator penilaian kinerja | E11: 3 | F11: 3 | G11: 3 | H11: 3 | M11: Penilain Risiko | N11: =J22 -> 2.8916667
A12: 1.4 | B12: Struktur Organisasi Sesuai Kebutuhan | E12: 4 | F12: 4 | G12: 4 | H12: 3 | I12: =AVERAGE(E12:H12) -> 3.75 | M12: Kegiatan Pengendalian | N12: =J32 -> 3.5681818
A13: 1.5 | B13: Pendelegasian Wewenang dan Tanggung Jawab yang Tepat | E13: 5 | F13: 5 | G13: 5 | H13: 4 | I13: =AVERAGE(E13:H13) -> 4.75 | M13: Informasi dan Komunikasi | N13: =J43 -> 3.03125
A14: 1.6 | B14: Penyusunan dan Penerapan Kebijakan yang Sehat tentang Pembinaan SDM | E14: =AVERAGE(E15:E17) -> 3 | F14: =AVERAGE(F15:F17) -> 2 | G14: =AVERAGE(G15:G17) -> 3 | H14: =AVERAGE(H15:H17) -> 3 | I14: =AVERAGE(E14:H14) -> 2.75 | M14: Pemantauan | N14: =J49 -> 2.8541667
A15: 1.6 | C15: 1 | D15: Penerapan kebijakan manajemen dan praktik pembinaan SDM sehingga dapat digunakan secara maksimal untuk mencapai tujuan organisasi | E15: 3 | F15: 2 | G15: 5 | H15: 3
A16: 1.6 | C16: 2 | D16: Pegawai telah mendapatkan fasilitas untuk meningkatkan kompetensi dan keterampilan terkait manajemen risiko | E16: 3 | F16: 2 | G16: 2 | H16: 3
A17: 1.6 | C17: 3 | D17: Pegawai memiliki kesadaran terkait manajemen risiko | E17: 3 | F17: 2 | G17: 2 | H17: 3
A18: 1.7 | B18: Perwujudan Peran APIP yang Efektif | E18: 3 | F18: 3 | G18: 3 | H18: 3 | I18: =AVERAGE(E18:H18) -> 3
A19: 1.8 | B19: Hubungan Kerja yang Baik dengan Instansi Pemerintah Terkait | E19: =AVERAGE(E20:E21) -> 3 | F19: =AVERAGE(F20:F21) -> 4 | G19: =AVERAGE(G20:G21) -> 4 | H19: =AVERAGE(H20:H21) -> 3.5 | I19: =AVERAGE(E19:H19) -> 3.625
A20: 1.8 | C20: 1 | D20: Pimpinan organisasi menjalin hubungan kerja yang baik (kemitraan) dengan instansi lain terkait dengan upaya pencapaian tujuan organisasi. | E20: 3 | F20: 5 | G20: 5 | H20: 4
A21: 1.8 | C21: 2 | D21: Dalam rangka menciptakan hubungan kerja yang baik, instansi Pemerintah telah mengidentifikasi, menilai, dan mengelola risiko (termasuk implikasi dari transfer risiko) terkait kemitraan | E21: 3 | F21: 3 | G21: 3 | H21: 3
A22: 2.1 | B22: Identifikasi Risiko | E22: =AVERAGE(E23:E25) -> 4 | F22: =AVERAGE(F23:F25) -> 2.3333333 | G22: =AVERAGE(G23:G25) -> 2.3333333 | H22: =AVERAGE(H23:H25) -> 2.6666667 | I22: =AVERAGE(E22:H22) -> 2.8333333 | J22: =AVERAGE(I22:I31) -> 2.8916667
A23: 2.1 | C23: 1 | D23: Pemerintah Daerah telah memiliki Kebijakan Manajemen Risiko. | E23: 4 | F23: 2 | G23: 2 | H23: 4
A24: 2.1 | C24: 2 | D24: Risiko telah teridentifikasi dan dituangkan dalam register risiko | E24: 4 | F24: 3 | G24: 3 | H24: 2
A25: 2.1 | C25: 3 | D25: Proses manajemen risiko telah melekat pada proses bisnis Instansi Pemerintah | E25: 4 | F25: 2 | G25: 2 | H25: 2
A26: 2.2 | B26: Analisis Risiko | E26: =AVERAGE(E27:E31) -> 3.6 | F26: =AVERAGE(F27:F31) -> 2.6 | G26: =AVERAGE(G27:G31) -> 2.6 | H26: =AVERAGE(H27:H31) -> 3 | I26: =AVERAGE(E26:H26) -> 2.95
A27: 2.2 | C27: 1 | D27: Seluruh risiko telah dianalisis dampak dan tingkat keterjadiannya | E27: 4 | F27: 3 | G27: 3 | H27: 3
A28: 2.2 | C28: 2 | D28: Instansi pemerintah telah menentukan prioritas risiko | E28: 4 | F28: 3 | G28: 3 | H28: 4
A29: 2.2 | C29: 3 | D29: Instansi Pemerintah telah menentukan rencana tindak pengendalian | E29: 4 | F29: 3 | G29: 3 | H29: 3
A30: 2.2 | C30: 4 | D30: Tindak pengendalian telah diimplementasikan | E30: 3 | F30: 3 | G30: 3 | H30: 3
A31: 2.2 | C31: 5 | D31: Tindak pengendalian efektif menurunkan risiko | E31: 3 | F31: 1 | G31: 1 | H31: 2
A32: 3.1 | B32: Reviu atas Kinerja | E32: 3 | F32: 3 | G32: 3 | H32: 3 | I32: =AVERAGE(E32:H32) -> 3 | J32: =AVERAGE(I32:I42) -> 3.5681818
A33: 3.2 | B33: Pembinaan SDM | E33: 4 | F33: 5 | G33: 4 | H33: 3 | I33: =AVERAGE(E33:H33) -> 4
A34: 3.3 | B34: Pengendalian atas Pengelolaan Sistem Informasi | E34: 4 | F34: 3 | G34: 3 | H34: 4 | I34: =AVERAGE(E34:H34) -> 3.5
A35: 3.4 | B35: Pengendalian Fisik atas Aset | E35: 4 | F35: 4 | G35: 5 | H35: 3 | I35: =AVERAGE(E35:H35) -> 4
A36: 3.5 | B36: Penetapan dan Reviu atas Indikator dan Ukuran Kinerja | E36: 4 | F36: 3 | G36: 3 | H36: 4 | I36: =AVERAGE(E36:H36) -> 3.5
A37: 3.6 | B37: Pemisahan Fungsi | E37: 4 | F37: 3 | G37: 3 | H37: 3 | I37: =AVERAGE(E37:H37) -> 3.25
A38: 3.7 | B38: Otorisasi atas Transaksi dan Kejadian yang Penting | E38: 4 | F38: 3 | G38: 3 | H38: 3 | I38: =AVERAGE(E38:H38) -> 3.25
A39: 3.8 | B39: Pencatatan yang Akurat dan Tepat Waktu atas Transaksi dan Kejadian | E39: 5 | F39: 4 | G39: 3 | H39: 4 | I39: =AVERAGE(E39:H39) -> 4
A40: 3.9 | B40: Pembatasan Akses atas Sumber Daya dan Pencatatannya | E40: 3 | F40: 3 | G40: 4 | H40: 4 | I40: =AVERAGE(E40:H40) -> 3.5
A41: 3.10 | B41: Akuntabilitas terhadap Sumber Daya dan Pencatatannya | E41: 5 | F41: 3 | G41: 3 | H41: 4 | I41: =AVERAGE(E41:H41) -> 3.75
A42: 3.11 | B42: Dokumentasi yang Baik atas SPI serta Transaksi dan Kejadian Penting | E42: 3 | F42: 4 | G42: 4 | H42: 3 | I42: =AVERAGE(E42:H42) -> 3.5
A43: 4.1 | B43: Informasi yang Relevan | E43: =AVERAGE(E44:E47) -> 3 | F43: =AVERAGE(F44:F47) -> 3 | G43: =AVERAGE(G44:G47) -> 3 | H43: =AVERAGE(H44:H47) -> 3.25 | I43: =AVERAGE(E43:H43) -> 3.0625 | J43: =AVERAGE(I43:I48) -> 3.03125
A44: 4.1 | C44: 1 | D44: Tersedianya informasi yang relevan untuk kebutuhan internal dan eksternal. | E44: 3 | F44: 3 | G44: 3 | H44: 4
A45: 4.1 | C45: 2 | D45: Pimpinan Instansi Pemerintah membangun sistem pengaduan | E45: 3 | F45: 3 | G45: 3 | H45: 3
A46: 4.1 | C46: 3 | D46: Strategi dan kebijakan manajemen risiko telah dikomunikasikan. | E46: 3 | F46: 3 | G46: 3 | H46: 3
A47: 4.1 | C47: 4 | D47: Register risiko dan rencana tindak pengendalian telah dikomunikasikan ke pihak terkait | E47: 3 | F47: 3 | G47: 3 | H47: 3
A48: 4.2 | B48: Komunikasi yang Efektif | E48: 4 | F48: 2 | G48: 2 | H48: 4 | I48: =AVERAGE(E48:H48) -> 3
A49: 5.1 | B49: Pemantauan Berkelanjutan | E49: =AVERAGE(E50:E52) -> 3.3333333 | F49: =AVERAGE(F50:F52) -> 3 | G49: =AVERAGE(G50:G52) -> 3 | H49: =AVERAGE(H50:H52) -> 3 | I49: =AVERAGE(E49:H49) -> 3.0833333 | J49: =AVERAGE(I49:I53) -> 2.8541667
A50: 5.1 | C50: 1 | D50: Pimpinan organisasi/penanggungjawab program dan kegiatan/penanggungjawab operasional mengevaluasi secara berkala pengendalian intern yang telah dilakukan dalam rangka mencapai tujuan organisasi. | E50: 4 | F50: 4 | G50: 4 | H50: 3
A51: 5.1 | C51: 2 | D51: Proses manajemen risiko telah direviu | E51: 3 | F51: 2 | G51: 2 | H51: 3
A52: 5.1 | C52: 3 | D52: Pemantauan/monitoring terhadap risiko telah dilakukan | E52: 3 | F52: 3 | G52: 3 | H52: 3
A53: 5.2 | B53: Evaluasi Terpisah | E53: =AVERAGE(E54:E55) -> 3.5 | F53: =AVERAGE(F54:F55) -> 2.5 | G53: =AVERAGE(G54:G55) -> 2.5 | H53: =AVERAGE(H54:H55) -> 2 | I53: =AVERAGE(E53:H53) -> 2.625
A54: 5.2 | C54: 1 | D54: Evaluasi terpisah dilakukan oleh pegawai dengan keahlian tertentu yang disyaratkan dan dapat melibatkan APIP atau auditor eksternal untuk menilai kinerja sistem pengendalian intern, mengidentifikasi kelemahan pengendalian, menentukan penyebab dari kegagalan aktivitas pengendalian, serta pengaruhnya terhadap pencapaian tujuan instansi. | E54: 4 | F54: 3 | G54: 3 | H54: 2
A55: 5.2 | C55: 2 | D55: Terdapat reviu independen terhadap proses manajemen risiko | E55: 3 | F55: 2 | G55: 2 | H55: 2

Sheet KKlead I KL
A1: PENJAMINAN KUALITAS HASIL PENILAIAN MANDIRI MATURITAS PENYELENGGARAAN SPIP TERINTEGRASI PEMERINTAH DAERAH … Periode Penilaian sampai dengan 30 Juni 20XX
A2: KERTAS KERJA PENILAIAN PENETAPAN TUJUAN KK LEAD I - PENETAPAN TUJUAN | E2: Indeks KK No. Disusun oleh/Tanggal Direviu oleh/Tanggal Disetujui oleh/Tanggal | H2: : : : :
A4: A. Kualitas Sasaran Strategis (KK 1)
A5: No | B5: Uraian | E5: KK | F5: Kolom | G5: Bobot | H5: Skor | I5: Skor Akhir
A7: 1 | B7: Sasaran Strategis | G7: 0.5 | H7: =AVERAGE(H8:H12) -> 0.9 | I7: =G7*H7 -> 0.45
B8: a | C8: Sasaran strategis berorientasi hasil | E8: 1.1 | F8: K | H8: ='KKE 1.1 SASTRA PEMDA'!K26 -> 0.94444444
B9: b | C9: Sasaran strategis relevan menggambarkan mandat | E9: 1.1 | F9: L | H9: ='KKE 1.1 SASTRA PEMDA'!L26 -> 1
B10: c | C10: Indikator kinerja tepat | E10: 1.1 | F10: M | H10: ='KKE 1.1 SASTRA PEMDA'!M26 -> 0.72222222
B11: d | C11: Indikator kinerja cukup untuk mengukur sasaran | E11: 1.1 | F11: N | H11: ='KKE 1.1 SASTRA PEMDA'!N26 -> 1
B12: e | C12: Target kinerja tepat | E12: 1.1 | F12: O | H12: ='KKE 1.1 SASTRA PEMDA'!O26 -> 0.83333333
A13: 2 | B13: Sasaran Program | G13: 0.5 | H13: =AVERAGE(H14:H18) -> 0.896 | I13: =G13*H13 -> 0.448
B14: a | C14: Sasaran Program berorientasi hasil | E14: 1.2 | F14: O | H14: ='KKE 1.2 SASARAN OPD'!N57 -> 1
B15: b | C15: Sasaran program relevan dengan sasaran strategis dan menggambarkan tugas dan fungsi | E15: 1.2 | F15: P | H15: ='KKE 1.2 SASARAN OPD'!O57 -> 0.78
B16: c | C16: Indikator kinerja tepat | E16: 1.2 | F16: Q | H16: ='KKE 1.2 SASARAN OPD'!P57 -> 0.94
B17: d | C17: Indikator kinerja cukup untuk mengukur sasaran | E17: 1.2 | F17: R | H17: ='KKE 1.2 SASARAN OPD'!Q57 -> 0.84
B18: e | C18: Target kinerja tepat | E18: 1.2 | F18: S | H18: ='KKE 1.2 SASARAN OPD'!R57 -> 0.92
C19: Skor Akhir | I19: =I7+I13 -> 0.898
C20: Level | I20: =(IF(I19>=90%,"5",IF(I19>=80%,"4",IF(I19>=70%,"3",IF(I19>=60%,"2","1")))))*1 -> 4
A23: B. Kualitas Strategi Pencapaian Sasaran Strategis (KK 2)
A24: No | B24: Uraian | E24: KK | F24: Kolom | G24: Bobot | H24: Skor | I24: Skor Akhir
A26: 1 | B26: Kualitas Sasaran Kegiatan | G26: 0.5 | H26: =AVERAGE(H27:H31) -> 0.94901961 | I26: =G26*H26 -> 0.4745098
B27: a | C27: Sasaran kegiatan berorientasi hasil | E27: 2.1 | F27: S | H27: ='KKE 2.1 SASKEG'!R127 -> 0.98039216
B28: b | C28: Sasaran kegiatan relevan dengan sasaran program dan menggambarkan tugas dan fungsi | E28: 2.1 | F28: T | H28: ='KKE 2.1 SASKEG'!S127 -> 0.98039216
B29: c | C29: Indikator kinerja tepat | E29: 2.1 | F29: U | H29: ='KKE 2.1 SASKEG'!T127 -> 0.91176471
B30: d | C30: Indikator kinerja cukup untuk mengukur sasaran | E30: 2.1 | F30: V | H30: ='KKE 2.1 SASKEG'!U127 -> 0.94117647
B31: e | C31: Target kinerja tepat | E31: 2.1 | F31: W | H31: ='KKE 2.1 SASKEG'!V127 -> 0.93137255
A32: 2 | B32: Kualitas Rincian Output | G32: 0.5 | H32: =AVERAGE(H33:H37) -> 1.1057143 | I32: =G32*H32 -> 0.55285714
B33: a | C33: Rincian Output relevan dengan sasaran kegiatan | E33: 2.2 | F33: U | H33: ='KK 2.2 RO'!T210 -> 1.0857143
B34: b | C34: Indikator kinerja tepat | E34: 2.2 | F34: V | H34: ='KK 2.2 RO'!U210 -> 1.0857143
B35: c | C35: Indikator kinerja cukup untuk mengukur sasaran | E35: 2.2 | F35: W | H35: ='KK 2.2 RO'!V210 -> 1.1257143
B36: d | C36: Target kinerja tepat | E36: 2.2 | F36: X | H36: ='KK 2.2 RO'!W210 -> 1.1257143
C43: Skor Akhir | I43: =I26+I32+I38 -> 1.0273669
C44: Level | I44: =(IF(I43>=90%,"5",IF(I43>=80%,"4",IF(I43>=70%,"3",IF(I43>=60%,"2","1")))))*1 -> 5
A46: Gradasi Level
C47: 1 | D47: sampai dengan 60%
C48: 2 | D48: lebih besar dari 60% s.d. 70%
C49: 3 | D49: lebih besar dari 70% s.d. 80%
C50: 4 | D50: lebih besar dari 80% s.d. 90%
C51: 5 | D51: lebih besar dari 90%

Sheet KKE 1.1 SASTRA PEMDA
A1: PENJAMINAN KUALITAS HASIL PENILAIAN MANDIRI MATURITAS PENYELENGGARAAN SPIP TERINTEGRASI KEMENTERIAN KOMUNIKASI DAN INFORMATIKA Periode Penilaian sampai dengan 30 Juni 2025
A2: KK 1.1 - PENILAIAN PENETAPAN TUJUAN - SASARAN STRATEGIS KEMENTERIAN/LEMBAGA
A3: NO | B3: URAIAN SASARAN STRATEGIS | C3: URAIAN INDIKATOR KINERJA SASARAN | D3: TARGET KINERJA | E3: SASARAN STRATEGIS | K3: PENJAMINAN KUALITAS
E4: SASTRA BERORIENTASI HASIL | F4: SASTRA RELEVAN DAN MENGGAMBARKAN MANDAT | G4: INDIKATOR KINERJA TEPAT | H4: UJI KECUKUPAN INDIKATOR | I4: TARGET KINERJA TEPAT | J4: KETERANGAN | K4: SASTRA BERORIENTASI HASIL | L4: SASTRA RELEVAN DAN MENGGAMBARKAN MANDAT | M4: INDIKATOR KINERJA TEPAT | N4: UJI KECUKUPAN INDIKATOR | O4: TARGET KINERJA TEPAT | P4: KETERANGAN
A5: 1 | B5: =A5+1 -> 2 | C5: =B5+1 -> 3 | D5: =C5+1 -> 4 | E5: =D5+1 -> 5 | F5: =E5+1 -> 6 | G5: =F5+1 -> 7 | H5: =G5+1 -> 8 | I5: =H5+1 -> 9 | ... P5: =O5+1 -> 16
A6: 1 | B6: Mempercepat Penyediaan Konektivitas Broadband Inklusif, Berkualitas, dan Terjangkau | C6: Skor Indeks Transformasi Digital Nasional Pilar Jaringan dan Infrastruktur | D6: 56,08 Nilai | E6: Y | F6: Y | G6: Y | H6: Y | I6: Y | J6: Persentase (%) kecamatan yang terjangkau infrastruktur jaringan serat optik broadband (Kumulatif) merupakan indikator bersifat outcome. Output dari IKSS ini diantaranya Penyediaan Fiber Optik pada Daerah (Kecamatan) di Kawasan Prioritas | K6: Y | L6: Y | M6: Y | N6: Y | O6: Y
A7: 2 | B7: Mempercepat Penyediaan Sistem dan Jaringan Komunikasi untuk Layanan Khusus Secara Nasional | C7: Persentase Kab/Kota yang memanfaatkan sistem penyampaian informasi kebencanaan dan kegawatdaruratan | D7: 33 Persen | E7: Y | F7: Y | G7: Y | H7: Y | I7: Y | J7: Akan diperbaiki dalam Renstra Kominfo periode berikutnya 2025-2029, mengingat Renstra tahun berjalan hanya dapat diperbaiki jika terdapat beberapa kondisi seperti kebijakan pemerintah (paling rendah dituangkan dalam Perpres), perubahan SOTK yang dituangkan dalam Perpres dan Kebijakan Nasional Perencanaan dan Penganggaran (RSPP) | K7: Y | L7: Y | M7: Y | N7: Y | O7: Y
A8: 3 | B8: Meningkatnya Pertumbuhan Ekonomi dari Pengembangan Ekosistem Digital Nasional | C8: Indeks TDN Pilar Bisnis | D8: 40,38 Nilai | E8: Y | F8: Y | G8: Y | H8: Y | I8: Y | J8: Persentase (%) rumah tangga terlayani jaringan internet akses fixed broadband terhadap total rumah Tangga (Kumulatif) merupakan indiaktor bersifat outcome. Output dari IKSS ini diantaranya | K8: Y | L8: Y | M8: T | N8: Y | O8: Y | P8: Indikator belum menunjukan efek keberlanjutan , masih menujukan impact jangan pendek
A9: 4 | B9: Mengakselerasi Kualitas dan Produktivitas Masyarakat Digital | C9: Indeks Masyarakat Digital Indonesia (IMDI) | D9: 45,23 Nilai | E9: Y | F9: Y | G9: Y | H9: Y | I9: Y | J9: Indikator ini terdapat dalam RPJMN Tahun 2020-2024. IKSS pada Renstra mengacu pada RPJMN sehingga untuk perbaikan indikator perlu dilakukan koordinasi dengan Bappenas untuk periode RPJMN berikutnya, mengingat tahun Tahun 2024 merupakan akhir periode dari RPJMN Tahun 2020-2024. | K9: Y | L9: Y | M9: Y | N9: Y | O9: Y
A10: 5 | B10: Mempercepat pemanfaatan teknologi untuk pemerintahan digital yang terpadu dan citizen centric | C10: Indeks Transformasi Digital Nasional Pilar Pemerintah | D10: 54,05 Nilai | E10: Y | F10: Y | G10: Y | H10: Y | I10: Y | J10: Memenuhi Kriteria | K10: Y | L10: Y | M10: Y | N10: Y | O10: Y
A11: 6 | B11: Menciptakan ruang digital yang aman dan berdaulat | C11: Indeks Ruang Digital Kondusif | D11: 3 Nilai | E11: Y | F11: Y | G11: Y | H11: Y | I11: Y | J11: Memenuhi Kriteria | K11: Y | L11: Y | M11: Y | N11: Y | O11: Y
A12: 7 | B12: Meningkatnya kualitas pengelolaan layanan publik Kemenkomdigi | C12: Indeks Kepuasan masyarakat terhadap layanan publik Kemenkomdigi | D12: >3.5 Nilai | E12: Y | F12: Y | G12: Y | H12: Y | I12: Y | J12: Persentase (%) jangkauan populasi penyiaran digital (Kumulatif) merupakan indikator bersifat outcome. Output dari IKSS ini diantaranya penyediaan Set Top Box (STB), pembangunan menara Transmitter, revitalisasi perangkat penyiaran digital LPP TVRI, Penyiapan Regulasi dll. | K12: Y | L12: Y | M12: T | N12: Y | O12: Y
A13: 8 | B13: Meningkatnya efektivitas penyelenggaraan informasi dan komunikasi publik | C13: Indeks Komunikasi Pembangunan dan Informasi Publik (KPIP) | D13: 71 Nilai | E13: Y | F13: Y | G13: Y | H13: Y | I13: Y | J13: Persentase (%) cakupan layanan pos (Kumulatif) merupakan indiaktor bersifat outcome, Output dari IKSS ini diantaranya penyusunan Kebijakan Pemberian Subsidi Operasional Pada Layanan Pos Universal | K13: Y | L13: Y | M13: Y | N13: Y | O13: Y
A14: 9 | B14: Mewujudkan Transformasi Internal Manajemen adaptif dan resilien | C14: Indeks Reformasi Birokrasi Kemenkomdigi | D14: 87 Nilai | E14: Y | F14: Y | G14: Y | H14: Y | I14: Y | J14: Akan diperbaiki dalam Renstra Kominfo periode berikutnya 2025-2029, mengingat Renstra tahun berjalan hanya dapat diperbaiki jika terdapat beberapa kondisi seperti kebijakan pemerintah (paling rendah dituangkan dalam Perpres), perubahan SOTK yang dituangkan dalam Perpres dan Kebijakan Nasional Perencanaan dan Penganggaran (RSPP) | K14: Y | L14: Y | M14: Y | N14: Y | O14: Y
A15: 10 | B15: Mempercepat Penyediaan Konektivitas Broadband Inklusif, Berkualitas, dan Terjangkau | C15: Indeks Pembangunan TIK (IPTIK) Nasional | D15: 6,10 Nilai | E15: Y | F15: Y | G15: Y | H15: Y | I15: Y | J15: Memenuhi Kriteria | K15: Y | L15: Y | M15: Y | N15: Y | O15: Y | P15: Indikator kinerja baru mengukur pemanfaatan spektrum frekuensi radio, tetapi tidak mengukur aspek kualitas pengelolaan layanan publik. Untuk sepenuhnya selaras dengan sasaran strategis, perlu ada indikator tambahan yang mengukur peningkatan kualitas layanan publik di bidang pos, telekomunikasi, dan informatika
A16: 11 | B16: Meningkatnya Pertumbuhan Ekonomi dari Pengembangan Ekosistem Digital Nasional | C16: Kontribusi Komdigi pada Nilai Ekonomi Digital | D16: 137.888.51 Rp | E16: Y | F16: Y | G16: Y | H16: Y | I16: Y | J16: Indikator ini terdapat dalam RPJMN Tahun 2020-2024. IKSS pada Renstra mengacu pada RPJMN sehingga untuk perbaikan indikator perlu dilakukan koordinasi dengan Bappenas untuk periode RPJMN berikutnya, mengingat tahun 2024 merupakan akhir periode dari RPJMN Tahun 2020-2024. | K16: Y | L16: Y | M16: Y | N16: Y | O16: Y
A17: 12 | B17: Mengakselerasi Kualitas dan Produktivitas Masyarakat Digital | C17: Indeks TDN pilar Masyarakat | D17: 52,08 Nilai | E17: Y | F17: Y | G17: Y | H17: Y | I17: Y | J17: Indikator ini terdapat dalam RPJMN Tahun 2020-2024 tagging PN 7 (Memperkuat Stabilitas Polhankam dan Transformasi pelayanan Publik). Seharusnya indikator ini masuk ke dalam PN 3 (Meningkatkan Sumber Daya Manusia Berkualitas dan Berdaya Saing) terkait Peningkatan Sumber Daya Manusia dan Daya Saing. Untuk perbaikan tagging indikator perlu dilakukan koordinasi dengan Bappenas untuk periode RPJMN berikutnya, mengingat tahun 2024 merupakan akhir periode dari RPJMN Tahun 2020-2024. | K17: Y | L17: Y | M17: T | N17: Y | O17: Y | P17: Indikator kinerja masih bersifat umum
A18: 13 | B18: Mewujudkan Transformasi Internal Manajemen adaptif dan resilien | C18: Indeks Opini Badan Pemeriksaan Keuangan (BPK) atas Laporan Keuangan | D18: WTP Nilai | E18: Y | F18: Y | G18: Y | H18: Y | I18: Y | J18: Memenuhi Kriteria | K18: Y | L18: Y | M18: T | N18: Y | O18: Y | P18: indikator kinerja masih belum menggambarkan transformasi bersifat internal karena aspek resiliensi cakupannya bukan hanya laporan keuangan akan tetapi cakupannya sangat luas seperti Tata Kelola, SDM, Teknologi dan infrastruktur digital dsb
A19: 14 | B19: Mempercepat Penyediaan Konektivitas Broadband Inklusif, Berkualitas, dan Terjangkau | C19: Peningkatan kota/kab yang memiliki internet broadband berkecepatan giga (min. 1 Gbps) | D19: TBD Nilai | E19: Y | F19: Y | G19: Y | H19: Y | I19: T | J19: Target Kinerja masih dalam tahap diskusi dengan Ditjen Terkait | K19: Y | L19: Y | M19: Y | N19: Y | O19: T
A20: 15 | B20: Meningkatnya Pertumbuhan Ekonomi dari Pengembangan Ekosistem Digital Nasional | C20: Kontribusi sektor informasi dan komunikasi terhadap PDB | D20: 4,3 Persen | E20: Y | F20: Y | G20: Y | H20: Y | I20: Y | J20: Memenuhi Kriteria | K20: Y | L20: Y | M20: Y | N20: Y | O20: Y
A21: 16 | B21: Mengakselerasi Kualitas dan Produktivitas Masyarakat Digital | C21: Peningkatan Tenaga Kerja Sektor TIK (kumulatif) (%) | D21: 1310 Persen | E21: Y | F21: Y | G21: Y | H21: Y | I21: T | J21: Target direvisi menjadi sebesar 3,2% | K21: Y | L21: Y | M21: Y | N21: Y | O21: T
A22: 17 | B22: Mewujudkan Transformasi Internal Manajemen adaptif dan resilien | C22: Tingkat Dampak Kerja Sama Internasional terhadap Kolaborasi Pemangku Kebijakan Digital | D22: 4 Nilai | E22: Y | F22: Y | G22: Y | H22: Y | I22: Y | J22: Memenuhi Kriteria | K22: Y | L22: Y | M22: Y | N22: Y | O22: Y
A23: 18 | B23: Mengakselerasi Kualitas dan Produktivitas Masyarakat Digital | C23: Tingkat ASN yang memiliki kompetensi digital | D23: TBD Nilai | E23: Y | F23: Y | G23: Y | H23: Y | I23: T | J23: Target masih didiskusikan dengan BPSDM | K23: T | L23: Y | M23: T | N23: Y | O23: T | P23: belum menunjukan indikator yang efektif
E24: =COUNTIF(E6:E23,"Y") -> 18 | F24: =COUNTIF(F6:F23,"Y") -> 18 | G24: =COUNTIF(G6:G23,"Y") -> 18 | H24: =COUNTIF(H6:H23,"Y") -> 18 | I24: =COUNTIF(I6:I23,"Y") -> 15 | K24: =COUNTIF(K6:K23,"Y") -> 17 | L24: =COUNTIF(L6:L23,"Y") -> 18 | M24: =COUNTIF(M6:M23,"Y") -> 13 | N24: =COUNTIF(N6:N23,"Y") -> 18 | O24: =COUNTIF(O6:O23,"Y") -> 15
E25: =COUNTA(E6:E23) -> 18 | F25: =COUNTA(F6:F23) -> 18 | G25: =COUNTA(G6:G23) -> 18 | H25: =COUNTA(H6:H23) -> 18 | I25: =COUNTA(I6:I23) -> 18 | K25: =COUNTA(K6:K23) -> 18 | L25: =COUNTA(L6:L23) -> 18 | M25: =COUNTA(M6:M23) -> 18 | N25: =COUNTA(N6:N23) -> 18 | O25: =COUNTA(O6:O23) -> 18
E26: =E24/E25 -> 1 | F26: =F24/F25 -> 1 | G26: =G24/G25 -> 1 | H26: =H24/H25 -> 1 | I26: =I24/I25 -> 0.83333333 | K26: =K24/K25 -> 0.94444444 | L26: =L24/L25 -> 1 | M26: =M24/M25 -> 0.72222222 | N26: =N24/N25 -> 1 | O26: =O24/O25 -> 0.83333333

Sheet KKE 1.2 SASARAN OPD
A1: PENILAIAN MANDIRI MATURITAS PENYELENGGARAAN SPIP Kementerian Komunikasi dan Digital RI Periode penilaian 01 Juli 2024 s.d 30 Juni 2025
A2: KK 1.2 - PENILAIAN PENETAPAN TUJUAN - SASARAN PROGRAM KEMENTERIAN LEMBAGA
A3: No | B3: SASARAN STRATEGIS | D3: KUALITAS SASARAN PROGRAM | M3: Keterangan | N3: PENJAMINAN KUALITAS
B4: URAIAN SASARAN STRATEGIS | C4: SASTRA RELEVAN DAN MENGGAMBARKAN MANDAT | D4: NAMA PROGRAM | E4: URAIAN SASARAN PROGRAM | F4: INDIKATOR KINERJA SASARAN | G4: TARGET KINERJA | H4: SASARAN PROGRAM BERORIENTASI HASIL | I4: SASPRO RELEVAN DENGAN SASTRA DAN MENGGAMBARKAN TUGAS DAN FUNGSI | J4: INDIKATOR KINERJA TEPAT | K4: UJI KECUKUPAN INDIKATOR | L4: TARGET KINERJA TEPAT | N4: SASARAN OPD BERORIENTASI HASIL | O4: SASTRA OPD RELEVAN DAN MENGGAMBARKAN MANDAT | P4: INDIKATOR KINERJA TEPAT | Q4: UJI KECUKUPAN INDIKATOR | R4: TARGET KINERJA TEPAT | S4: KETERANGAN
A5: 1 | B5: Mempercepat Penyediaan Konektivitas Broadband Inklusif, Berkualitas, dan Terjangkau | C5: Y | D5: Program Pengembangan dan Penguatan Infrastruktur Digital | E5: Meningkatnya Kualitas Internet Broadband Nasional | F5: Rata-rata kecepatan internet mobile broadband di wilayah Indonesia | G5: 45 Mbps | H5: Y | I5: Y | J5: Y | K5: Y | L5: Y | M5: - | N5: Y | O5: Y | P5: Y | Q5: Y | R5: Y
A6: 2 | B6: Mempercepat Penyediaan Konektivitas Broadband Inklusif, Berkualitas, dan Terjangkau | C6: Y | D6: Program Pengembangan dan Penguatan Infrastruktur Digital | E6: Meningkatnya Kualitas Internet Broadband Nasional | F6: Kecepatan Internet Jaringan Pita Lebar Tetap (Fixed Broadband) | G6: 32 Mbps | H6: Y | I6: Y | J6: Y | K6: Y | L6: Y | M6: - | N6: Y | O6: Y | P6: Y | Q6: Y | R6: Y
A7: 3 | B7: Mempercepat Penyediaan Konektivitas Broadband Inklusif, Berkualitas, dan Terjangkau | C7: Y | D7: Program Pengembangan dan Penguatan Infrastruktur Digital | E7: Meningkatnya Kualitas Internet Broadband Nasional | F7: Persentase (%) Penanganan Gangguan Spektrum Frekuensi Radio (SFR) | G7: 95 Persen | H7: Y | I7: Y | J7: Y | K7: Y | L7: Y | M7: - | N7: Y | O7: Y | P7: Y | Q7: T | R7: Y | S7: belum menunjukan aspek kualitas dan kuantitas
A8: 4 | B8: Mempercepat Penyediaan Konektivitas Broadband Inklusif, Berkualitas, dan Terjangkau | C8: Y | D8: Program Pengembangan dan Penguatan Infrastruktur Digital | E8: Meningkatnya Kualitas Internet Broadband Nasional | F8: Persentase (%) Tingkat Kepatuhan Standar Teknis Alat dan /atau Perangkat Telekomunikasi dan Digital | G8: 75 persen | H8: Y | I8: Y | J8: Y | K8: Y | L8: Y | M8: - | N8: Y | O8: Y | P8: Y | Q8: Y | R8: Y
A9: 5 | B9: Mempercepat Penyediaan Konektivitas Broadband Inklusif, Berkualitas, dan Terjangkau | C9: Y | D9: Program Pengembangan dan Penguatan Infrastruktur Digital | E9: Meningkatnya Kualitas Internet Broadband Nasional | F9: Persentase (%) Tersedianya Layanan Akses Internet Pita Lebar Dengan Kecepatan yang Lebih Tinggi Menggunakan Spektrum Frekuensi Radio (SFR) | G9: 100 Persen | H9: Y | I9: Y | J9: Y | K9: Y | L9: Y | M9: - | N9: Y | O9: Y | P9: T | Q9: T | R9: Y | S9: Indikator : tingkat efisiensi
A10: 6 | B10: Mempercepat Penyediaan Konektivitas Broadband Inklusif, Berkualitas, dan Terjangkau | C10: Y | D10: Program Pengembangan dan Penguatan Infrastruktur Digital | E10: Meningkatnya Kualitas Internet Broadband Nasional | F10: Persentase (%) Tindak Lanjut Hasil Pengawasan terhadap Kualitas Layanan dan Aduan Masyarakat | G10: 100 Persen | H10: Y | I10: Y | J10: Y | K10: Y | L10: Y | M10: - | N10: Y | O10: Y | P10: T | Q10: T | R10: Y | S10: Indikator : tingkat efektivitas
A11: 7 | B11: Mempercepat Penyediaan Konektivitas Broadband Inklusif, Berkualitas, dan Terjangkau | C11: Y | D11: Program Pengembangan dan Penguatan Infrastruktur Digital | E11: Mempercepat Terwujudnya Coverage Broadband yang Merata ke Seluruh Indonesia | F11: Persentase (%) Cakupan Luas Pemukiman yang Tercover Layanan Mobile Broadband | G11: 97,6 Persen | H11: Y | I11: Y | J11: Y | K11: Y | L11: Y | M11: Nomenklatur Sasaran Program telah direvisi menjadi "Meningkatnya Coverage Broadband yang menjangkau ke seluruh indonesia" | N11: Y | O11: Y | P11: T | Q11: T | R11: Y | S11: Indikator : harusnya berfokus ke pemerataan jangkauan terhadap layanan belum menunjukan aspek kebijkan yang lebih jelas
A12: 8 | B12: Mempercepat Penyediaan Konektivitas Broadband Inklusif, Berkualitas, dan Terjangkau | C12: Y | D12: Program Pengembangan dan Penguatan Infrastruktur Digital | E12: Mempercepat Terwujudnya Coverage Broadband yang Merata ke Seluruh Indonesia | F12: Persentase (%) Jangkauan Jaringan Fiber Optik Kecamatan | G12: 71,5 Persen | H12: Y | I12: Y | J12: Y | K12: Y | L12: Y | M12: Nomenklatur Indikator telah direvisi menjadi "Persentase jaringan fiber optic menjangkau desa/kelurahan" | N12: Y | O12: Y | P12: Y | Q12: Y | R12: Y
A13: 9 | B13: Mempercepat Penyediaan Konektivitas Broadband Inklusif, Berkualitas, dan Terjangkau | C13: Y | D13: Program Pengembangan dan Penguatan Infrastruktur Digital | E13: Meningkatnya Penetrasi dan Utilisasi (Take Up) Internet Broadband | F13: Persentase (%) Peningkatan Jumlah Pelanggan Jaringan Tetap Pita Lebar Nasional | G13: 2,43 Persen | H13: Y | I13: Y | J13: Y | K13: Y | L13: Y | M13: Indikator telah diubah menjadi "Persentase (%) Tersedianya Akses Internet di Sektor Publik" | N13: Y | O13: Y | P13: Y | Q13: Y | R13: Y
A14: 10 | B14: Mempercepat Penyediaan Konektivitas Broadband Inklusif, Berkualitas, dan Terjangkau | C14: Y | D14: Program Pengembangan dan Penguatan Infrastruktur Digital | E14: Mewujudkan Industri Telekomunikasi dan Data Center yang berkelanjutan | F14: Rasio Biaya Hak Penggunaan (BHP) Spektrum Frekuensi Radio (SFR) terhadap Gross Revenue Industri dalam Rangka Keberlanjutan Industri Telekomunikasi | G14: 9,7 Persen | H14: Y | I14: Y | J14: Y | K14: Y | L14: Y | M14: - | N14: Y | O14: Y | P14: Y | Q14: T | R14: Y
A15: 11 | B15: Mempercepat Penyediaan Konektivitas Broadband Inklusif, Berkualitas, dan Terjangkau | C15: Y | D15: Program Pengembangan dan Penguatan Infrastruktur Digital | E15: Mewujudkan Industri Telekomunikasi dan Data Center yang berkelanjutan | F15: Kapasitas Data Center per kapita (Watt per kapita) | G15: 0,85 Watt Per Kapita | H15: Y | I15: Y | J15: Y | K15: Y | L15: Y | M15: Terdapat perubahan target menjadi "1,47 Watt per kapita" | N15: Y | O15: T | P15: Y | Q15: T | R15: Y | S15: ditambahkan tingkat ketersedian agar dapat terlihat kuantitasnya
A16: 12 | B16: Mempercepat Penyediaan Konektivitas Broadband Inklusif, Berkualitas, dan Terjangkau | C16: Y | D16: Program Pengembangan dan Penguatan Infrastruktur Digital | E16: Meningkatnya Pengembangan Industri Perangkat Digital yang Aman | F16: Persentase (%) Pengembangan Industri Perangkat Digital Dalam Negeri | G16: 20 Persen | H16: Y | I16: Y | J16: Y | K16: Y | L16: Y | M16: Nomenklatur Indikator mengalami perubahan menjadi "Nilai ekspor jasa telekomunikasi, komputer, dan informasi " | N16: Y | O16: T | P16: Y | Q16: Y | R16: Y
A17: 13 | B17: Mempercepat Penyediaan Konektivitas Broadband Inklusif, Berkualitas, dan Terjangkau | C17: Y | D17: Program Pengembangan dan Penguatan Infrastruktur Digital | E17: Meningkatnya cakupan dan kualitas layanan broadband di wilayah non komersial | F17: Jumlah Desa di Wilayah 3T Yang Mendapatkan Akses Seluler 4G (Kumulatif) | G17: 1.044 Lokasi | H17: Y | I17: Y | J17: Y | K17: Y | L17: Y | M17: Pada Rancangan Renstra 2025-2029, sasaran program & indikator program dari BAKTI bergabung bersama Ditjen Infrastruktur Digital | N17: Y | O17: Y | P17: Y | Q17: Y | R17: Y
A18: 14 | B18: Mempercepat Penyediaan Konektivitas Broadband Inklusif, Berkualitas, dan Terjangkau | C18: Y | D18: Program Pengembangan dan Penguatan Infrastruktur Digital | E18: Meningkatnya cakupan dan kualitas layanan broadband di wilayah non komersial | F18: Jumlah Lokasi Penyediaan Akses Internet di Wilayah Tertinggal, Terdepan, Terluar, Kawasan Prioritas, dan Lokasi Layanan Publik (Kumulatif) | G18: 27.869 Lokasi | H18: Y | I18: Y | J18: Y | K18: Y | L18: Y | M18: Pada Rancangan Renstra 2025-2029, sasaran program & indikator program dari BAKTI bergabung bersama Ditjen Infrastruktur Digital | N18: Y | O18: Y | P18: Y | Q18: Y | R18: Y
A19: 15 | B19: Mempercepat Penyediaan Konektivitas Broadband Inklusif, Berkualitas, dan Terjangkau | C19: Y | D19: Program Pengembangan dan Penguatan Infrastruktur Digital | E19: Meningkatnya cakupan dan kualitas layanan broadband di wilayah non komersial | F19: Persentase (%) Pemanfaatan Kapasitas Palapa Ring Barat 70%, Palapa Ring Tengah 45%, Palapa Ring Timur 45%, dengan Service Level Agreement (SLA) Minimal 95% | G19: 53 Persen | H19: Y | I19: Y | J19: Y | K19: Y | L19: Y | M19: Pada Rancangan Renstra 2025-2029, sasaran program & indikator program dari BAKTI bergabung bersama Ditjen Infrastruktur Digital | N19: Y | O19: Y | P19: Y | Q19: Y | R19: Y
A20: 16 | B20: Mempercepat Penyediaan Konektivitas Broadband Inklusif, Berkualitas, dan Terjangkau | C20: Y | D20: Program Pengembangan dan Penguatan Infrastruktur Digital | E20: Meningkatnya cakupan dan kualitas layanan broadband di wilayah non komersial | F20: Jumlah Kapasitas Penyediaan Satelit Multifungsi (SATRIA-1) (Kumulatif) | G20: 150 Gbps | H20: Y | I20: Y | J20: Y | K20: Y | L20: Y | M20: Pada Rancangan Renstra 2025-2029, sasaran program & indikator program dari BAKTI bergabung bersama Ditjen Infrastruktur Digital | N20: Y | O20: Y | P20: Y | Q20: Y | R20: Y
A21: 17 | B21: Mempercepat Penyediaan Konektivitas Broadband Inklusif, Berkualitas, dan Terjangkau | C21: Y | D21: Program Pengembangan dan Penguatan Infrastruktur Digital | E21: Meningkatnya cakupan dan kualitas layanan broadband di wilayah non komersial | F21: Jumlah Solusi Ekosistem Dalam Rangka Peningkatan Produktivitas masyarakat melalui Pemanfaatan Infrastruktur Dan Penguatan Ekosistem di WPUTI (Kumulatif) | G21: 15 Kelompok Masyarakat | H21: Y | I21: Y | J21: Y | K21: Y | L21: Y | M21: Pada Rancangan Renstra 2025-2029, sasaran program & indikator program dari BAKTI bergabung bersama Ditjen Infrastruktur Digital | N21: Y | O21: Y | P21: Y | Q21: Y | R21: Y
A22: 18 | B22: Mempercepat Penyediaan Sistem dan Jaringan Komunikasi untuk Layanan Khusus Secara Nasional | C22: Y | D22: Program Pengembangan dan Penguatan Infrastruktur Digital | E22: Meningkatnya Akselerasi Penyediaan Infrastruktur dan Sumber Daya untuk Layanan Khusus | F22: Persentase (%) Kabupaten/Kota yang Terfasilitasi Layanan Infrastruktur Telekomunikasi untuk Keperluan Perlindungan Masyarakat dan Penanggulangan Bencana | G22: 33,2 Persen (kumulatif) | H22: Y | I22: Y | J22: Y | K22: Y | L22: Y | M22: Sasaran Program telah berubah menjadi " Presentase Kab/Kota yang sudah terintegrasi Sistem Informasi dan Infrastruktur Jaringan Komunikasi Layanan Khusus Publik" dan target telah direvisi menjadi "35%" | N22: Y | O22: Y | P22: Y | Q22: Y | R22: Y
A23: 19 | B23: Meningkatnya Pertumbuhan Ekonomi dari Pengembangan Ekosistem Digital Nasional | C23: Y | D23: Program Pengembangan dan Penguatan Ekosistem dan Ruang Digital | E23: Meningkatnya Pertumbuhan Industri Pos Logistik dan Penyiaran | F23: Persentase pertumbuhan sektor penyiaran | G23: TBD TBD | H23: Y | I23: Y | J23: Y | K23: Y | L23: Y | M23: - | N23: Y | O23: Y | P23: Y | Q23: Y | R23: T
A24: 20 | B24: Meningkatnya Pertumbuhan Ekonomi dari Pengembangan Ekosistem Digital Nasional | C24: Y | D24: Program Pengembangan dan Penguatan Ekosistem dan Ruang Digital | E24: Meningkatnya Pertumbuhan Industri Gim dan Startup Digital Nasional | F24: Tingkat kesuksesan startup nasional / success rate startup | G24: 7 Persen | H24: Y | I24: Y | J24: Y | K24: Y | L24: Y | M24: - | N24: Y | O24: Y | P24: Y | Q24: Y | R24: Y
A25: 21 | B25: Meningkatnya Pertumbuhan Ekonomi dari Pengembangan Ekosistem Digital Nasional | C25: Y | D25: Program Pengembangan dan Penguatan Ekosistem dan Ruang Digital | E25: Meningkatnya Pertumbuhan Industri Gim dan Startup Digital Nasional | F25: Kontribusi startup digital terhadap nilai ekonomi digital | G25: TBD TBD | H25: Y | I25: Y | J25: Y | K25: Y | L25: Y | M25: Sasaran program berubah menjadi "Meningkatnya Penciptaan Nilai Ekonomi Digital dengan Penguatan Ekosistem Digital Nasional" dan target masih didiskusikan dengan Ditjen terkait | N25: Y | O25: Y | P25: Y | Q25: T | R25: T | S25: indikator belum dapat diukur
A26: 22 | B26: Meningkatnya Pertumbuhan Ekonomi dari Pengembangan Ekosistem Digital Nasional | C26: Y | D26: Program Pengembangan dan Penguatan Ekosistem dan Ruang Digital | E26: Meningkatnya Pertumbuhan Industri Gim dan Startup Digital Nasional | F26: Kontribusi Komdigi dalam persentase pertumbuhan gim nasional | G26: TBD TBD | H26: Y | I26: Y | J26: Y | K26: Y | L26: Y | M26: Sasaran program berubah menjadi "Meningkatnya Penciptaan Nilai Ekonomi Digital dengan Penguatan Ekosistem Digital Nasional" dan target masih didiskusikan dengan Ditjen terkait | N26: Y | O26: Y | P26: Y | Q26: T | R26: T | S26: indikator belum dapat diukur
A27: 23 | B27: Meningkatnya Pertumbuhan Ekonomi dari Pengembangan Ekosistem Digital Nasional | C27: Y | D27: Program Pengembangan dan Penguatan Ekosistem dan Ruang Digital | E27: Meningkatnya Pertumbuhan Industri Pos Logistik dan Penyiaran | F27: Persentase pertumbuhan sektor pos | G27: 9.5 Persen | H27: Y | I27: Y | J27: Y | K27: Y | L27: Y | M27: Indikator Program berubah menjadi "Pertumbuhan Sektor Pos Logistik" | N27: Y | O27: Y | P27: Y | Q27: Y | R27: Y
A28: 24 | B28: Meningkatnya Pertumbuhan Ekonomi dari Pengembangan Ekosistem Digital Nasional | C28: Y | D28: Program Pengembangan dan Penguatan Ekosistem dan Ruang Digital | E28: Meningkatnya Produktivitas di Sektor-sektor Prioritas dengan Pemanfaatan Teknologi Digital | F28: Persentase peningkatan produktivitas pelaku usaha di sektor produktif melalui pemanfaatan teknologi digital | G28: 10 Persen | H28: Y | I28: Y | J28: Y | K28: Y | L28: Y | M28: Indikator berubah menjadi "Persentase tingkat pertumbuhan pelaku usaha bidang teknologi baru" | N28: Y | O28: Y | P28: Y | Q28: Y | R28: Y
A29: 25 | B29: Meningkatnya Pertumbuhan Ekonomi dari Pengembangan Ekosistem Digital Nasional | C29: Y | D29: Program Pengembangan dan Penguatan Ekosistem dan Ruang Digital | E29: Meningkatnya Produktivitas di Sektor-sektor Prioritas dengan Pemanfaatan Teknologi Digital | F29: Persentase rata-rata peningkatan produktivitas sektor pasca adopsi digital | G29: TBD TBD | H29: Y | I29: Y | J29: Y | K29: Y | L29: Y | M29: - | N29: Y | O29: Y | P29: Y | Q29: Y | R29: T
A30: 26 | B30: Meningkatnya efektivitas penyelenggaraan informasi dan komunikasi publik | C30: Y | D30: Program Komunikasi Publik dan Media | E30: Meningkatnya efektivitas penyelenggaraan komunikasi publik nasional | F30: Tingkat jangkauan komunikasi publik | G30: 75 Persen | H30: Y | I30: Y | J30: Y | K30: Y | L30: Y | M30: - | N30: Y | O30: Y | P30: Y | Q30: Y | R30: Y
A31: 27 | B31: Meningkatnya efektivitas penyelenggaraan informasi dan komunikasi publik | C31: Y | D31: Program Komunikasi Publik dan Media | E31: Meningkatnya efektivitas penyelenggaraan komunikasi publik nasional | F31: Tingkat pemerataan aksesibilitas informasi publik pada kelompok masyarakat marginal (mencakup masyarakat di wilayah 3T, kelompok rentan, dan penyandang disabilitas) | G31: 75 Persen | H31: Y | I31: Y | J31: Y | K31: Y | L31: Y | M31: - | N31: Y | O31: Y | P31: Y | Q31: Y | R31: Y
A32: 28 | B32: Meningkatnya efektivitas penyelenggaraan informasi dan komunikasi publik | C32: Y | D32: Program Komunikasi Publik dan Media | E32: Meningkatnya efektivitas penyelenggaraan komunikasi publik nasional | F32: Tingkat kepuasan masyarakat terhadap akses dan kualitas informasi publik | G32: 75 Persen | H32: Y | I32: Y | J32: Y | K32: Y | L32: Y | M32: - | N32: Y | O32: Y | P32: Y | Q32: Y | R32: Y
A33: 29 | B33: Meningkatnya efektivitas penyelenggaraan informasi dan komunikasi publik | C33: Y | D33: Program Komunikasi Publik dan Media | E33: Meningkatnya keterbukaan informasi publik | F33: Tingkat kepuasan masyarakat terhadap keterbukaan informasi | G33: 76 Persen | H33: Y | I33: Y | J33: Y | K33: Y | L33: Y | M33: - | N33: Y | O33: Y | P33: Y | Q33: Y | R33: Y
A34: 30 | B34: Meningkatnya efektivitas penyelenggaraan informasi dan komunikasi publik | C34: Y | D34: Program Komunikasi Publik dan Media | E34: Meningkatnya kualitas ekosistem media yang terpercaya | F34: Persentase (%) peningkatan kualitas pengelolaan media | G34: 65 Persen | H34: Y | I34: Y | J34: Y | K34: Y | L34: Y | M34: - | N34: Y | O34: Y | P34: Y | Q34: Y | R34: Y
A35: 31 | B35: Meningkatnya efektivitas penyelenggaraan informasi dan komunikasi publik | C35: Y | D35: Program Komunikasi Publik dan Media | E35: Meningkatnya efektivitas penyelenggaraan komunikasi publik nasional | F35: Keberhasilan pengelolaan isu dan situasi krisis komunikasi publik | G35: 65 Persen | H35: Y | I35: Y | J35: Y | K35: Y | L35: Y | M35: - | N35: Y | O35: Y | P35: Y | Q35: Y | R35: Y
A36: 32 | B36: Meningkatnya kualitas pengelolaan layanan publik Kemenkomdigi | C36: Y | D36: Program Pengembangan dan Penguatan Infrastruktur Digital | E36: Meningkatnya Kualitas Layanan Publik Bidang Infrastruktur Digital | F36: Persentase (%) Realisasi Penerimaan PNBP Infrastruktur Digital | G36: 100 Persen | H36: Y | I36: Y | J36: Y | K36: Y | L36: Y | M36: - | N36: Y | O36: Y | P36: Y | Q36: Y | R36: Y
A37: 33 | B37: Meningkatnya kualitas pengelolaan layanan publik Kemenkomdigi | C37: Y | D37: Program Pengembangan dan Penguatan Infrastruktur Digital | E37: Meningkatnya Kualitas Layanan Publik Bidang Infrastruktur Digital | F37: Indeks Integritas Pelayanan Publik (IIPP) Bidang Infrastruktur Digital | G37: 8,5 Nilai | H37: Y | I37: Y | J37: Y | K37: Y | L37: Y | M37: - | N37: Y | O37: Y | P37: Y | Q37: Y | R37: Y
A38: 34 | B38: Meningkatnya kualitas pengelolaan layanan publik Kemenkomdigi | C38: Y | D38: Program Pengembangan dan Penguatan Infrastruktur Digital | E38: Meningkatnya Kualitas Layanan Publik Bidang Infrastruktur Digital | F38: Indeks Kepuasan Masyarakat (IKM) Terhadap Layanan Publik Bidang Infrastruktur Digital | G38: 3,6 Nilai | H38: Y | I38: Y | J38: Y | K38: Y | L38: Y | M38: - | N38: Y | O38: Y | P38: Y | Q38: Y | R38: Y
... A54: 52 | B54: Mewujudkan Transformasi Internal Manajemen adaptif dan resilien | C54: Y | D54: Program Dukungan Manajemen | E54: Meningkatkan efektivitas dan efisiensi pengelolaan birokrasi di Komdigi untuk mendukung transformasi digital nasional | F54: Nilai Kualitas Pelaporan Keuangan Unit Akuntansi Pembantu Pengguna Anggaran Eselon I (UAPPA Esselon 1) atas Laporan Keuangan BAKTI Tahun 2024 | G54: 80 Nilai | H54: Y | I54: Y | J54: Y | K54: Y | L54: Y | M54: Indikator ini telah diturunkan ke level kegiatan pada rancangan akhir renstra 2025-2029 | N54: Y | O54: T | P54: Y | Q54: Y | R54: Y
H55: 52 | I55: =COUNTIF(I5:I54,"Y") -> 50 | J55: =COUNTIF(J5:J54,"Y") -> 50 | K55: =COUNTIF(K5:K54,"Y") -> 50 | L55: =COUNTIF(L5:L54,"Y") -> 50 | N55: =COUNTIF(N5:N54,"Y") -> 50 | O55: =COUNTIF(O5:O54,"Y") -> 39 | P55: =COUNTIF(P5:P54,"Y") -> 47 | Q55: =COUNTIF(Q5:Q54,"Y") -> 42 | R55: =COUNTIF(R5:R54,"Y") -> 46
H56: 52 | I56: =COUNTA(I5:I54) -> 50 | J56: =COUNTA(J5:J54) -> 50 | K56: =COUNTA(K5:K54) -> 50 | L56: =COUNTA(L5:L54) -> 50 | N56: =COUNTA(N5:N54) -> 50 | O56: =COUNTA(O5:O54) -> 50 | P56: =COUNTA(P5:P54) -> 50 | Q56: =COUNTA(Q5:Q54) -> 50 | R56: =COUNTA(R5:R54) -> 50
H57: 1 | I57: 1 | J57: 1 | K57: 1 | L57: 1 | N57: =N55/N56 -> 1 | O57: =O55/O56 -> 0.78 | P57: =P55/P56 -> 0.94 | Q57: =Q55/Q56 -> 0.84 | R57: =R55/R56 -> 0.92

Sheet KKE 2.1 SASKEG
A1: PENJAMINAN KUALITAS HASIL PENILAIAN MANDIRI MATURITAS PENYELENGGARAAN SPIP TERINTEGRASI KEMENTERIAN KOMUNIKASI DAN INFORMATIKA Periode Penilaian sampai dengan 30 Juni 2024
A2: KK 2.1 - PENILAIAN PENETAPAN TUJUAN - SASARAN KEGIATAN
A3: NO | B3: SASARAN STRATEGIS | D3: SASARAN PROGRAM | G3: UNIT KERJA | H3: NAMA KEGIATAN | I3: SASARAN KEGIATAN | J3: INDIKATOR KINERJA | K3: TARGET KINERJA | L3: KUALITAS SASARAN KEGIATAN | Q3: KETERANGAN | R3: PENJAMINAN KUALITAS | W3: KETERANGAN
B4: URAIAN SASARAN STRATEGIS | C4: SASTRA RELEVAN DAN MENGGAMBARKAN MANDAT | D4: NAMA PROGRAM | E4: URAIAN SASARAN PROGRAM | F4: SASPRO RELEVAN DENGAN SASTRA DAN MENGGAMBARKAN TUGAS DAN FUNGSI | L4: SASTRA KEGIATAN BERORIENTASI HASIL | M4: SASKEG RELEVAN DENGAN SASPRO DAN MENGGAMBARKAN TUGAS DAN FUNGSI | N4: INDIKATOR KINERJA TEPAT | O4: UJI KECUKUPAN INDIKATOR | P4: TARGET KINERJA TEPAT | R4: SASTRA KEGIATAN BERORIENTASI HASIL | S4: SASKEG RELEVAN DENGAN SASPRO DAN MENGGAMBARKAN TUGAS DAN FUNGSI | T4: INDIKATOR KINERJA TEPAT | U4: UJI KECUKUPAN INDIKATOR | V4: TARGET KINERJA TEPAT
A5: 1 | B5: =A5+1 -> 2 | C5: =B5+1 -> 3 | D5: =C5+1 -> 4 | E5: =D5+1 -> 5 | F5: =E5+1 -> 6 | H5: =G5+1 -> 1 | I5: =H5+1 -> 2 | J5: 11 | K5: 12 | L5: =K5+1 -> 13 | M5: =L5+1 -> 14 | N5: =M5+1 -> 15 | O5: =N5+1 -> 16 | P5: =O5+1 -> 17 | Q5: =P5+1 -> 18 | R5: =Q5+1 -> 19 | S5: =R5+1 -> 20 | ... W5: =V5+1 -> 24
A6: Direktorat Jenderal Komunikasi Publik dan Media
A7: 1 | B7: Meningkatnya efektivitas penyelenggaraan informasi dan komunikasi publik | C7: Y | D7: Program Komunikasi Publik dan Media | E7: Meningkatnya efektivitas penyelenggaraan komunikasi publik nasional | F7: Y | G7: Direktorat Informasi Publik | H7: Penguatan Komunikasi dan Informasi Publik Nasional | I7: Menyediakan Konten Informasi Publik yang Berkualitas, Relevan, dan Kredibel | J7: Tingkat kepatuhan standar konten informasi publik dan manajemen aset K/L/D | K7: 0.7 | L7: T | M7: Y | N7: Y | O7: Y | P7: Y | R7: T | S7: Y | T7: Y | U7: Y | V7: Y | W7: -Saskeg masih berorientasi pada proses -Indikator untuk mengkukur kualitas, relevansi, dan kredibilitas seperti apa? | Z7: Saskeg merupakan turunan dari Draft Perpres SKPN. Indeks komunikasi pembangunan dan informasi publik mengukur 5 aspek, bisa terukur kualittasnya. -Manajemen aset berupa informasi | AA7: Cara mengkukur kualitas, relevansi, dan kredibilitas. Apa indikatornya?
A8: 2 | B8: Meningkatnya efektivitas penyelenggaraan informasi dan komunikasi publik | C8: Y | D8: Program Komunikasi Publik dan Media | E8: Meningkatnya efektivitas penyelenggaraan komunikasi publik nasional | F8: Y | G8: Direktorat Informasi Publik | H8: Penguatan Komunikasi dan Informasi Publik Nasional | I8: Menyediakan Konten Informasi Publik yang Berkualitas, Relevan, dan Kredibel | J8: Tingkat aksesibilitas digital informasi untuk penyandang disabilitas | K8: 0.65 | L8: T | M8: Y | N8: Y | O8: Y | P8: Y | R8: T | S8: Y | T8: Y | U8: Y | V8: Y | W8: -Saskeg masih berorientasi pada proses -Indikator ini tidak menjawab kualitas, relevansi, dan kredibilitas. -Uji kecukupan indikator tidak dapat menjawab saskeg -Belum ada baseline penentuan target | X8: Web Content Accessibility Guidelines (WCAG) -->WCAG adalah framework yang tepat dan standar untuk mengukur target aksesibilitas digital Anda sebesar 65% | Y8: Web Content Accessibility Guidelines (WCAG) -->WCAG adalah framework yang tepat dan standar untuk mengukur target aksesibilitas digital Anda sebesar 65% | Z8: Output yang diharapkan adalah Permenkomdigi. K/L/D akan diukur penyediaan fitur yang aksesibel untuk penyandang disabilitas | AA8: -Indikator ini tidak menjawab kualitas, relevansi, dan kredibilitas. -Uji kecukupan indikator tidak dapat menjawab saskeg -Belum ada baseline penentuan target
A9: 3 | B9: Meningkatnya efektivitas penyelenggaraan informasi dan komunikasi publik | C9: Y | D9: Program Komunikasi Publik dan Media | E9: Meningkatnya efektivitas penyelenggaraan komunikasi publik nasional | F9: Y | G9: Direktorat Informasi Publik | H9: Penguatan Komunikasi dan Informasi Publik Nasional | I9: Menyediakan Konten Informasi Publik yang Berkualitas, Relevan, dan Kredibel | J9: Persentase konten komunikasi publik yang dapat memperkuat kohesivitas sosial berlandaskan nilai-nilai Pancasila | K9: 0.7 | L9: Y | M9: Y | N9: Y | O9: Y | P9: Y | R9: Y | S9: Y | T9: Y | U9: Y | V9: Y | W9: Saskeg masih berorientasi pada proses | Z9: Merupakan turunan dari RPJMN | AA9: Kohesivitas : agar ditanyakan
A10: 4 | B10: Meningkatnya efektivitas penyelenggaraan informasi dan komunikasi publik | C10: Y | D10: Program Komunikasi Publik dan Media | E10: Meningkatnya efektivitas penyelenggaraan komunikasi publik nasional | F10: Y | G10: Direktorat Komunikasi Publik | H10: Penguatan Komunikasi dan Informasi Publik Nasional | I10: Meningkatnya kualitas tata kelola dan penyelenggaraan komunikasi publik | J10: Tingkat kepatuhan penyelenggaraan komunikasi publik K/L/D | K10: 0.7 | L10: Y | M10: Y | N10: Y | O10: Y | P10: Y | R10: Y | S10: Y | T10: Y | U10: Y | V10: Y | W10: -kepatuhan penyelenggaraan tidak mengukur peningkatan penyelenggaraan kompub -tidak ada indikator untuk mengukur penyelenggaraan kompub -indikator tambahan untuk mengukur peningkatan penyelenggaraan kompun -belum ada baseline penentuan target | X10: Laporan Audit Kepatuhan Komunikasi Publik yang disusun berdasarkan standar dan peraturan pemerintah yang berlaku. | Y10: Laporan Audit Kepatuhan Komunikasi Publik yang disusun berdasarkan standar dan peraturan pemerintah yang berlaku. | Z10: Indikator sudah cukup karena akan dibuatkan NSPK yang mengatur takel dan penyelenggaraannya. Target merupakan jumlah K/L yang patuh | AA10: -kepatuhan penyelenggaraan tidak mengukur peningkatan penyelenggaraan kompub -tidak ada indikator untuk mengukur penyelenggaraan kompub -indikator tambahan untuk mengukur peningkatan penyelenggaraan kompun -belum ada baseline penentuan target
A11: 5 | B11: Meningkatnya efektivitas penyelenggaraan informasi dan komunikasi publik | C11: Y | D11: Program Komunikasi Publik dan Media | E11: Meningkatnya efektivitas penyelenggaraan komunikasi publik nasional | F11: Y | G11: Direktorat Kemitraan Komunikasi Lembaga dan Kehumasan | H11: Pengembangan Ekosistem Media, Kehumasan, dan Kemitraan Komunikasi Publik | I11: Penguatan Kehumasan dan Kemitraan Komunikasi Publik | J11: Tingkat keterlibatan mitra strategis dalam komunikasi publik | K11: 0.7 | L11: Y | M11: Y | N11: Y | O11: Y | P11: Y | R11: Y | S11: Y | T11: Y | U11: Y | V11: Y | W11: -Saskeg masih berorientasi pada proses -Indikator kinerja tidak spesifik -Mitra strategis siapa? -Belum ada baseline penentuan target | X11: -Laporan Monitoring dan Evaluasi Kemitraan Komunikasi Publik -Perjanjian Kerja Sama (PKS) atau Memorandum of Understanding (MoU): -Rencana Kerja Kolaborasi (Joint Action Plan) | Y11: -Laporan Monitoring dan Evaluasi Kemitraan Komunikasi Publik -Perjanjian Kerja Sama (PKS) atau Memorandum of Understanding (MoU): -Rencana Kerja Kolaborasi (Joint Action Plan) | Z11: Pada RO ada terkait target lembaga | AA11: -Indikator kinerja tidak spesifik -Mitra strategis siapa? -Belum ada baseline penentuan target
A12: 6 | B12: Meningkatnya efektivitas penyelenggaraan informasi dan komunikasi publik | C12: Y | D12: Program Komunikasi Publik dan Media | E12: Meningkatnya efektivitas penyelenggaraan komunikasi publik nasional | F12: Y | G12: Direktorat Kemitraan Komunikasi Lembaga dan Kehumasan | H12: Pengembangan Ekosistem Media, Kehumasan, dan Kemitraan Komunikasi Publik | I12: Penguatan Kehumasan dan Kemitraan Komunikasi Publik | J12: Tingkat akses media informasi pemerintah oleh masyarakat | K12: 0.7 | L12: Y | M12: T | N12: T | O12: Y | P12: Y | R12: Y | S12: T | T12: T | U12: Y | V12: Y | W12: -Saskeg masih berorientasi pada proses -Indikator kinerja tidak spesifik dan relevan -Belum ada baseline penentuan target | X12: -Laporan Analitik Akses Media Informasi Publik - Laporan Survei Persepsi dan Jangkauan Publik (Data Kualitatif & Pelengkap) | Y12: -Laporan Analitik Akses Media Informasi Publik - Laporan Survei Persepsi dan Jangkauan Publik (Data Kualitatif & Pelengkap) | AA12: -Indikator kinerja tidak spesifik dan relevan --Belum ada baseline penentuan target
A13: 7 | B13: Meningkatnya efektivitas penyelenggaraan informasi dan komunikasi publik | C13: Y | D13: Program Komunikasi Publik dan Media | E13: Meningkatnya efektivitas penyelenggaraan komunikasi publik nasional | F13: Y | G13: Monumen Pers Nasional | H13: Penguatan Komunikasi dan Informasi Publik Nasional | I13: Terselenggaranya Layanan pemanfaatan informasi media cetak dan koleksi benda bersejarah bagi masyarakat | J13: Persentase (%) Kepuasan Pengunjung Terhadap Layanan Monumen Pers Nasional | K13: 0.85 | L13: Y | M13: Y | N13: Y | O13: Y | P13: Y | R13: Y | S13: Y | T13: Y | U13: Y | V13: Y | W13: -Saskeg masih berorientasi pada proses -Belum ada baseline penentuan target | AA13: -Belum ada baseline penentuan target
A14: 8 | B14: Meningkatnya efektivitas penyelenggaraan informasi dan komunikasi publik | C14: Y | D14: Program Komunikasi Publik dan Media | E14: Meningkatnya efektivitas penyelenggaraan komunikasi publik nasional | F14: Y | G14: Museum Penerangan | H14: Penguatan Komunikasi dan Informasi Publik Nasional | I14: Terselenggaranya Layanan Informasi Benda-benda Bersejarah di Bidang Komunikasi dan Informasi | J14: Persentase (%) Kepuasan Pengunjung Terhadap Layanan Museum Penerangan | K14: 0.85 | L14: Y | M14: Y | N14: Y | O14: Y | P14: Y | R14: Y | S14: Y | T14: Y | U14: Y | V14: Y | W14: -Saskeg masih berorientasi pada proses -Belum ada baseline penentuan target | AA14: -Belum ada baseline penentuan target
A15: 9 | B15: Meningkatnya efektivitas penyelenggaraan informasi dan komunikasi publik | C15: Y | D15: Program Komunikasi Publik dan Media | E15: Meningkatnya keterbukaan informasi publik | F15: Y | G15: Direktorat Informasi Publik | H15: Penguatan Komunikasi dan Informasi Publik Nasional | I15: Kepatuhan Dalam Pelaksanaan Keterbukaan Informasi Publik | J15: Tingkat kepatuhan K/L/D dalam pelaksanaan keterbukaan informasi publik | K15: 0.7 | L15: Y | M15: Y | N15: Y | O15: Y | P15: Y | R15: Y | S15: Y | T15: Y | U15: Y | V15: Y | W15: -Saskeg masih berorientasi pada proses -Belum ada baseline penentuan target | X15: Laporan Hasil Monitoring dan Evaluasi (Monev) Keterbukaan Informasi Publik | Y15: Laporan Hasil Monitoring dan Evaluasi (Monev) Keterbukaan Informasi Publik | AA15: -Belum ada baseline penentuan target
A16: 10 | B16: Meningkatnya efektivitas penyelenggaraan informasi dan komunikasi publik | C16: Y | D16: Program Komunikasi Publik dan Media | E16: Meningkatnya kualitas ekosistem media yang terpercaya | F16: Y | G16: Direktorat Ekosistem Media | H16: Pengembangan Ekosistem Media, Kehumasan, dan Kemitraan Komunikasi Publik | I16: Mewujudkan ekosistem media yang sehat di era digital | J16: Tingkat resiliensi media | K16: 0.65 | L16: Y | M16: T | N16: T | O16: Y | P16: Y | R16: Y | S16: T | T16: T | U16: Y | V16: Y | W16: -Belum ada baseline penentuan target -maksud resiliensi media? apakah kemampuan survival media? | X16: -SOP atau Protokol Manajemen Krisis Komunikasi -Laporan Simulasi Krisis (Crisis Drill Report) -Laporan Analisis Isu dan Sentimen Media | Y16: -SOP atau Protokol Manajemen Krisis Komunikasi -Laporan Simulasi Krisis (Crisis Drill Report) -Laporan Analisis Isu dan Sentimen Media | AA16: -Belum ada baseline penentuan target -maksud resiliensi media? apakah kemampuan survival media?
A17: 11 | B17: Meningkatnya efektivitas penyelenggaraan informasi dan komunikasi publik | C17: Y | D17: Program Komunikasi Publik dan Media | E17: Meningkatnya kualitas ekosistem media yang terpercaya | F17: Y | G17: Direktorat Ekosistem Media | H17: Pengembangan Ekosistem Media, Kehumasan, dan Kemitraan Komunikasi Publik | I17: Mewujudkan ekosistem media yang sehat di era digital | J17: Tingkat keterlibatan publik dalam komunikasi publik | K17: 0.65 | L17: Y | M17: Y | N17: T | O17: Y | P17: Y | R17: Y | S17: Y | T17: T | U17: Y | V17: Y | W17: -Belum ada baseline penentuan target -hubungan keterlibatan publik dengan ekosistem media sehat? | X17: Laporan Analitik Media Sosial | Y17: Laporan Analitik Media Sosial | AA17: -Belum ada baseline penentuan target -hubungan keterlibatan publik dengan ekosistem media sehat?
A18: 12 | B18: Meningkatnya efektivitas penyelenggaraan informasi dan komunikasi publik | C18: Y | D18: Program Dukungan Manajemen | E18: Meningkatkan efektivitas dan efisiensi pengelolaan birokrasi di Komdigi untuk mendukung transformasi digital nasional | F18: Y | G18: Sekretariat Ditjen Komunikasi Publik dan Media | H18: Pengelolaan Keuangan, BMN dan Umum Direktorat Jenderal Komunikasi Publik dan Media | I18: Meningkatnya Kualitas Tata Kelola Ditjen KPM yang Bersih dan Efisien | J18: Nilai Indeks Reformasi Birokrasi Ditjen KPM Tahun 2025 | K18: 84 | L18: Y | M18: Y | N18: Y | O18: Y | P18: Y | R18: Y | S18: Y | T18: Y | U18: Y | V18: Y | W18: -bagaimana menkuantifikasi nilai 84 sementara skrg hanya memantau renaksi RB Tematik? -nilai LAKIP 2024 adalah 85->100 | AA18: -bagaimana menkuantifikasi nilai 84 sementara skrg hanya memantau renaksi RB Tematik? -nilai LAKIP 2024 adalah 85->100
A19: 13 | B19: Meningkatnya efektivitas penyelenggaraan informasi dan komunikasi publik | C19: Y | D19: Program Dukungan Manajemen | E19: Meningkatkan efektivitas dan efisiensi pengelolaan birokrasi di Komdigi untuk mendukung transformasi digital nasional | F19: Y | G19: Sekretariat Ditjen Komunikasi Publik dan Media | H19: Pengelolaan Keuangan, BMN dan Umum Direktorat Jenderal Komunikasi Publik dan Media | I19: Meningkatnya Kualitas Tata Kelola Ditjen KPM yang Bersih dan Efisien | J19: Nilai Akuntabilitas Kinerja (AKIP) Ditjen KPM Tahun 2025 | K19: 75 | L19: Y | M19: Y | N19: Y | O19: Y | P19: Y | R19: Y | S19: Y | T19: Y | U19: Y | V19: Y | W19: -nilai LAKIP 2024 75->67 | AA19: -nilai LAKIP 2024 75->67
A20: 14 | B20: Meningkatnya efektivitas penyelenggaraan informasi dan komunikasi publik | C20: Y | D20: Program Dukungan Manajemen | E20: Meningkatkan efektivitas dan efisiensi pengelolaan birokrasi di Komdigi untuk mendukung transformasi digital nasional | F20: Y | G20: Sekretariat Ditjen Komunikasi Publik dan Media | H20: Pengelolaan Keuangan, BMN dan Umum Direktorat Jenderal Komunikasi Publik dan Media | I20: Meningkatnya Kualitas Tata Kelola Ditjen KPM yang Bersih dan Efisien | J20: Persentase (%) Batas Tertinggi Temuan Hasil Pemeriksaan BPK di Ditjen KPM Tahun 2025 | K20: 0.01 | L20: Y | M20: Y | N20: Y | O20: Y | P20: Y | R20: Y | S20: Y | T20: Y | U20: Y | V20: Y | W20: -nilai LAKIP 1%->0.001% | AA20: -nilai LAKIP 1%->0.001%
A21: 15 | B21: Meningkatnya efektivitas penyelenggaraan informasi dan komunikasi publik | C21: Y | D21: Program Dukungan Manajemen | E21: Meningkatkan efektivitas dan efisiensi pengelolaan birokrasi di Komdigi untuk mendukung transformasi digital nasional | F21: Y | G21: Sekretariat Ditjen Komunikasi Publik dan Media | H21: Pengelolaan Keuangan, BMN dan Umum Direktorat Jenderal Komunikasi Publik dan Media | I21: Meningkatnya Kualitas Tata Kelola Ditjen KPM yang Bersih dan Efisien | J21: Nilai Kinerja Anggaran Ditjen KPM Tahun 2025 | K21: 88 | L21: Y | M21: Y | N21: Y | O21: Y | P21: Y | R21: Y | S21: Y | T21: Y | U21: Y | V21: Y | W21: kenapa hanya 88? capaian LAKIP 2024 92-->95 | AA21: kenapa hanya 88? capaian LAKIP 2024 92-->95
A22: 16 | B22: Meningkatnya efektivitas penyelenggaraan informasi dan komunikasi publik | C22: Y | D22: Program Dukungan Manajemen | E22: Meningkatkan efektivitas dan efisiensi pengelolaan birokrasi di Komdigi untuk mendukung transformasi digital nasional | F22: Y | G22: Sekretariat Ditjen Komunikasi Publik dan Media | H22: Pengelolaan Keuangan, BMN dan Umum Direktorat Jenderal Komunikasi Publik dan Media | I22: Meningkatnya Kualitas Tata Kelola Ditjen KPM yang Bersih dan Efisien | J22: Nilai SPIP Ditjen KPM Tahun 2025 | K22: 3.8 | L22: Y | M22: Y | N22: Y | O22: Y | P22: Y | R22: Y | S22: Y | T22: Y | U22: Y | V22: Y | W22: Berdasarkan LAKIP 2024 4.33->3.88 | AA22: Berdasarkan LAKIP 2024 4.33->3.88
A23: 17 | B23: Meningkatnya efektivitas penyelenggaraan informasi dan komunikasi publik | C23: Y | D23: Program Dukungan Manajemen | E23: Meningkatkan efektivitas dan efisiensi pengelolaan birokrasi di Komdigi untuk mendukung transformasi digital nasional | F23: Y | G23: Sekretariat Ditjen Komunikasi Publik dan Media | H23: Pengelolaan Keuangan, BMN dan Umum Direktorat Jenderal Komunikasi Publik dan Media | I23: Meningkatnya Kualitas Tata Kelola Ditjen KPM yang Bersih dan Efisien | J23: Indeks kepuasan pegawai terhadap layanan Dukungan Manajemen Ditjen KPM Tahun 2025 | K23: 3.8 | L23: Y | M23: Y | N23: Y | O23: Y | P23: Y | R23: Y | S23: Y | T23: Y | U23: Y | V23: Y | W23: Berdasarkan LAKIP 2024 4.27->4.28 | AA23: Berdasarkan LAKIP 2024 4.27->4.28
A24: 18 | B24: Meningkatnya efektivitas penyelenggaraan informasi dan komunikasi publik | C24: Y | D24: Program Dukungan Manajemen | E24: Meningkatkan efektivitas dan efisiensi pengelolaan birokrasi di Komdigi untuk mendukung transformasi digital nasional | F24: Y | G24: Sekretariat Ditjen Komunikasi Publik dan Media | H24: Pengelolaan Keuangan, BMN dan Umum Direktorat Jenderal Komunikasi Publik dan Media | I24: Meningkatnya Kualitas Tata Kelola Ditjen KPM yang Bersih dan Efisien | J24: Persentase Penyelesaian Tindak Lanjut Hasil Pemeriksaan BPK Tahun Berjalan di Ditjen KPM Tahun 2025 | K24: 0.7 | L24: Y | M24: Y | N24: Y | O24: Y | P24: Y | R24: Y | S24: Y | T24: Y | U24: Y | V24: Y | W24: di LAKIP 70->100 | AA24: di LAKIP 70->100
A25: 19 | B25: Meningkatnya efektivitas penyelenggaraan informasi dan komunikasi publik | C25: Y | D25: Program Dukungan Manajemen | E25: Meningkatkan efektivitas dan efisiensi pengelolaan birokrasi di Komdigi untuk mendukung transformasi digital nasional | F25: Y | G25: Sekretariat Ditjen Komunikasi Publik dan Media | H25: Pengelolaan Keuangan, BMN dan Umum Direktorat Jenderal Komunikasi Publik dan Media | I25: Meningkatnya Kualitas Tata Kelola Ditjen KPM yang Bersih dan Efisien | J25: Persentase Penyelesaian Tindak Lanjut Hasil Pemeriksaan BPK Tahun Sebelumnya di Ditjen KPM Tahun 2025 | K25: 0.3 | L25: Y | M25: Y | N25: Y | O25: Y | P25: Y | R25: Y | S25: Y | T25: Y | U25: Y | V25: Y | W25: di LAKIP 30->87 | AA25: di LAKIP 30->87
A26: 20 | B26: Meningkatnya efektivitas penyelenggaraan informasi dan komunikasi publik | C26: Y | D26: Program Dukungan Manajemen | E26: Meningkatkan efektivitas dan efisiensi pengelolaan birokrasi di Komdigi untuk mendukung transformasi digital nasional | F26: Y | G26: Sekretariat Ditjen Komunikasi Publik dan Media | H26: Pengelolaan Keuangan, BMN dan Umum Direktorat Jenderal Komunikasi Publik dan Media | I26: Meningkatnya Kualitas Tata Kelola Ditjen KPM yang Bersih dan Efisien | J26: Nilai Kualitas Pelaporan Keuangan Unit Akuntansi Pembantu Pengguna Anggaran Eselon I (UAPPA E1) Ditjen KPM Tahun 2025 | K26: 80 | L26: Y | M26: Y | N26: Y | O26: Y | P26: Y | R26: Y | S26: Y | T26: Y | U26: Y | V26: Y | W26: di LAKIP 2024 100->95, kenapa 2025 hanya 80? | AA26: di LAKIP 2024 100->95, kenapa 2025 hanya 80?
A27: 21 | B27: Meningkatnya efektivitas penyelenggaraan informasi dan komunikasi publik | C27: Y | D27: Program Dukungan Manajemen | E27: Meningkatkan efektivitas dan efisiensi pengelolaan birokrasi di Komdigi untuk mendukung transformasi digital nasional | F27: Y | G27: Sekretariat Ditjen Komunikasi Publik dan Media | H27: Pengelolaan Keuangan, BMN dan Umum Direktorat Jenderal Komunikasi Publik dan Media | I27: Meningkatnya Kualitas Tata Kelola Ditjen KPM yang Bersih dan Efisien | J27: Nilai Kualitas Pelaporan Keuangan Unit Akuntansi Kuasa Pengguna Anggaran (UAKPA) Ditjen KPM Tahun 2025 | K27: 80 | L27: Y | M27: Y | N27: Y | O27: Y | P27: Y | R27: Y | S27: Y | T27: Y | U27: Y | V27: Y | W27: di LAKIP 100->97 | AA27: di LAKIP 100->97
A28: Direktorat Jenderal Infrastruktur Digital
A29: 1 | B29: Meningkatnya kualitas pengelolaan layanan publik Kemenkomdigi | C29: Y | D29: Program Pengembangan dan Penguatan Infrastruktur Digital | E29: Meningkatnya Kualitas Layanan Publik Bidang Infrastruktur Digital | F29: Y | G29: Direktorat Layanan Infrastruktur Digital | H29: Layanan Publik Bidang Sumber Daya dan Perangkat Digital | I29: Meningkatnya kualitas layanan publik dan PNBP bidang Infrastruktur Digital | J29: Indeks Kepuasan Masyarakat (IKM) Layanan Perizinan Spektrum Frekuensi Radio, Sertifikasi Operator Radio, dan Sertifikasi Perangkat Digital | K29: 3,6 Nilai | L29: Y | M29: Y | N29: Y | O29: Y | P29: Y | Q29: sesuai | R29: Y | S29: Y | T29: Y | U29: Y | V29: Y | W29: sesuai
A30: 2 | B30: Meningkatnya kualitas pengelolaan layanan publik Kemenkomdigi | C30: Y | D30: Program Pengembangan dan Penguatan Infrastruktur Digital | E30: Meningkatnya Kualitas Layanan Publik Bidang Infrastruktur Digital | F30: Y | G30: Direktorat Layanan Infrastruktur Digital | H30: Layanan Publik Bidang Sumber Daya dan Perangkat Digital | I30: Meningkatnya kualitas layanan publik dan PNBP bidang Infrastruktur Digital | J30: Indeks Integritas Pelayanan Publik (IIPP) Layanan Perizinan Spektrum Frekuensi Radio, Sertifikasi Operator Radio, dan Sertifikasi Perangkat Digital | K30: 8,5 Nilai | L30: Y | M30: Y | N30: Y | O30: Y | P30: Y | Q30: sesuai | R30: Y | S30: Y | T30: Y | U30: Y | V30: Y | W30: sesuai
A31: 3 | B31: Meningkatnya kualitas pengelolaan layanan publik Kemenkomdigi | C31: Y | D31: Program Pengembangan dan Penguatan Infrastruktur Digital | E31: Meningkatnya Kualitas Layanan Publik Bidang Infrastruktur Digital | F31: Y | G31: Direktorat Layanan Infrastruktur Digital | H31: Layanan Publik Bidang Sumber Daya dan Perangkat Digital | I31: Meningkatnya kualitas layanan publik dan PNBP bidang Infrastruktur Digital | J31: Persentase Capaian target PNBP SFR, Sertifikasi alat dan perangkat Digital | K31: 100 Persen | L31: Y | M31: Y | N31: Y | O31: Y | P31: Y | Q31: Penjelasan Indikator Saskeg : Pengelolaan sumber daya frekuensi dan sertifikasi perangkat untuk mendukung pendapatan negara dan transformasi digital serta pelayanan publik yang prima dan kepatuhan pelaku usaha terhadap regulasi | R31: Y | S31: Y | T31: Y | U31: Y | V31: Y | W31: Penjelasan Indikator Saskeg : Pengelolaan sumber daya frekuensi dan sertifikasi perangkat untuk mendukung pendapatan negara dan transformasi digital serta pelayanan publik yang prima dan kepatuhan pelaku usaha terhadap regulasi
A32: 4 | B32: Meningkatnya kualitas pengelolaan layanan publik Kemenkomdigi | C32: Y | D32: Program Dukungan Manajemen | E32: Meningkatkan efektivitas dan efisiensi pengelolaan birokrasi di Komdigi untuk mendukung transformasi digital nasional | F32: Y | G32: Sekretariat Ditjen Infrastruktur Digital | H32: Pengelolaan Keuangan, BMN dan Umum Direktorat Jenderal Infrastruktur Digital | I32: Meningkatnya kualitas tata kelola internal Ditjen Infrastruktur Digital | J32: Nilai AKIP Ditjen Infrastruktur Digital Tahun 2025 | K32: 77,10 Nilai | L32: Y | M32: Y | N32: Y | O32: Y | P32: Y | Q32: sesuai | R32: Y | S32: Y | T32: Y | U32: Y | V32: Y | W32: sesuai
A33: 5 | B33: Meningkatnya kualitas pengelolaan layanan publik Kemenkomdigi | C33: Y | D33: Program Dukungan Manajemen | E33: Meningkatkan efektivitas dan efisiensi pengelolaan birokrasi di Komdigi untuk mendukung transformasi digital nasional | F33: Y | G33: Sekretariat Ditjen Infrastruktur Digital | H33: Pengelolaan Keuangan, BMN dan Umum Direktorat Jenderal Infrastruktur Digital | I33: Meningkatnya kualitas tata kelola internal Ditjen Infrastruktur Digital | J33: Persentase (%) Batas Tertinggi Temuan Hasil Pemeriksaan BPK di Ditjen Infrastruktur Digital Tahun 2025 | K33: 1 Persen | L33: Y | M33: Y | N33: Y | O33: Y | P33: Y | Q33: sesuai | R33: Y | S33: Y | T33: Y | U33: Y | V33: Y | W33: sesuai
A34: 6 | B34: Meningkatnya kualitas pengelolaan layanan publik Kemenkomdigi | C34: Y | D34: Program Dukungan Manajemen | E34: Meningkatkan efektivitas dan efisiensi pengelolaan birokrasi di Komdigi untuk mendukung transformasi digital nasional | F34: Y | G34: Sekretariat Ditjen Infrastruktur Digital | H34: Pengelolaan Keuangan, BMN dan Umum Direktorat Jenderal Infrastruktur Digital | I34: Meningkatnya kualitas tata kelola internal Ditjen Infrastruktur Digital | J34: Nilai Kinerja Anggaran Ditjen Infrastruktur Digital Tahun 2025 | K34: 70 Nilai | L34: Y | M34: Y | N34: Y | O34: Y | P34: Y | Q34: sesuai | R34: Y | S34: Y | T34: Y | U34: Y | V34: Y | W34: sesuai
A35: 7 | B35: Meningkatnya kualitas pengelolaan layanan publik Kemenkomdigi | C35: Y | D35: Program Dukungan Manajemen | E35: Meningkatkan efektivitas dan efisiensi pengelolaan birokrasi di Komdigi untuk mendukung transformasi digital nasional | F35: Y | G35: Sekretariat Ditjen Infrastruktur Digital | H35: Pengelolaan Keuangan, BMN dan Umum Direktorat Jenderal Infrastruktur Digital | I35: Meningkatnya kualitas tata kelola internal Ditjen Infrastruktur Digital | J35: Nilai Maturitas SPIP Ditjen Infrastruktur Digital Tahun 2025 | K35: 3,57 Nilai | L35: Y | M35: Y | N35: Y | O35: Y | P35: Y | Q35: sesuai | R35: Y | S35: Y | T35: Y | U35: Y | V35: Y | W35: sesuai
A36: 8 | B36: Meningkatnya kualitas pengelolaan layanan publik Kemenkomdigi | C36: Y | D36: Program Dukungan Manajemen | E36: Meningkatkan efektivitas dan efisiensi pengelolaan birokrasi di Komdigi untuk mendukung transformasi digital nasional | F36: Y | G36: Sekretariat Ditjen Infrastruktur Digital | H36: Pengelolaan Keuangan, BMN dan Umum Direktorat Jenderal Infrastruktur Digital | I36: Meningkatnya kualitas tata kelola internal Ditjen Infrastruktur Digital | J36: Indeks kepuasan pegawai terhadap layanan Dukungan Manajemen Ditjen Infrastruktur Digital Tahun 2025 | K36: 4,25 Nilai | L36: Y | M36: Y | N36: Y | O36: Y | P36: Y | Q36: sesuai | R36: Y | S36: Y | T36: Y | U36: Y | V36: Y | W36: sesuai
A37: 9 | B37: Meningkatnya kualitas pengelolaan layanan publik Kemenkomdigi | C37: Y | D37: Program Dukungan Manajemen | E37: Meningkatkan efektivitas dan efisiensi pengelolaan birokrasi di Komdigi untuk mendukung transformasi digital nasional | F37: Y | G37: Sekretariat Ditjen Infrastruktur Digital | H37: Pengelolaan Keuangan, BMN dan Umum Direktorat Jenderal Infrastruktur Digital | I37: Meningkatnya kualitas tata kelola internal Ditjen Infrastruktur Digital | J37: Nilai Kualitas Pelaporan Keuangan Unit Akuntansi Pembantu Pengguna Anggaran Eselon I (UAPPA-E1) Atas Laporan Keuangan Ditjen Infrastruktur Digital Tahun 2025 | K37: 90 Nilai | L37: Y | M37: Y | N37: Y | O37: Y | P37: Y | Q37: sesuai | R37: Y | S37: Y | T37: Y | U37: Y | V37: Y | W37: sesuai
A38: 10 | B38: Meningkatnya kualitas pengelolaan layanan publik Kemenkomdigi | C38: Y | D38: Program Dukungan Manajemen | E38: Meningkatkan efektivitas dan efisiensi pengelolaan birokrasi di Komdigi untuk mendukung transformasi digital nasional | F38: Y | G38: Sekretariat Ditjen Infrastruktur Digital | H38: Pengelolaan Keuangan, BMN dan Umum Direktorat Jenderal Infrastruktur Digital | I38: Meningkatnya kualitas tata kelola internal Ditjen Infrastruktur Digital | J38: Nilai Kualitas Pelaporan Keuangan Unit Akuntansi Kuasa Pengguna Anggaran (UAKPA) Atas Laporan Keuangan Ditjen Infrastruktur Digital Tahun 2025 | K38: 83 Nilai | L38: Y | M38: Y | N38: Y | O38: Y | P38: Y | Q38: sesuai | R38: Y | S38: Y | T38: Y | U38: Y | V38: Y | W38: sesuai
A39: 11 | B39: Meningkatnya kualitas pengelolaan layanan publik Kemenkomdigi | C39: Y | D39: Program Dukungan Manajemen | E39: Meningkatkan efektivitas dan efisiensi pengelolaan birokrasi di Komdigi untuk mendukung transformasi digital nasional | F39: Y | G39: Sekretariat Ditjen Infrastruktur Digital | H39: Pengelolaan Keuangan, BMN dan Umum Direktorat Jenderal Infrastruktur Digital | I39: Meningkatnya kualitas tata kelola internal Ditjen Infrastruktur Digital | J39: Persentase (%) Penyelesaian Tindak Lanjut Hasil Pemeriksaan BPK pada Tahun Berjalan di Ditjen Infrastruktur Digital pada Tahun 2025 | K39: 70 Persen | L39: Y | M39: Y | N39: Y | O39: Y | P39: Y | Q39: sesuai | R39: Y | S39: Y | T39: Y | U39: Y | V39: Y | W39: sesuai
A40: 12 | B40: Meningkatnya kualitas pengelolaan layanan publik Kemenkomdigi | C40: Y | D40: Program Dukungan Manajemen | E40: Meningkatkan efektivitas dan efisiensi pengelolaan birokrasi di Komdigi untuk mendukung transformasi digital nasional | F40: Y | G40: Sekretariat Ditjen Infrastruktur Digital | H40: Pengelolaan Keuangan, BMN dan Umum Direktorat Jenderal Infrastruktur Digital | I40: Meningkatnya kualitas tata kelola internal Ditjen Infrastruktur Digital | J40: Persentase (%) Penyelesaian Tindak Lanjut Hasil Pemeriksaan BPK pada Tahun Sebelumnya di Ditjen Infrastruktur Digital pada Tahun 2025 | K40: 30 Persen | L40: Y | M40: Y | N40: Y | O40: Y | P40: Y | Q40: sesuai | R40: Y | S40: Y | T40: Y | U40: Y | V40: Y | W40: sesuai
... A55: 27 | B55: Mempercepat Penyediaan Sistem dan Jaringan Komunikasi untuk Layanan Khusus Secara Nasional | C55: Y | D55: Program Pengembangan dan Penguatan Infrastruktur Digital | E55: Meningkatnya Pengembangan Industri Perangkat Digital yang Aman | F55: Y | G55: Dit Penataan Spektrum Frekuensi Radio, Orbit Satelit dan Standardisasi Infrastruktur Digital | H55: Penataan Spektrum Frekuensi Radio dan Standarisasi Perangkat Digital | I55: Menguatnya industri perangkat dalam negeri yang aman dan terstandardisasi | J55: Persentase penetapan standar teknis alat/perangkat telekomunikasi | K55: 100 Persen | L55: Y | M55: Y | N55: Y | O55: Y | P55: Y | Q55: Indikator ini menunjukkan bahwa setiap tahun disusun standar teknis perangkat, sehingga perangkat-perangkat yang masuk dan digunakan di Indonesia sesuai dengan standar teknis yang ditetapkan tersebut sehingga tidak menimbulkan interferensi, gangguan antar perangkat dan dapat saling terhubung | R55: Y | S55: Y | T55: Y | U55: Y | V55: Y | W55: Indikator ini menunjukkan bahwa setiap tahun disusun standar teknis perangkat, sehingga perangkat-perangkat yang masuk dan digunakan di Indonesia sesuai dengan standar teknis yang ditetapkan tersebut sehingga tidak menimbulkan interferensi, gangguan antar perangkat dan dapat saling terhubung
A56: 28 | B56: Mempercepat Penyediaan Sistem dan Jaringan Komunikasi untuk Layanan Khusus Secara Nasional | C56: Y | D56: Program Pengembangan dan Penguatan Infrastruktur Digital | E56: Meningkatnya Pengembangan Industri Perangkat Digital yang Aman | F56: Y | G56: Dit Penataan Spektrum Frekuensi Radio, Orbit Satelit dan Standardisasi Infrastruktur Digital | I56: Menguatnya industri perangkat dalam negeri yang aman dan terstandardisasi | J56: Persentase pengembangan industri perangkat digital dalam negeri | K56: 20 Persen | L56: Y | M56: Y | N56: T | O56: T | P56: T | Q56: Persentase pengembangan industri perangkat digital dalam negeri, indikator ini menunjukkan bahwa Dit Infradig mendukung pengembangan industri perangkat digital dalam negeri melalui fasilitasi pengembangan industri perangkat dalam negri dengan target 1 perusahaan setiap tahunnya | R56: Y | S56: Y | T56: T | U56: T | V56: T | W56: Persentase pengembangan industri perangkat digital dalam negeri, indikator ini menunjukkan bahwa Dit Infradig mendukung pengembangan industri perangkat digital dalam negeri melalui fasilitasi pengembangan industri perangkat dalam negri dengan target 1 perusahaan setiap tahunnya
A57: 29 | B57: Mempercepat Penyediaan Sistem dan Jaringan Komunikasi untuk Layanan Khusus Secara Nasional | C57: Y | D57: Program Pengembangan dan Penguatan Infrastruktur Digital | E57: Meningkatnya Pengembangan Industri Perangkat Digital yang Aman | F57: Y | G57: Dit Penataan Spektrum Frekuensi Radio, Orbit Satelit dan Standardisasi Infrastruktur Digital | H57: Penataan Spektrum Frekuensi Radio dan Standarisasi Perangkat Digital | I57: Menguatnya industri perangkat dalam negeri yang aman dan terstandardisasi | J57: Persentase Registrasi Data IMEI untuk Keperluan Pemerintah yang Diproses Tepat Waktu | K57: 90 Persen | L57: Y | M57: Y | N57: Y | O57: Y | P57: Y | Q57: Persentase registrasi IMEI yang diproses tepat waktu, indikator ini menghitung persentase registrasi IMEI yang masuk yamg diproses tepat waktu | R57: Y | S57: Y | T57: Y | U57: Y | V57: Y | W57: Persentase registrasi IMEI yang diproses tepat waktu, indikator ini menghitung persentase registrasi IMEI yang masuk yamg diproses tepat waktu
A58: 30 | B58: Mempercepat Penyediaan Sistem dan Jaringan Komunikasi untuk Layanan Khusus Secara Nasional | C58: Y | D58: Program Pengembangan dan Penguatan Infrastruktur Digital | E58: Meningkatnya Pengembangan Industri Perangkat Digital yang Aman | F58: Y | G58: Dit Penataan Spektrum Frekuensi Radio, Orbit Satelit dan Standardisasi Infrastruktur Digital | H58: Penataan Spektrum Frekuensi Radio dan Standarisasi Perangkat Digital | I58: Menguatnya industri perangkat dalam negeri yang aman dan terstandardisasi | J58: Jumlah layanan Kesesuaian dan Harmonisasi Perangkat Digital | K58: 2 Layanan | L58: Y | M58: Y | N58: Y | O58: Y | P58: Y | Q58: Jumlah layanan kesesuaian dan harmonisasi perangkat digital, indikator ini menunjukan bagaimana pelaksanaan layanan Imei dan Penetapan Balai Uji di Ditjen Infradig | R58: Y | S58: Y | T58: Y | U58: Y | V58: Y | W58: Jumlah layanan kesesuaian dan harmonisasi perangkat digital, indikator ini menunjukan bagaimana pelaksanaan layanan Imei dan Penetapan Balai Uji di Ditjen Infradig
A59: 31 | B59: Mempercepat Penyediaan Sistem dan Jaringan Komunikasi untuk Layanan Khusus Secara Nasional | C59: Y | D59: Program Pengembangan dan Penguatan Infrastruktur Digital | E59: Meningkatnya Akselerasi Penyediaan Infrastruktur dan Sumber Daya untuk Layanan Khusus | F59: Y | G59: Dit Penataan Spektrum Frekuensi Radio, Orbit Satelit dan Standardisasi Infrastruktur Digital | H59: Penataan Spektrum Frekuensi Radio dan Standarisasi Perangkat Digital | I59: Menyediakan alokasi spektrum frekuensi radio untuk kebutuhan layanan khusus dan penyiaran | J59: Jumlah Rekomendasi Kebijakan untuk Harmonisasi dan Inovasi Pemanfaatan Spektrum Frekuensi Radio | K59: 2 Rekomendasi Kebijakan | L59: Y | M59: Y | N59: T | O59: T | P59: T | Q59: Indikator kinerja kurang mendukung sasaran kegiatan | R59: Y | S59: Y | T59: T | U59: T | V59: T | W59: Indikator kinerja kurang mendukung sasaran kegiatan
A60: 32 | B60: Mempercepat Penyediaan Sistem dan Jaringan Komunikasi untuk Layanan Khusus Secara Nasional | C60: Y | D60: Program Pengembangan dan Penguatan Infrastruktur Digital | E60: Meningkatnya Akselerasi Penyediaan Infrastruktur dan Sumber Daya untuk Layanan Khusus | F60: Y | G60: Dit Penataan Spektrum Frekuensi Radio, Orbit Satelit dan Standardisasi Infrastruktur Digital | H60: Penataan Spektrum Frekuensi Radio dan Standarisasi Perangkat Digital | I60: Menyediakan alokasi spektrum frekuensi radio untuk kebutuhan layanan khusus dan penyiaran | J60: Presentase Stasiun Radio Teresterial yang Dinotifikasi | K60: 80 Persen | L60: Y | M60: Y | N60: T | O60: T | P60: T | Q60: Indikator kinerja kurang mendukung sasaran kegiatan | R60: Y | S60: Y | T60: T | U60: T | V60: T | W60: Indikator kinerja kurang mendukung sasaran kegiatan
A61: 33 | B61: Mempercepat Penyediaan Sistem dan Jaringan Komunikasi untuk Layanan Khusus Secara Nasional | C61: Y | D61: Program Pengembangan dan Penguatan Infrastruktur Digital | E61: Meningkatnya Akselerasi Penyediaan Infrastruktur dan Sumber Daya untuk Layanan Khusus | F61: Y | G61: Dit Penataan Spektrum Frekuensi Radio, Orbit Satelit dan Standardisasi Infrastruktur Digital | H61: Penataan Spektrum Frekuensi Radio dan Standarisasi Perangkat Digital | I61: Menyediakan alokasi spektrum frekuensi radio untuk kebutuhan layanan khusus dan penyiaran | J61: Jumlah Layanan khusus dan penyiaran yang ditetapkan dan dioptimalkan pengaturan penggunaan spektrum frekuensi radionya | K61: 1 Layanan | L61: Y | M61: Y | N61: Y | O61: Y | P61: Y | Q61: Indikator kinerja “Jumlah layanan khusus dan penyiaran yang ditetapkan dan dioptimalkan pengaturan penggunaan spektrum frekuensi radionya” menunjukkan bahwa perlu dilakukan pengaturan spektrum frekuensi radio sesuai dengan perkembangan pembahasan di tingkat internasional, bisa mengakomodir pembaruan dari pengaturan yang telah ada sebelumnya maupun penetapan pengaturan baru yang belum pernah ada karena adanya perkembangan teknologi. | R61: Y | S61: Y | T61: Y | U61: Y | V61: Y | W61: Indikator kinerja “Jumlah layanan khusus dan penyiaran yang ditetapkan dan dioptimalkan pengaturan penggunaan spektrum frekuensi radionya” menunjukkan bahwa perlu dilakukan pengaturan spektrum frekuensi radio sesuai dengan perkembangan pembahasan di tingkat internasional, bisa mengakomodir pembaruan dari pengaturan yang telah ada sebelumnya maupun penetapan pengaturan baru yang belum pernah ada karena adanya perkembangan teknologi.
A62: 34 | B62: Mempercepat Penyediaan Konektivitas Broadband Inklusif, Berkualitas, dan Terjangkau | C62: Y | D62: Program Pengembangan dan Penguatan Infrastruktur Digital | E62: Mewujudkan Industri Telekomunikasi dan Data Center yang berkelanjutan | F62: Y | G62: Dit Strategi dan Kebijakan Infrastruktur Digital | H62: Pengembangan Strategi dan Kebijakan Infrastruktur Digital | I62: Meningkatnya Pertumbuhan Industri Telekomunikasi | J62: Pertumbuhan Pendapatan Industri Telekomunikasi | K62: 5 Persen | L62: Y | M62: Y | N62: Y | O62: Y | P62: Y | Q62: Perubahan Renstra :Sasaran Program : Meningkatnya Pertumbuhan Industri Telekomunikasi dan Data Center yang Berkelanjutan Sasaran Kegiatan : Meningkatnya Pertumbuhan Industri Telekomunikasi untuk Mendukung Peningkatan Penggelaran Konektivitas Digital NasionalUntuk mengukur pertumbuhan industri telekomunikasi salah satunya dengan menggunakan parameter pertumbuhan pendapatan industri telekomunikasiPertumbuhan pendapatan industri telekomunikasi diukur berdasarkan parameter total pendapatan penyelenggara telekomunikasi. Pengukuran dilakukan tiap tahun dengan lagging 1 tahun pelaksanaan program. | R62: Y | S62: Y | T62: Y | U62: Y | V62: Y | W62: Perubahan Renstra :Sasaran Program : Meningkatnya Pertumbuhan Industri Telekomunikasi dan Data Center yang Berkelanjutan Sasaran Kegiatan : Meningkatnya Pertumbuhan Industri Telekomunikasi untuk Mendukung Peningkatan Penggelaran Konektivitas Digital NasionalUntuk mengukur pertumbuhan industri telekomunikasi salah satunya dengan menggunakan parameter pertumbuhan pendapatan industri telekomunikasiPertumbuhan pendapatan industri telekomunikasi diukur berdasarkan parameter total pendapatan penyelenggara telekomunikasi. Pengukuran dilakukan tiap tahun dengan lagging 1 tahun pelaksanaan program.
A63: 35 | B63: Mempercepat Penyediaan Konektivitas Broadband Inklusif, Berkualitas, dan Terjangkau | C63: Y | D63: Program Pengembangan dan Penguatan Infrastruktur Digital | E63: Mewujudkan Industri Telekomunikasi dan Data Center yang berkelanjutan | F63: Y | G63: Dit Strategi dan Kebijakan Infrastruktur Digital | H63: Pengembangan Strategi dan Kebijakan Infrastruktur Digital | I63: Meningkatnya Distribusi Lokasi Data Center | J63: Pertumbuhan lokasi data center di Indonesia | K63: 14 Lokasi Data Center (kumulatif) | L63: Y | M63: Y | N63: Y | O63: Y | P63: Y | Q63: Pertumbuhan distribusi lokasi data center secara kumulatif di Indonesia merujuk pada peningkatan jumlah dan distribusi lokasi pusat data (data center) yang dibangun dan dioperasikan di seluruh wilayah Indonesia.Indikator ini berfokus pada pertumbuhan lokasi DC di Indonesia, dimana harapannya DC tidak terpusat pada satu lokasi saja, sehingga ketika terjadi disaster/serangan siber, ada DC di lokasi lain. Selain itu, pada industri DC juga perlu sistem mirroring sehingga penyedia DC didorong memiliki infrastruktur DC tidak hanya di 1 region tetapi juga menyebar ke region lainnya. Hal ini untuk mengurangi latency ke pengguna | R63: Y | S63: Y | T63: Y | U63: Y | V63: Y | W63: Pertumbuhan distribusi lokasi data center secara kumulatif di Indonesia merujuk pada peningkatan jumlah dan distribusi lokasi pusat data (data center) yang dibangun dan dioperasikan di seluruh wilayah Indonesia.Indikator ini berfokus pada pertumbuhan lokasi DC di Indonesia, dimana harapannya DC tidak terpusat pada satu lokasi saja, sehingga ketika terjadi disaster/serangan siber, ada DC di lokasi lain. Selain itu, pada industri DC juga perlu sistem mirroring sehingga penyedia DC didorong memiliki infrastruktur DC tidak hanya di 1 region tetapi juga menyebar ke region lainnya. Hal ini untuk mengurangi latency ke pengguna
A64: 36 | B64: Meningkatnya kualitas pengelolaan layanan publik Kemenkomdigi | C64: Y | D64: Program Pengembangan dan Penguatan Infrastruktur Digital | E64: Meningkatnya Kualitas Layanan Publik Bidang Infrastruktur Digital | F64: Y | G64: Balai Besar Pengujian Perangkat Telekomunikasi | H64: Layanan Publik Bidang Sumber Daya dan Perangkat Digital | I64: Meningkatnya Kualitas Layanan Pengujian Perangkat Digital dan Kalibrasi Alat Ukur | J64: Indeks Kepuasan Masyarakat atas Layanan Pengujian Perangkat Digital dan kalibrasi alat ukur | K64: 3.6 Nilai | L64: Y | M64: Y | N64: Y | O64: Y | P64: Y | Q64: Sesuai | R64: Y | S64: Y | T64: Y | U64: Y | V64: Y | W64: Sesuai
A65: 37 | B65: Meningkatnya kualitas pengelolaan layanan publik Kemenkomdigi | C65: Y | D65: Program Pengembangan dan Penguatan Infrastruktur Digital | E65: Meningkatnya Kualitas Layanan Publik Bidang Infrastruktur Digital | F65: Y | G65: Balai Besar Pengujian Perangkat Telekomunikasi | H65: Layanan Publik Bidang Sumber Daya dan Perangkat Digital | I65: Meningkatnya Kualitas Layanan Pengujian Perangkat Digital dan Kalibrasi Alat Ukur | J65: Indeks Integritas Pelayanan Publik atas layanan pengujian perangkat digital dan kalibrasi alat ukur | K65: 8.5 Nilai | L65: Y | M65: Y | N65: Y | O65: Y | P65: Y | Q65: Sesuai | R65: Y | S65: Y | T65: Y | U65: Y | V65: Y | W65: Sesuai
A66: 38 | B66: Meningkatnya kualitas pengelolaan layanan publik Kemenkomdigi | C66: Y | D66: Program Pengembangan dan Penguatan Infrastruktur Digital | E66: Meningkatnya Kualitas Layanan Publik Bidang Infrastruktur Digital | F66: Y | G66: Balai Besar Pengujian Perangkat Telekomunikasi | H66: Layanan Publik Bidang Sumber Daya dan Perangkat Digital | I66: Meningkatnya Kualitas Layanan Pengujian Perangkat Digital dan Kalibrasi Alat Ukur | J66: Persentase (%) Capaian target PNBP Pengujian Perangkat Digital dan Kalibrasi Alat Ukur | K66: 100 % | L66: Y | M66: Y | N66: Y | O66: Y | P66: Y | Q66: Penjelasan Indikator Saskeg : Salah satu tolak ukur bahwa kualitas layanan pengujian dan kalibrasi meningkat, adalah perolehan PNBP pengujian dan kalibrasi terpenuhi pada akhir tahun mencapa 100% dari target PNBP yang telah ditetapkan, hal ini mengindikasikan bahwa banyak pemohon atau masyarakat datang ke BBPPT untuk mengajukan permohonan pengujian maupun kalibrasi yang disebabkan kepuasan mereka tehadap kualitas pelayanan di BBPPT yang semakin baik. | R66: Y | S66: Y | T66: Y | U66: Y | V66: Y | W66: Penjelasan Indikator Saskeg : Salah satu tolak ukur bahwa kualitas layanan pengujian dan kalibrasi meningkat, adalah perolehan PNBP pengujian dan kalibrasi terpenuhi pada akhir tahun mencapa 100% dari target PNBP yang telah ditetapkan, hal ini mengindikasikan bahwa banyak pemohon atau masyarakat datang ke BBPPT untuk mengajukan permohonan pengujian maupun kalibrasi yang disebabkan kepuasan mereka tehadap kualitas pelayanan di BBPPT yang semakin baik.
A67: 39 | B67: Meningkatnya kualitas pengelolaan layanan publik Kemenkomdigi | C67: Y | D67: Program Pengembangan dan Penguatan Infrastruktur Digital | E67: Meningkatnya Kualitas Layanan Publik Bidang Infrastruktur Digital | F67: Y | G67: Balai Besar Pengujian Perangkat Telekomunikasi | H67: Layanan Publik Bidang Sumber Daya dan Perangkat Digital | I67: Meningkatnya Kualitas Layanan Pengujian Perangkat Digital dan Kalibrasi Alat Ukur | J67: Persentase (%) Pemenuhan SLA Pengujian Perangkat Digital dan Kalibrasi Alat Ukur | K67: 96 % | L67: Y | M67: Y | N67: Y | O67: Y | P67: Y | Q67: Penjelasan Indikator Sasaran Kegiatan :Sasaran kegiatan meningkatnya kualitas layanan pengujian dan kalibrasi alat ukur dapat diukur antara lain dengan melihat persentase pemenuhan Service Level Agreement (SLA) Pengujian dan kaibrasi alat ukur sebesar 96%. Cara menghitungnya adalah membandingkan antara jumlah penyelesaian permohonan pengujian dan kalibrasi sesuai Jangka Waktu Pelaksanaan Pengujian dalam Keputusan Kepala BBPPT Nomor 70 Tahun 2024 tentang Standar Pelayanan BBPPT, dibandingkan dengan jumlah permohonan pengujian dan kalibrasi yang masuk pada tahun berjalan.Jika target pemenuhan SLA tercapai 96%, maka menunjukkan/mengindikasikan bahwa kualitas layanan pengujian perangkat digital dan kalibrasi alat ukur meningkat | R67: Y | S67: Y | T67: Y | U67: Y | V67: Y | W67: Penjelasan Indikator Sasaran Kegiatan :Sasaran kegiatan meningkatnya kualitas layanan pengujian dan kalibrasi alat ukur dapat diukur antara lain dengan melihat persentase pemenuhan Service Level Agreement (SLA) Pengujian dan kaibrasi alat ukur sebesar 96%. Cara menghitungnya adalah membandingkan antara jumlah penyelesaian permohonan pengujian dan kalibrasi sesuai Jangka Waktu Pelaksanaan Pengujian dalam Keputusan Kepala BBPPT Nomor 70 Tahun 2024 tentang Standar Pelayanan BBPPT, dibandingkan dengan jumlah permohonan pengujian dan kalibrasi yang masuk pada tahun berjalan.Jika target pemenuhan SLA tercapai 96%, maka menunjukkan/mengindikasikan bahwa kualitas layanan pengujian perangkat digital dan kalibrasi alat ukur meningkat
A68: 40 | B68: Mempercepat Penyediaan Konektivitas Broadband Inklusif, Berkualitas, dan Terjangkau | C68: Y | D68: Program Pengembangan dan Penguatan Infrastruktur Digital | E68: Meningkatnya Kualitas Internet Broadband Nasional | F68: T | G68: Dit Pengendalian Infrastruktur Digital | H68: Monitoring dan Pengendalian Spektrum Frekuensi Radio, Perangkat Digital dan Kualitas Layanan Telekomunikasi | I68: Meningkatnya kualitas pengendalian spektrum frekuensi radio, perangkat telekomunikasi dan layanan telekomunikasi | J68: Persentase tingkat kepatuhan standar teknis alat dan/atau perangkat telekomunikasi dan digital | K68: 75 Persen | L68: Y | M68: Y | N68: Y | O68: Y | P68: Y | Q68: Penjelasan Indikator Sasaran Kegiatan : indikator kinerja "persentase kepatuhan alat telekomunikasi dan/atau perangkat telekomunikasi yang memenuhi standar teknis" merupakan Prosentase kepatuhan dari pengguna dan penjual alat dan perangkat telekomunikasi yang beredar di masyarakat baik peredaran secara online di e-commerce maupun secara offline yang bersertifikat dan sesuai dengan standar teknis. Diukur per tahun oleh UPT seluruh wilayahRelevansi Sasaran Kegiatan dengan Sasaran Programnya : Sasaran Kegiatan "Meningkatnya kualitas pengendalian spektrum frekuensi radio, perangkat telekomunikasi dan layanan telekomunikasi" mendukung pencapaian sasaran program "Meningkatnya kualitas internet broadband Nasional" karena terwujudnya tertib penggunaan SFR sesuai perijinan, terwujudnya kepatuhan penggunaan alat dan/atau perangkat telekomunikasi serta layanan telekomunikasi mobile dan fixed broadband yang memenuhi standar kualitas pelayanan merupakan faktor penting dalam meningkatnya kualitas internet broadband | R68: Y | S68: Y | T68: Y | U68: Y | V68: Y | W68: Penjelasan Indikator Sasaran Kegiatan : indikator kinerja "persentase kepatuhan alat telekomunikasi dan/atau perangkat telekomunikasi yang memenuhi standar teknis" merupakan Prosentase kepatuhan dari pengguna dan penjual alat dan perangkat telekomunikasi yang beredar di masyarakat baik peredaran secara online di e-commerce maupun secara offline yang bersertifikat dan sesuai dengan standar teknis. Diukur per tahun oleh UPT seluruh wilayahRelevansi Sasaran Kegiatan dengan Sasaran Programnya : Sasaran Kegiatan "Meningkatnya kualitas pengendalian spektrum frekuensi radio, perangkat telekomunikasi dan layanan telekomunikasi" mendukung pencapaian sasaran program "Meningkatnya kualitas internet broadband Nasional" karena terwujudnya tertib penggunaan SFR sesuai perijinan, terwujudnya kepatuhan penggunaan alat dan/atau perangkat telekomunikasi serta layanan telekomunikasi mobile dan fixed broadband yang memenuhi standar kualitas pelayanan merupakan faktor penting dalam meningkatnya kualitas internet broadband
... A73: 45 | B73: Mempercepat Penyediaan Konektivitas Broadband Inklusif, Berkualitas, dan Terjangkau | C73: Y | D73: Program Pengembangan dan Penguatan Infrastruktur Digital | E73: Meningkatnya Kualitas Internet Broadband Nasional | F73: T | G73: Dit Pengendalian Infrastruktur Digital | H73: Monitoring dan Pengendalian Spektrum Frekuensi Radio, Perangkat Digital dan Kualitas Layanan Telekomunikasi | I73: Meningkatnya kualitas pengendalian spektrum frekuensi radio, perangkat telekomunikasi dan layanan telekomunikasi | J73: Persentase kepatuhan alat telekomunikasi dan/atau perangkat telekomunikasi yang memenuhi standar teknis | K73: 100 Persen | L73: Y | M73: Y | N73: Y | O73: Y | P73: Y | Q73: Indikator ini dicapai melalui pengawasan dan pengendalian terhadap peredaran alat dan/atau perangkat telekomunikasi dan digital yang dibuat, dirakit, dan/atau dimasukkan untuk diperdagangkan dan/atau digunakan di wilayah Negara Republik Indonesia. | R73: Y | S73: Y | T73: Y | U73: Y | V73: Y | W73: Indikator ini dicapai melalui pengawasan dan pengendalian terhadap peredaran alat dan/atau perangkat telekomunikasi dan digital yang dibuat, dirakit, dan/atau dimasukkan untuk diperdagangkan dan/atau digunakan di wilayah Negara Republik Indonesia.
A74: Direktorat Jenderal Ekosistem Digital
A75: 1 | B75: Mewujudkan Transformasi Internal Manajemen adaptif dan resilien | C75: Y | D75: Program Dukungan Manajemen | E75: Meningkatkan efektivitas dan efisiensi pengelolaan birokrasi di Komdigi untuk mendukung transformasi digital nasional | F75: T | G75: Sekretariat Ditjen Ekosistem Digital | H75: Pengelolaan Keuangan, BMN dan Umum Direktorat Jenderal Ekosistem Digital | I75: Meningkatnya kualitas tata kelola Ditjen Ekosistem Digital yang transparan,akuntabel, bersih dan efisien | J75: Nilai Indeks Reformasi Birokrasi Ditjen Ekosistem Digital Tahun 2025 | K75: 84 Nilai | L75: Y | M75: Y | N75: Y | O75: Y | P75: Y | Q75: - | R75: Y | S75: Y | T75: Y | U75: Y | V75: Y | W75: -
A76: 2 | B76: Meningkatnya Pertumbuhan Ekonomi dari Pengembangan Ekosistem Digital Nasional | C76: Y | D76: Program Dukungan Manajemen | E76: Meningkatkan efektivitas dan efisiensi pengelolaan birokrasi di Komdigi untuk mendukung transformasi digital nasional | F76: T | G76: Sekretariat Ditjen Ekosistem Digital | H76: Pengelolaan Keuangan, BMN dan Umum Direktorat Jenderal Ekosistem Digital | I76: Meningkatnya kualitas tata kelola Ditjen Ekosistem Digital yang transparan,akuntabel, bersih dan efisien | J76: Nilai Akuntabilitas Kinerja (AKIP) Ditjen Ekosistem Digital Tahun 2025 | K76: 75 Nilai | L76: Y | M76: Y | N76: Y | O76: Y | P76: Y | Q76: - | R76: Y | S76: Y | T76: Y | U76: Y | V76: Y | W76: -
A77: 3 | B77: Meningkatnya Pertumbuhan Ekonomi dari Pengembangan Ekosistem Digital Nasional | C77: Y | D77: Program Pengembangan dan Penguatan Ekosistem dan Ruang Digital | E77: Meningkatkan efektivitas dan efisiensi pengelolaan birokrasi di Komdigi untuk mendukung transformasi digital nasional | F77: T | G77: Sekretariat Ditjen Ekosistem Digital | H77: Pengelolaan Keuangan, BMN dan Umum Direktorat Jenderal Ekosistem Digital | I77: Meningkatnya kualitas tata kelola Ditjen Ekosistem Digital yang transparan,akuntabel, bersih dan efisien | J77: Persentase (%) Batas Tertinggi Temuan Hasil Pemeriksaan BPK di Ditjen Ekosistem Digital Tahun 2025 | K77: 1 Persentase | L77: Y | M77: Y | N77: Y | O77: Y | P77: Y | Q77: - | R77: Y | S77: Y | T77: Y | U77: Y | V77: Y | W77: -
A78: 4 | B78: Meningkatnya Pertumbuhan Ekonomi dari Pengembangan Ekosistem Digital Nasional | C78: Y | D78: Program Dukungan Manajemen | E78: Meningkatkan efektivitas dan efisiensi pengelolaan birokrasi di Komdigi untuk mendukung transformasi digital nasional | F78: T | G78: Sekretariat Ditjen Ekosistem Digital | H78: Pengelolaan Keuangan, BMN dan Umum Direktorat Jenderal Ekosistem Digital | I78: Meningkatnya kualitas tata kelola Ditjen Ekosistem Digital yang transparan,akuntabel, bersih dan efisien | J78: Persentase Penyelesaian Tindak Lanjut Hasil Pemeriksaan BPK Pada Tahun Berjalan di Ditjen Ekosistem Digital pada Tahun 2025 | K78: 70 Persentase | L78: Y | M78: Y | N78: Y | O78: Y | P78: Y | Q78: - | R78: Y | S78: Y | T78: Y | U78: Y | V78: Y | W78: -
A79: 5 | B79: Meningkatnya Pertumbuhan Ekonomi dari Pengembangan Ekosistem Digital Nasional | C79: Y | D79: Program Dukungan Manajemen | E79: Meningkatkan efektivitas dan efisiensi pengelolaan birokrasi di Komdigi untuk mendukung transformasi digital nasional | F79: T | G79: Sekretariat Ditjen Ekosistem Digital | H79: Pengelolaan Keuangan, BMN dan Umum Direktorat Jenderal Ekosistem Digital | I79: Meningkatnya kualitas tata kelola Ditjen Ekosistem Digital yang transparan,akuntabel, bersih dan efisien | J79: Nilai Kinerja Anggaran Ditjen Ekosistem Digital Tahun 2025 | K79: 88 Nilai | L79: Y | M79: Y | N79: Y | O79: Y | P79: Y | Q79: - | R79: Y | S79: Y | T79: Y | U79: Y | V79: Y | W79: -
A80: 6 | B80: Meningkatnya Pertumbuhan Ekonomi dari Pengembangan Ekosistem Digital Nasional | C80: Y | D80: Program Dukungan Manajemen | E80: Meningkatkan efektivitas dan efisiensi pengelolaan birokrasi di Komdigi untuk mendukung transformasi digital nasional | F80: T | G80: Sekretariat Ditjen Ekosistem Digital | H80: Pengelolaan Keuangan, BMN dan Umum Direktorat Jenderal Ekosistem Digital | I80: Meningkatnya kualitas tata kelola Ditjen Ekosistem Digital yang transparan,akuntabel, bersih dan efisien | J80: Persentase Penyelesaian Tindak Lanjut Hasil Pemeriksaan BPK Tahun Pada Sebelumnya di Ditjen Ekosistem Digital pada Tahun 2025 | K80: 30 Persentase | L80: Y | M80: Y | N80: Y | O80: Y | P80: Y | Q80: - | R80: Y | S80: Y | T80: Y | U80: Y | V80: Y | W80: -
A81: 7 | B81: Meningkatnya Pertumbuhan Ekonomi dari Pengembangan Ekosistem Digital Nasional | C81: Y | D81: Program Dukungan Manajemen | E81: Meningkatkan efektivitas dan efisiensi pengelolaan birokrasi di Komdigi untuk mendukung transformasi digital nasional | F81: T | G81: Sekretariat Ditjen Ekosistem Digital | H81: Pengelolaan Keuangan, BMN dan Umum Direktorat Jenderal Ekosistem Digital | I81: Meningkatnya kualitas tata kelola Ditjen Ekosistem Digital yang transparan,akuntabel, bersih dan efisien | J81: Nilai SPIP Ditjen Ekosistem Digital Tahun 2025 | K81: 3.5 Nilai | L81: Y | M81: Y | N81: Y | O81: Y | P81: Y | Q81: - | R81: Y | S81: Y | T81: Y | U81: Y | V81: Y | W81: -
A82: 8 | B82: Mewujudkan Transformasi Internal Manajemen adaptif dan resilien | C82: Y | D82: Program Dukungan Manajemen | E82: Meningkatkan efektivitas dan efisiensi pengelolaan birokrasi di Komdigi untuk mendukung transformasi digital nasional | F82: T | G82: Sekretariat Ditjen Ekosistem Digital | H82: Pengelolaan Keuangan, BMN dan Umum Direktorat Jenderal Ekosistem Digital | I82: Meningkatnya kualitas tata kelola Ditjen Ekosistem Digital yang transparan,akuntabel, bersih dan efisien | J82: Indeks kepuasan pegawai terhadap layanan Dukungan Manajemen Ditjen Ekosistem Digital Tahun 2025 | K82: 3.8 Nilai | L82: Y | M82: Y | N82: Y | O82: Y | P82: Y | Q82: - | R82: Y | S82: Y | T82: Y | U82: Y | V82: Y | W82: -
A83: 9 | B83: Meningkatnya Pertumbuhan Ekonomi dari Pengembangan Ekosistem Digital Nasional | C83: Y | D83: Program Dukungan Manajemen | E83: Meningkatkan efektivitas dan efisiensi pengelolaan birokrasi di Komdigi untuk mendukung transformasi digital nasional | F83: T | G83: Sekretariat Ditjen Ekosistem Digital | H83: Pengelolaan Keuangan, BMN dan Umum Direktorat Jenderal Ekosistem Digital | I83: Meningkatnya kualitas tata kelola Ditjen Ekosistem Digital yang transparan,akuntabel, bersih dan efisien | J83: Nilai Kualitas Pelaporan Keuangan Unit Akuntansi Pembantu Pengguna Anggaran Eselon I (UAPPA E1) | K83: 80 Nilai | L83: Y | M83: Y | N83: Y | O83: Y | P83: Y | Q83: - | R83: Y | S83: Y | T83: Y | U83: Y | V83: Y | W83: -
A84: 10 | B84: Mewujudkan Transformasi Internal Manajemen adaptif dan resilien | C84: Y | D84: Program Pengembangan dan Penguatan Ekosistem dan Ruang Digital | E84: Meningkatkan efektivitas dan efisiensi pengelolaan birokrasi di Komdigi untuk mendukung transformasi digital nasional | F84: T | G84: Sekretariat Ditjen Ekosistem Digital | H84: Pengelolaan Keuangan, BMN dan Umum Direktorat Jenderal Ekosistem Digital | I84: Meningkatnya kualitas tata kelola Ditjen Ekosistem Digital yang transparan,akuntabel, bersih dan efisien | J84: Nilai Kualitas Pelaporan Keuangan Unit Akuntansi Kuasa Pengguna Anggaran (UAKPA) | K84: 80 Nilai | L84: Y | M84: Y | N84: Y | O84: Y | P84: Y | Q84: - | R84: Y | S84: Y | T84: Y | U84: Y | V84: Y | W84: -
A85: 11 | B85: Meningkatnya Pertumbuhan Ekonomi dari Pengembangan Ekosistem Digital Nasional | C85: Y | D85: Program Pengembangan dan Penguatan Ekosistem dan Ruang Digital | E85: Meningkatnya Pertumbuhan Industri Gim dan Startup Digital Nasional | F85: Y | G85: Direktorat Pengembangan Ekosistem Digital | H85: Pengembangan Ekosistem untuk Startup Digital dan Gim Nasional | I85: Meningkatnya Pengembangan Startup Digital | J85: Penambahan Kota yang memiliki Indeks Ekosistem Startup Digital Tier 1 | K85: TBD TBD | L85: Y | M85: Y | N85: Y | O85: Y | P85: Y | Q85: Target pada Dokumen Renja belum ada, namun telah ditetapkan pada Dokumen Perjanjian Kinerja dengan target sebesar 10% | R85: Y | S85: Y | T85: Y | U85: Y | V85: Y | W85: Target pada Dokumen Renja belum ada, namun telah ditetapkan pada Dokumen Perjanjian Kinerja dengan target sebesar 10%
A86: 12 | B86: Meningkatnya Pertumbuhan Ekonomi dari Pengembangan Ekosistem Digital Nasional | C86: Y | D86: Program Pengembangan dan Penguatan Ekosistem dan Ruang Digital | E86: Meningkatnya Pertumbuhan Industri Gim dan Startup Digital Nasional | F86: Y | G86: Direktorat Pengembangan Ekosistem Digital | H86: Pengembangan Ekosistem untuk Startup Digital dan Gim Nasional | I86: Meningkatnya Pengembangan Startup Digital | J86: Rasio Startup yang Berhasil Scale Up | K86: 5 Persen | L86: Y | M86: Y | N86: Y | O86: Y | P86: Y | Q86: - | R86: Y | S86: Y | T86: Y | U86: Y | V86: Y | W86: -
... A90: 16 | B90: Meningkatnya Pertumbuhan Ekonomi dari Pengembangan Ekosistem Digital Nasional | C90: Y | D90: Program Pengembangan dan Penguatan Ekosistem dan Ruang Digital | E90: Meningkatnya Produktivitas di Sektor-sektor Prioritas dengan Pemanfaatan Teknologi Digital | F90: Y | G90: Dit. Kecerdasan Artifisial dan Ekosistem Teknologi Baru | H90: Pengembangan Inovasi Digital dan Teknologi Baru | I90: Meningkatnya Inovasi Digital Berbasis Teknologi Baru | J90: Persentase pertumbuhan inovasi digital berbasis teknologi baru | K90: TBD TBD | L90: Y | M90: Y | N90: Y | O90: Y | P90: Y | Q90: Target pada Dokumen Renja Eksisting belum ada, namun telah diusulkan pada Dokumen Renstra/Renja revisi | R90: Y | S90: Y | T90: Y | U90: Y | V90: Y | W90: Target pada Dokumen Renja Eksisting belum ada, namun telah diusulkan pada Dokumen Renstra/Renja revisi
A91: 17 | B91: Meningkatnya Pertumbuhan Ekonomi dari Pengembangan Ekosistem Digital Nasional | C91: Y | D91: Program Pengembangan dan Penguatan Ekosistem dan Ruang Digital | E91: Meningkatkan efektivitas dan efisiensi pengelolaan birokrasi di Komdigi untuk mendukung transformasi digital nasional | F91: T | G91: Dit. Kecerdasan Artifisial dan Ekosistem Teknologi Baru | H91: Pengembangan Inovasi Digital dan Teknologi Baru | I91: Meningkatnya Inovasi Digital Berbasis Teknologi Baru | J91: Persentase pertumbuhan inovasi digital berbasis greentech | K91: TBD TBD | L91: Y | M91: Y | N91: Y | O91: Y | P91: Y | Q91: Target pada Dokumen Renja Eksisting belum ada, namun telah diusulkan pada Dokumen Renstra/Renja revisi | R91: Y | S91: Y | T91: Y | U91: Y | V91: Y
A92: 18 | B92: Meningkatnya Pertumbuhan Ekonomi dari Pengembangan Ekosistem Digital Nasional | C92: Y | D92: Program Pengembangan dan Penguatan Ekosistem dan Ruang Digital | E92: Meningkatnya Pertumbuhan Industri Pos Logistik dan Penyiaran | F92: Y | G92: Direktorat Pos dan Penyiaran | H92: Pengembangan Industri Pos dan Penyiaran | I92: Meningkatnya Pemerataan Layanan Pos di Seluruh Wilayah Indonesia | J92: Persentase kecamatan yang memiliki titik layanan pos | K92: 69,5 Persen | L92: Y | M92: Y | N92: Y | O92: Y | P92: Y | Q92: - | R92: Y | S92: Y | T92: Y | U92: Y | V92: Y
A93: 19 | B93: Meningkatnya Pertumbuhan Ekonomi dari Pengembangan Ekosistem Digital Nasional | C93: Y | D93: Program Pengembangan dan Penguatan Ekosistem dan Ruang Digital | E93: Meningkatnya Pertumbuhan Industri Pos Logistik dan Penyiaran | F93: Y | G93: Direktorat Pos dan Penyiaran | H93: Pengembangan Industri Pos dan Penyiaran | I93: Meningkatnya Kualitas dan Daya Saing Penyelenggara Pos Logistik | J93: Peningkatan Indeks kualitas regulasi/kebijakan bidang pos logistik | K93: 2 Poin | L93: Y | M93: Y | N93: Y | O93: Y | P93: Y | Q93: - | R93: Y | S93: Y | T93: Y | U93: Y | V93: Y
A94: 20 | B94: Meningkatnya Pertumbuhan Ekonomi dari Pengembangan Ekosistem Digital Nasional | C94: Y | D94: Program Pengembangan dan Penguatan Ekosistem dan Ruang Digital | E94: Meningkatnya Pertumbuhan Industri Pos Logistik dan Penyiaran | F94: Y | G94: Direktorat Pos dan Penyiaran | H94: Pengembangan Industri Pos dan Penyiaran | I94: Meningkatnya Kualitas dan Daya Saing Penyelenggara Pos Logistik | J94: Integrated Index for Postal Development (2IPD) | K94: 60 Poin | L94: Y | M94: Y | N94: Y | O94: Y | P94: Y | Q94: - | R94: Y | S94: Y | T94: Y | U94: Y | V94: Y
A95: 21 | B95: Meningkatnya Pertumbuhan Ekonomi dari Pengembangan Ekosistem Digital Nasional | C95: Y | D95: Program Pengembangan dan Penguatan Ekosistem dan Ruang Digital | E95: Meningkatnya Pertumbuhan Industri Pos Logistik dan Penyiaran | F95: Y | G95: Direktorat Pos dan Penyiaran | H95: Pengembangan Industri Pos dan Penyiaran | I95: Meningkatnya Kualitas dan Daya Saing Penyelenggara Pos Logistik | J95: Indeks Kinerja Industri Pos Nasional | K95: 2,5 Poin | L95: Y | M95: Y | N95: Y | O95: Y | P95: Y | Q95: - | R95: Y | S95: Y | T95: Y | U95: Y | V95: Y
A96: 22 | B96: Meningkatnya Pertumbuhan Ekonomi dari Pengembangan Ekosistem Digital Nasional | C96: Y | D96: Program Pengembangan dan Penguatan Ekosistem dan Ruang Digital | E96: Meningkatnya Pertumbuhan Industri Pos Logistik dan Penyiaran | F96: Y | G96: Direktorat Pos dan Penyiaran | H96: Pengembangan Industri Pos dan Penyiaran | I96: Menguatnya Tata Kelola untuk Mendukung Keberlanjutan Industri Penyiaran | J96: Peningkatan Skor Indeks kualitas regulasi/kebijakan bidang penyiaran | K96: 2 Poin | L96: Y | M96: Y | N96: Y | O96: Y | P96: Y | Q96: - | R96: Y | S96: Y | T96: Y | U96: Y | V96: Y
A97: 23 | B97: Meningkatnya Pertumbuhan Ekonomi dari Pengembangan Ekosistem Digital Nasional | C97: Y | D97: Program Pengembangan dan Penguatan Ekosistem dan Ruang Digital | E97: Meningkatnya Pertumbuhan Industri Pos Logistik dan Penyiaran | F97: Y | G97: Direktorat Pos dan Penyiaran | H97: Pengembangan Industri Pos dan Penyiaran | I97: Menguatnya Tata Kelola untuk Mendukung Keberlanjutan Industri Penyiaran | J97: Indeks kualitas penyelenggaraan penyiaran | K97: TBD TBD | L97: Y | M97: Y | N97: Y | O97: Y | P97: T | Q97: Target kinerja belum ditetapkan | R97: Y | S97: Y | T97: Y | U97: Y | V97: T | W97: Target kinerja belum ditetapkan
A98: 24 | B98: Meningkatnya Pertumbuhan Ekonomi dari Pengembangan Ekosistem Digital Nasional | C98: Y | D98: Program Pengembangan dan Penguatan Ekosistem dan Ruang Digital | E98: Meningkatnya Kualitas Layanan Publik Bidang Ekosistem Digital | F98: Y | G98: Direktorat Layanan Ekosistem Digital | H98: Layanan Publik Bidang Pos Logistik, Penyiaran, Telekomunikasi, dan Informatika | I98: Mendorong Peningkatan Keandalan Layanan Publik Bidang Pos Logistik, Penyiaran, dan Telekomunikasi | J98: Indeks Kepuasan terhadap Layanan Publik bidang Pos | K98: 3,5 Nilai | L98: Y | M98: Y | N98: Y | O98: Y | P98: Y | Q98: - | R98: Y | S98: Y | T98: Y | U98: Y | V98: Y
A99: 25 | B99: Meningkatnya Pertumbuhan Ekonomi dari Pengembangan Ekosistem Digital Nasional | C99: Y | D99: Program Pengembangan dan Penguatan Ekosistem dan Ruang Digital | E99: Meningkatnya Kualitas Layanan Publik Bidang Ekosistem Digital | F99: Y | G99: Direktorat Layanan Ekosistem Digital | H99: Layanan Publik Bidang Pos Logistik, Penyiaran, Telekomunikasi, dan Informatika | I99: Mendorong Peningkatan Keandalan Layanan Publik Bidang Pos Logistik, Penyiaran, dan Telekomunikasi | J99: Indeks Kepuasan terhadap Layanan Publik bidang Penyiaran | K99: 3,5 Nilai | L99: Y | M99: Y | N99: Y | O99: Y | P99: Y | Q99: - | R99: Y | S99: Y | T99: Y | U99: Y | V99: Y
A100: 26 | B100: Meningkatnya Pertumbuhan Ekonomi dari Pengembangan Ekosistem Digital Nasional | C100: Y | D100: Program Pengembangan dan Penguatan Ekosistem dan Ruang Digital | E100: Meningkatnya Kualitas Layanan Publik Bidang Ekosistem Digital | F100: Y | G100: Direktorat Layanan Ekosistem Digital | H100: Layanan Publik Bidang Pos Logistik, Penyiaran, Telekomunikasi, dan Informatika | I100: Mendorong Peningkatan Keandalan Layanan Publik Bidang Pos Logistik, Penyiaran, dan Telekomunikasi | J100: Indeks Kepuasan terhadap Layanan Publik bidang Telekomunikasi | K100: 3,5 Nilai | L100: Y | M100: Y | N100: Y | O100: Y | P100: Y | Q100: - | R100: Y | S100: Y | T100: Y | U100: Y | V100: Y
A101: 27 | B101: Meningkatnya Pertumbuhan Ekonomi dari Pengembangan Ekosistem Digital Nasional | C101: Y | D101: Program Pengembangan dan Penguatan Ekosistem dan Ruang Digital | E101: Meningkatnya Kualitas Layanan Publik Bidang Ekosistem Digital | F101: Y | G101: Direktorat Layanan Ekosistem Digital | H101: Layanan Publik Bidang Pos Logistik, Penyiaran, Telekomunikasi, dan Informatika | I101: Mendorong Peningkatan Keandalan Layanan Publik Bidang Pos Logistik, Penyiaran, dan Telekomunikasi | J101: Persentase (%) Capaian target PNBP Pos | K101: 100 Persen | L101: Y | M101: Y | N101: Y | O101: Y | P101: Y | Q101: - | R101: Y | S101: Y | T101: Y | U101: Y | V101: Y
A102: 28 | B102: Meningkatnya Pertumbuhan Ekonomi dari Pengembangan Ekosistem Digital Nasional | C102: Y | D102: Program Pengembangan dan Penguatan Ekosistem dan Ruang Digital | E102: Meningkatnya Kualitas Layanan Publik Bidang Ekosistem Digital | F102: Y | G102: Direktorat Layanan Ekosistem Digital | H102: Layanan Publik Bidang Pos Logistik, Penyiaran, Telekomunikasi, dan Informatika | I102: Mendorong Peningkatan Keandalan Layanan Publik Bidang Pos Logistik, Penyiaran, dan Telekomunikasi | J102: Persentase (%) Capaian target PNBP Penyiaran | K102: 100 Persen | L102: Y | M102: Y | N102: Y | O102: Y | P102: Y | Q102: - | R102: Y | S102: Y | T102: Y | U102: Y | V102: Y
A103: 29 | B103: Meningkatnya Pertumbuhan Ekonomi dari Pengembangan Ekosistem Digital Nasional | C103: Y | D103: Program Pengembangan dan Penguatan Ekosistem dan Ruang Digital | E103: Meningkatnya Kualitas Layanan Publik Bidang Ekosistem Digital | F103: Y | G103: Direktorat Pengendalian Ekosistem Digital | H103: Pengelolaan data dan pengendalian bidang ekosistem digital | I103: Meningkatnya kepatuhan penyelenggaraan telekomunikasi, pos dan penyiaran | J103: Tingkat Kepatuhan Pemenuhan Kewajiban Penyelenggara Telekomunikasi, Pos logistik, dan Penyiaran | K103: 100 Persen | L103: Y | M103: Y | N103: Y | O103: Y | P103: Y | Q103: - | R103: Y | S103: Y | T103: Y | U103: Y | V103: Y
A104: 30 | B104: Meningkatnya Pertumbuhan Ekonomi dari Pengembangan Ekosistem Digital Nasional | C104: Y | D104: Program Pengembangan dan Penguatan Ekosistem dan Ruang Digital | E104: Meningkatnya Kualitas Layanan Publik Bidang Ekosistem Digital | F104: Y | G104: Direktorat Pengendalian Ekosistem Digital | H104: Pengelolaan data dan pengendalian bidang ekosistem digital | I104: Meningkatnya kepatuhan penyelenggaraan telekomunikasi, pos dan penyiaran | J104: Persentase Realisasi Penerimaan PNBP BHP Telekomunikasi | K104: 100 Persen | L104: Y | M104: Y | N104: Y | O104: Y | P104: Y | Q104: - | R104: Y | S104: Y | T104: Y | U104: Y | V104: Y
A105: 31 | B105: Meningkatnya Pertumbuhan Ekonomi dari Pengembangan Ekosistem Digital Nasional | C105: Y | D105: Program Pengembangan dan Penguatan Ekosistem dan Ruang Digital | E105: Meningkatnya Kualitas Layanan Publik Bidang Ekosistem Digital | F105: Y | G105: Direktorat Pengendalian Ekosistem Digital | H105: Pengelolaan data dan pengendalian bidang ekosistem digital | I105: Meningkatnya kepatuhan penyelenggaraan telekomunikasi, pos dan penyiaran | J105: Persentase Realisasi Penerimaan PNBP Kontribusi Penyelenggaraan LPU | K105: 100 Persen | L105: Y | M105: Y | N105: Y | O105: Y | P105: Y | Q105: - | R105: Y | S105: Y | T105: Y | U105: Y | V105: Y
A106: 32 | B106: Meningkatnya Pertumbuhan Ekonomi dari Pengembangan Ekosistem Digital Nasional | C106: Y | D106: Program Pengembangan dan Penguatan Ekosistem dan Ruang Digital | E106: Meningkatnya Kualitas Layanan Publik Bidang Ekosistem Digital | F106: Y | G106: Direktorat Pengendalian Ekosistem Digital | H106: Pengelolaan data dan pengendalian bidang ekosistem digital | I106: Meningkatnya Kualitas Pengelolaan Data dan Monitoring Kualitas Layanan Bidang Ekosistem Digital | J106: Tingkat ketersediaan data bidang pos logistik | K106: 100 Persen | L106: Y | M106: Y | N106: Y | O106: Y | P106: Y | Q106: - | R106: Y | S106: Y | T106: Y | U106: Y | V106: Y
A107: 33 | B107: Meningkatnya Pertumbuhan Ekonomi dari Pengembangan Ekosistem Digital Nasional | C107: Y | D107: Program Pengembangan dan Penguatan Ekosistem dan Ruang Digital | E107: Meningkatnya Kualitas Layanan Publik Bidang Ekosistem Digital | F107: Y | G107: Direktorat Pengendalian Ekosistem Digital | H107: Pengelolaan data dan pengendalian bidang ekosistem digital | I107: Meningkatnya Kualitas Pengelolaan Data dan Monitoring Kualitas Layanan Bidang Ekosistem Digital | J107: Tingkat kualitas layanan pos logistik | K107: 100 Persen | L107: Y | M107: Y | N107: Y | O107: Y | P107: Y | Q107: - | R107: Y | S107: Y | T107: Y | U107: Y | V107: Y
A108: 34 | B108: Meningkatnya Pertumbuhan Ekonomi dari Pengembangan Ekosistem Digital Nasional | C108: Y | D108: Program Pengembangan dan Penguatan Ekosistem dan Ruang Digital | E108: Meningkatnya Kualitas Layanan Publik Bidang Ekosistem Digital | F108: Y | G108: Direktorat Pengendalian Ekosistem Digital | H108: Pengelolaan data dan pengendalian bidang ekosistem digital | I108: Meningkatnya Kualitas Pengelolaan Data dan Monitoring Kualitas Layanan Bidang Ekosistem Digital | J108: Tingkat ketersediaan data bidang penyiaran | K108: 100 Persen | L108: Y | M108: Y | N108: Y | O108: Y | P108: Y | Q108: - | R108: Y | S108: Y | T108: Y | U108: Y | V108: Y
A109: 35 | B109: Meningkatnya Pertumbuhan Ekonomi dari Pengembangan Ekosistem Digital Nasional | C109: Y | D109: Program Pengembangan dan Penguatan Ekosistem dan Ruang Digital | E109: Meningkatnya Kualitas Layanan Publik Bidang Ekosistem Digital | F109: Y | G109: Direktorat Pengendalian Ekosistem Digital | H109: Pengelolaan data dan pengendalian bidang ekosistem digital | I109: Meningkatnya Kualitas Pengelolaan Data dan Monitoring Kualitas Layanan Bidang Ekosistem Digital | J109: Tingkat kualitas layanan penyiaran | K109: 100 Persen | L109: Y | M109: Y | N109: Y | O109: Y | P109: Y | Q109: - | R109: Y | S109: Y | T109: Y | U109: Y | V109: Y
A110: 36 | B110: Meningkatnya Pertumbuhan Ekonomi dari Pengembangan Ekosistem Digital Nasional | C110: Y | D110: Program Pengembangan dan Penguatan Ekosistem dan Ruang Digital | E110: Meningkatnya Kualitas Layanan Publik Bidang Ekosistem Digital | F110: Y | G110: Direktorat Pengendalian Ekosistem Digital | H110: Pengelolaan data dan pengendalian bidang ekosistem digital | I110: Meningkatnya Kualitas Pengelolaan Data dan Monitoring Kualitas Layanan Bidang Ekosistem Digital | J110: Tingkat ketersediaan data bidang telekomunikasi | K110: 100 Persen | L110: Y | M110: Y | N110: Y | O110: Y | P110: Y | Q110: - | R110: Y | S110: Y | T110: Y | U110: Y | V110: Y
A111: BADAN AKSESIBILITAS TELEKOMUNIKASI DAN INFORMASI
A112: 1 | B112: Mempercepat Penyediaan Konektivitas Broadband Inklusif, Berkualitas, dan Terjangkau | C112: Y | D112: Program Dukungan Manajemen | E112: Meningkatkan efektivitas dan efisiensi pengelolaan birokrasi di Komdigi untuk mendukung transformasi digital nasional | F112: Y | G112: SATUAN PEMERIKSAAN INTERN | H112: Pengelolaan Keuangan, BMN dan Umum BAKTI | I112: Meningkatnya kualitas manajemen keuangan dan BMN yang tertib dan sesuai peraturan perundangan BAKTI | J112: Persentase (%) Batas Tertinggi Temuan Hasil Pemeriksaan BPK di BAKTI Tahun 2025 | K112: 1 Persen | L112: Y | M112: Y | N112: Y | O112: Y | P112: Y | Q112: Sesuai | R112: Y | S112: T | T112: Y | U112: Y | V112: Y
A113: 2 | B113: Mempercepat Penyediaan Konektivitas Broadband Inklusif, Berkualitas, dan Terjangkau | C113: Y | D113: Program Dukungan Manajemen | E113: Meningkatkan efektivitas dan efisiensi pengelolaan birokrasi di Komdigi untuk mendukung transformasi digital nasional | F113: Y | G113: SATUAN PEMERIKSAAN INTERN | H113: Pengelolaan Keuangan, BMN dan Umum BAKTI | I113: Meningkatnya kualitas manajemen keuangan dan BMN yang tertib dan sesuai peraturan perundangan BAKTI | J113: Persentase (%) Penyelesaian Tindak Lanjut Hasil Pemeriksaan BPK Pada Tahun Berjalan di BAKTI pada Tahun 2025 | K113: 70 Persen | L113: Y | M113: Y | N113: Y | O113: Y | P113: Y | Q113: Sesuai | R113: Y | S113: T | T113: Y | U113: Y | V113: Y
A114: 3 | B114: Mempercepat Penyediaan Konektivitas Broadband Inklusif, Berkualitas, dan Terjangkau | C114: Y | D114: Program Dukungan Manajemen | E114: Meningkatkan efektivitas dan efisiensi pengelolaan birokrasi di Komdigi untuk mendukung transformasi digital nasional | F114: Y | G114: SATUAN PEMERIKSAAN INTERN | H114: Pengelolaan Keuangan, BMN dan Umum BAKTI | I114: Meningkatnya kualitas manajemen keuangan dan BMN yang tertib dan sesuai peraturan perundangan BAKTI | J114: Persentase (%) Penyelesaian Tindak Lanjut Hasil Pemeriksaan BPK Tahun Pada Sebelumnya di BAKTI pada Tahun 2025 | K114: 30 Persen | L114: Y | M114: Y | N114: Y | O114: Y | P114: Y | Q114: Sesuai | R114: Y | S114: T | T114: Y | U114: Y | V114: Y
A115: 4 | B115: Mempercepat Penyediaan Konektivitas Broadband Inklusif, Berkualitas, dan Terjangkau | C115: Y | D115: Program Dukungan Manajemen | E115: Meningkatkan efektivitas dan efisiensi pengelolaan birokrasi di Komdigi untuk mendukung transformasi digital nasional | F115: Y | G115: SATUAN PEMERIKSAAN INTERN | H115: Pengelolaan Keuangan, BMN dan Umum BAKTI | I115: Meningkatnya kualitas manajemen keuangan dan BMN yang tertib dan sesuai peraturan perundangan BAKTI | J115: Nilai Maturitas SPIP BAKTI Tahun 2025 | K115: 3 Nilai | L115: Y | M115: Y | N115: Y | O115: Y | P115: Y | Q115: Sesuai | R115: Y | S115: T | T115: Y | U115: Y | V115: Y
A116: 5 | B116: Mempercepat Penyediaan Konektivitas Broadband Inklusif, Berkualitas, dan Terjangkau | C116: Y | D116: Program Dukungan Manajemen | E116: Meningkatkan efektivitas dan efisiensi pengelolaan birokrasi di Komdigi untuk mendukung transformasi digital nasional | F116: Y | G116: DIREKTORAT SUMBER DAYA DAN ADMINISTRASI | H116: Pengelolaan Keuangan, BMN dan Umum BAKTI | I116: Meningkatnya kualitas manajemen keuangan dan BMN yang tertib dan sesuai peraturan perundangan BAKTI | J116: Indeks Kepuasan Pegawai Terhadap layanan Dukungan Manajemen BAKTI Tahun 2025 | K116: 3 Nilai | L116: Y | M116: Y | N116: Y | O116: Y | P116: Y | Q116: Sesuai | R116: Y | S116: T | T116: Y | U116: Y | V116: Y
A117: 6 | B117: Mempercepat Penyediaan Konektivitas Broadband Inklusif, Berkualitas, dan Terjangkau | C117: Y | D117: Program Dukungan Manajemen | E117: Meningkatkan efektivitas dan efisiensi pengelolaan birokrasi di Komdigi untuk mendukung transformasi digital nasional | F117: Y | G117: DIREKTORAT SUMBER DAYA DAN ADMINISTRASI | H117: Pengelolaan Keuangan, BMN dan Umum BAKTI | I117: Meningkatnya kualitas manajemen keuangan dan BMN yang tertib dan sesuai peraturan perundangan BAKTI | J117: Nilai EKA BLU BAKTI Tahun 2025 pada Aplikasi SMART | K117: 83 Nilai | L117: Y | M117: Y | N117: Y | O117: Y | P117: Y | Q117: Sesuai | R117: Y | S117: T | T117: Y | U117: Y | V117: Y
A118: 7 | B118: Mempercepat Penyediaan Konektivitas Broadband Inklusif, Berkualitas, dan Terjangkau | C118: Y | D118: Program Dukungan Manajemen | E118: Meningkatkan efektivitas dan efisiensi pengelolaan birokrasi di Komdigi untuk mendukung transformasi digital nasional | F118: Y | G118: DIREKTORAT KEUANGAN | H118: Pengelolaan Keuangan, BMN dan Umum BAKTI | I118: Meningkatnya kualitas manajemen keuangan dan BMN yang tertib dan sesuai peraturan perundangan BAKTI | J118: Nilai Kualitas Pelaporan Keuangan Unit Akuntansi Kuasa Pengguna Anggaran (UAKPA) | K118: 80 Nilai | L118: Y | M118: Y | N118: Y | O118: Y | P118: Y | Q118: Sesuai | R118: Y | S118: T | T118: T | U118: Y | V118: Y
A119: 8 | B119: Mempercepat Penyediaan Konektivitas Broadband Inklusif, Berkualitas, dan Terjangkau | C119: Y | D119: Program Pengembangan dan Penguatan Infrastruktur Digital | E119: Meningkatnya cakupan dan kualitas layanan broadband di wilayah non komersial | F119: Y | G119: DIREKTORAT INFRASTRUKTUR | H119: Penyediaan dan Pengelolaan Infrastruktur Telekomunikasi dan Informasi | I119: Terselenggaranya Aksesibilitas Telekomunikasi dan Informasi di Wilayah Pelayanan Universal Telekomunikasi dan Informatika | J119: Jumlah Lokasi Yang Terjangkau Jaringan Bergerak Seluler (Base Tranceiver Station/Lastmile 4 di Daerah 3T (Kumulatif) | K119: 7.300 Lokasi | L119: Y | M119: Y | N119: Y | O119: Y | P119: Y | Q119: Sesuai | R119: T | S119: Y | T119: T | U119: Y | V119: Y
A120: 9 | B120: Mempercepat Penyediaan Konektivitas Broadband Inklusif, Berkualitas, dan Terjangkau | C120: Y | D120: Program Pengembangan dan Penguatan Infrastruktur Digital | E120: Meningkatnya cakupan dan kualitas layanan broadband di wilayah non komersial | F120: Y | G120: DIREKTORAT INFRASTRUKTUR | H120: Penyediaan dan Pengelolaan Infrastruktur Telekomunikasi dan Informasi | I120: Terselenggaranya Aksesibilitas Telekomunikasi dan Informasi di Wilayah Pelayanan Universal Telekomunikasi dan Informatika | J120: Jumlah Kapasitas Penyediaan Satelit Multifungsi (SATRIA) (Kumulatif) | K120: 150 Gbps | L120: Y | M120: Y | N120: Y | O120: Y | P120: Y | Q120: Sesuai | R120: T | S120: Y | T120: T | U120: Y | V120: Y
A121: 10 | B121: Mempercepat Penyediaan Konektivitas Broadband Inklusif, Berkualitas, dan Terjangkau | C121: Y | D121: Program Pengembangan dan Penguatan Infrastruktur Digital | E121: Meningkatnya cakupan dan kualitas layanan broadband di wilayah non komersial | F121: Y | G121: DIREKTORAT INFRASTRUKTUR | H121: Penyediaan dan Pengelolaan Infrastruktur Telekomunikasi dan Informasi | I121: Terselenggaranya Aksesibilitas Telekomunikasi dan Informasi di Wilayah Pelayanan Universal Telekomunikasi dan Informatika | J121: Jumlah lokasi ketersediaan akses internet di wilayah Tertinggal, Terdepan, Terluar, kawasan prioritas, dan lokasi layanan publik (kumulatif) | K121: 36.830 Lokasi | L121: Y | M121: Y | N121: Y | O121: Y | P121: Y | Q121: Sesuai | R121: T | S121: Y | T121: T | U121: Y | V121: Y
...

Sheet KK 2.2 RO
A1: KKE 2.2 - RINCIAN OUTPUT
A2: PENILAIAN MANDIRI MATURITAS PENYELENGGARAAN SPIP TERINTEGRASI KEMENTERIAN KOMUNIKASI DAN INFORMATIKA Periode Penilaian sampai dengan 30 Juni 2023
A3: KK 2.2 - PENILAIAN PENETAPAN TUJUAN - RINCIAN OUTPUT
A4: NO | B4: SASARAN STRATEGIS KL | D4: SASARAN PROGRAM | G4: SASARAN KEGIATAN | K4: NO | L4: RINCIAN OUTPUT | M4: INDIKATOR KINERJA | N4: TARGET KINERJA | S4: KETERANGAN | T4: PENJAMIN KUALITAS | X4: KETERANGAN
B5: URAIAN SASARAN STRATEGIS | C5: SASTRA RELEVAN DAN MENGGAMBARKAN MANDAT | D5: NAMA PROGRAM | E5: URAIAN SASARAN PROGRAM | F5: SASPRO RELEVAN DENGAN SASTRA DAN MENGGAMBARKAN TUGAS DAN FUNGSI | G5: UNIT KERJA | H5: NAMA KEGIATAN | I5: URAIAN SASARAN KEGIATAN | J5: SASARAN KEGIATAN RELEVAN DENGAN SASPRO DAN MENGGAMBARKAN TUGAS DAN FUNGSI | O5: RINCIAN OUTPUT RELEVAN DENGAN SASARAN KEGIATAN | P5: INDIKATOR KINERJA TEPAT | Q5: UJI KECUKUPAN INDIKATOR | R5: TARGET KINERJA TEPAT | T5: RINCIAN OUTPUT RELEVAN DENGAN SASARAN KEGIATAN | U5: INDIKATOR KINERJA TEPAT | V5: UJI KECUKUPAN INDIKATOR | W5: TARGET KINERJA TEPAT
A6: =0+1 -> 1 | B6: =A6+1 -> 2 | C6: =B6+1 -> 3 | D6: =C6+1 -> 4 | E6: =D6+1 -> 5 | F6: =E6+1 -> 6 | G6: =F6+1 -> 7 | H6: =G6+1 -> 8 | I6: =H6+1 -> 9 | ... S6: =R6+1 -> 19 | T6: 15 | U6: 16 | V6: =U6+1 -> 17 | W6: =V6+1 -> 18 | X6: =W6+1 -> 19
A7: Direktorat Jenderal Komunikasi Publik dan Media
A8: 1 | B8: Meningkatnya efektivitas penyelenggaraan informasi dan komunikasi publik | D8: Program Komunikasi Publik dan Media | E8: Meningkatnya efektivitas penyelenggaraan komunikasi publik nasional | G8: Monumen Pers Nasional (Solo) | H8: Penguatan Komunikasi dan Informasi Publik Nasional | I8: Terselenggaranya Layanan pemanfaatan informasi media cetak dan koleksi benda bersejarah bagi masyarakat | J8: Y | L8: Layanan Pemanfaatan Informasi Media Cetak dan Koleksi Benda Bersejarah Bagi Masyarakat | M8: Layanan Pemanfaatan Informasi Media Cetak dan Koleksi Benda Bersejarah Bagi Masyarakat | N8: 100000 Orang | O8: Y | P8: Y | Q8: Y | R8: Y | T8: Y | U8: Y | V8: Y | W8: Y | X8: Sesaio
A9: 2 | B9: Meningkatnya efektivitas penyelenggaraan informasi dan komunikasi publik | D9: Program Komunikasi Publik dan Media | E9: Meningkatnya efektivitas penyelenggaraan komunikasi publik nasional | G9: Direktorat Informasi Publik | H9: Penguatan Komunikasi dan Informasi Publik Nasional | I9: Menyediakan Konten Informasi Publik yang Berkualitas, Relevan, dan Kredibel | J9: Y | L9: Rancangan Peraturan Menteri tentang Layanan Komunikasi dan Informasi Publik Berbasis Digital bagi Penyandang Disabilitas | M9: Rancangan Peraturan Menteri tentang Layanan Komunikasi dan Informasi Publik Berbasis Digital bagi Penyandang Disabilitas | N9: 1 Rancangan PerMen | O9: Y | P9: Y | Q9: Y | R9: Y | T9: Y | U9: Y | V9: Y | W9: Y | X9: Sesuai
A10: 3 | B10: Meningkatnya efektivitas penyelenggaraan informasi dan komunikasi publik | D10: Program Komunikasi Publik dan Media | E10: Meningkatnya efektivitas penyelenggaraan komunikasi publik nasional | G10: Direktorat Informasi Publik | H10: Penguatan Komunikasi dan Informasi Publik Nasional | I10: Menyediakan Konten Informasi Publik yang Berkualitas, Relevan, dan Kredibel | J10: Y | L10: Sosialisasi dan Bimtek Kebijakan Standardisasi Pengelolaan Akses dan Aset Konten Informasi Publik | M10: Sosialisasi dan Bimtek Kebijakan Standardisasi Pengelolaan Akses dan Aset Konten Informasi Publik | N10: 700 Orang | O10: Y | P10: Y | Q10: Y | R10: Y | T10: Y | U10: Y | V10: Y | W10: Y | X10: Sesuai
A11: 4 | B11: Meningkatnya efektivitas penyelenggaraan informasi dan komunikasi publik | D11: Program Komunikasi Publik dan Media | E11: Meningkatnya efektivitas penyelenggaraan komunikasi publik nasional | G11: Direktorat Informasi Publik | H11: Penguatan Komunikasi dan Informasi Publik Nasional | I11: Menyediakan Konten Informasi Publik yang Berkualitas, Relevan, dan Kredibel | J11: Y | L11: NSPK Pengelolaan Akses dan Aset Konten Informasi Publik | M11: NSPK Pengelolaan Akses dan Aset Konten Informasi Publik | N11: 1 NSPK | O11: Y | P11: Y | Q11: Y | R11: Y | T11: Y | U11: Y | V11: Y | W11: Y | X11: Sesuai
A12: 5 | B12: Meningkatnya efektivitas penyelenggaraan informasi dan komunikasi publik | D12: Program Komunikasi Publik dan Media | E12: Meningkatnya efektivitas penyelenggaraan komunikasi publik nasional | G12: Direktorat Informasi Publik | H12: Penguatan Komunikasi dan Informasi Publik Nasional | I12: Menyediakan Konten Informasi Publik yang Berkualitas, Relevan, dan Kredibel | J12: Y | L12: NSPK Standarisasi Konten Program Prioritas Pemerintah | M12: NSPK Standarisasi Konten Program Prioritas Pemerintah | N12: 1 NSPK | O12: Y | P12: Y | Q12: Y | R12: Y | T12: Y | U12: Y | V12: Y | W12: Y | X12: Sesuai
A13: 6 | B13: Meningkatnya efektivitas penyelenggaraan informasi dan komunikasi publik | D13: Program Komunikasi Publik dan Media | E13: Meningkatnya efektivitas penyelenggaraan komunikasi publik nasional | G13: Direktorat Informasi Publik | H13: Penguatan Komunikasi dan Informasi Publik Nasional | I13: Menyediakan Konten Informasi Publik yang Berkualitas, Relevan, dan Kredibel | J13: Y | L13: Pengelolaan Konten Kontra Narasi | M13: Pengelolaan Konten Kontra Narasi | N13: xxx Kegiatan | O13: Y | P13: Y | Q13: Y | R13: Y | T13: Y | U13: Y | V13: Y | W13: Y | X13: Sesuai
A14: 7 | B14: Meningkatnya efektivitas penyelenggaraan informasi dan komunikasi publik | D14: Program Komunikasi Publik dan Media | E14: Meningkatnya efektivitas penyelenggaraan komunikasi publik nasional | G14: Direktorat Informasi Publik | H14: Penguatan Komunikasi dan Informasi Publik Nasional | I14: Menyediakan Konten Informasi Publik yang Berkualitas, Relevan, dan Kredibel | J14: Y | L14: Konten Informasi Publik Program Prioritas Pemerintah | M14: Konten Informasi Publik Program Prioritas Pemerintah | N14: xxx Kegiatan | O14: Y | P14: Y | Q14: Y | R14: Y | T14: Y | U14: Y | V14: Y | W14: Y | X14: SESUAI
A15: 8 | B15: Meningkatnya efektivitas penyelenggaraan informasi dan komunikasi publik | D15: Program Komunikasi Publik dan Media | E15: Meningkatnya efektivitas penyelenggaraan komunikasi publik nasional | G15: Direktorat Informasi Publik | H15: Penguatan Komunikasi dan Informasi Publik Nasional | I15: Menyediakan Konten Informasi Publik yang Berkualitas, Relevan, dan Kredibel | J15: Y | L15: Layanan Manajemen Aset dan Aksesibilitas Konten Informasi Publik | M15: Layanan Manajemen Aset dan Aksesibilitas Konten Informasi Publik | N15: xxx Kegiatan | O15: Y | P15: Y | Q15: Y | R15: Y | T15: Y | U15: Y | V15: Y | W15: Y | X15: Sesuai
A16: 9 | B16: Meningkatnya efektivitas penyelenggaraan informasi dan komunikasi publik | D16: Program Komunikasi Publik dan Media | E16: Meningkatnya efektivitas penyelenggaraan komunikasi publik nasional | G16: Direktorat Informasi Publik | H16: Penguatan Komunikasi dan Informasi Publik Nasional | I16: Menyediakan Konten Informasi Publik yang Berkualitas, Relevan, dan Kredibel | J16: Y | L16: Monitoring Isu dalam Pengelolaan Komunikasi Publik | M16: Monitoring Isu dalam Pengelolaan Komunikasi Publik | N16: xxx Kegiatan | O16: Y | P16: Y | Q16: Y | R16: Y | T16: Y | U16: Y | V16: Y | W16: Y | X16: Sesuai
A17: 10 | B17: Meningkatnya efektivitas penyelenggaraan informasi dan komunikasi publik | D17: Program Komunikasi Publik dan Media | E17: Meningkatnya efektivitas penyelenggaraan komunikasi publik nasional | G17: Direktorat Informasi Publik | H17: Penguatan Komunikasi dan Informasi Publik Nasional | I17: Menyediakan Konten Informasi Publik yang Berkualitas, Relevan, dan Kredibel | J17: Y | L17: Monitoring dan Evaluasi Kualitas Konten Informasi K/L/D | M17: Monitoring dan Evaluasi Kualitas Konten Informasi K/L/D | N17: xxx Kegiatan | O17: Y | P17: Y | Q17: Y | R17: Y | T17: Y | U17: Y | V17: Y | W17: Y | X17: Sesuai
A18: 11 | B18: Meningkatnya efektivitas penyelenggaraan informasi dan komunikasi publik | D18: Program Komunikasi Publik dan Media | E18: Meningkatnya efektivitas penyelenggaraan komunikasi publik nasional | G18: Direktorat Informasi Publik | H18: Penguatan Komunikasi dan Informasi Publik Nasional | I18: Menyediakan Konten Informasi Publik yang Berkualitas, Relevan, dan Kredibel | J18: Y | L18: Aplikasi Monitoring Isu Berbagi Pakai | M18: Aplikasi Monitoring Isu Berbagi Pakai | N18: 1 Sistem Informasi | O18: Y | P18: Y | Q18: Y | R18: Y | T18: Y | U18: Y | V18: Y | W18: Y | X18: Sesuai
A19: 12 | B19: Meningkatnya efektivitas penyelenggaraan informasi dan komunikasi publik | D19: Program Komunikasi Publik dan Media | E19: Meningkatnya efektivitas penyelenggaraan komunikasi publik nasional | G19: Direktorat Informasi Publik | H19: Penguatan Komunikasi dan Informasi Publik Nasional | I19: Menyediakan Konten Informasi Publik yang Berkualitas, Relevan, dan Kredibel | J19: Y | L19: Aplikasi Umum Layanan Informasi Publik Bagi K/L/D | M19: Aplikasi Umum Layanan Informasi Publik Bagi K/L/D | N19: 1 Sistem Informasi | O19: Y | P19: Y | Q19: Y | R19: Y | T19: Y | U19: Y | V19: Y | W19: Y | X19: Sesuai
A20: 13 | B20: Meningkatnya efektivitas penyelenggaraan informasi dan komunikasi publik | D20: Program Komunikasi Publik dan Media | E20: Meningkatnya keterbukaan informasi publik | G20: Direktorat Informasi Publik | H20: Penguatan Komunikasi dan Informasi Publik Nasional | I20: Kepatuhan Dalam Pelaksanaan Keterbukaan Informasi Publik | J20: Y | L20: Rancangan Revisi UU KIP | M20: Rancangan Revisi UU KIP | N20: 1 RUU | O20: Y | P20: Y | Q20: Y | R20: Y | T20: Y | U20: Y | V20: Y | W20: Y | X20: Sesuai
A21: 14 | B21: Meningkatnya efektivitas penyelenggaraan informasi dan komunikasi publik | D21: Program Komunikasi Publik dan Media | E21: Meningkatnya keterbukaan informasi publik | G21: Direktorat Informasi Publik | H21: Penguatan Komunikasi dan Informasi Publik Nasional | I21: Kepatuhan Dalam Pelaksanaan Keterbukaan Informasi Publik | J21: Y | L21: Bimtek PPID | M21: Bimtek PPID | N21: 400 Orang | O21: Y | P21: Y | Q21: Y | R21: Y | T21: Y | U21: Y | V21: Y | W21: Y
A22: 15 | B22: Meningkatnya efektivitas penyelenggaraan informasi dan komunikasi publik | D22: Program Komunikasi Publik dan Media | E22: Meningkatnya efektivitas penyelenggaraan komunikasi publik nasional | G22: Direktorat Komunikasi Publik | H22: Penguatan Komunikasi dan Informasi Publik Nasional | I22: Meningkatnya kualitas tata kelola dan penyelenggaraan komunikasi publik | J22: Y | L22: Rancangan Peraturan Presiden Sistem Komunikasi Publik Nasional (SKPN) | M22: Rancangan Peraturan Presiden Sistem Komunikasi Publik Nasional (SKPN) | N22: 1 R.Perpres | O22: Y | P22: Y | Q22: Y | R22: Y | T22: Y | U22: Y | V22: Y | W22: Y
A23: 16 | B23: Meningkatnya efektivitas penyelenggaraan informasi dan komunikasi publik | D23: Program Komunikasi Publik dan Media | E23: Meningkatnya efektivitas penyelenggaraan komunikasi publik nasional | G23: Direktorat Komunikasi Publik | H23: Penguatan Komunikasi dan Informasi Publik Nasional | I23: Meningkatnya kualitas tata kelola dan penyelenggaraan komunikasi publik | J23: Y | L23: Rekomendasi Hasil Survey Indeks KPIP | M23: Rekomendasi Hasil Survey Indeks KPIP | N23: 1 Rekomendasi Kebijakan | O23: Y | P23: Y | Q23: Y | R23: Y | T23: Y | U23: Y | V23: Y | W23: Y
A24: 17 | B24: Meningkatnya efektivitas penyelenggaraan informasi dan komunikasi publik | D24: Program Komunikasi Publik dan Media | E24: Meningkatnya efektivitas penyelenggaraan komunikasi publik nasional | G24: Direktorat Komunikasi Publik | H24: Penguatan Komunikasi dan Informasi Publik Nasional | I24: Meningkatnya kualitas tata kelola dan penyelenggaraan komunikasi publik | J24: Y | L24: NSPK Bidang Konkuren Komunikasi Publik | M24: NSPK Bidang Konkuren Komunikasi Publik | N24: 1 NSPK | O24: Y | P24: Y | Q24: Y | R24: Y | T24: Y | U24: Y | V24: Y | W24: Y
A25: 18 | B25: Meningkatnya efektivitas penyelenggaraan informasi dan komunikasi publik | D25: Program Komunikasi Publik dan Media | E25: Meningkatnya efektivitas penyelenggaraan komunikasi publik nasional | G25: Direktorat Komunikasi Publik | H25: Penguatan Komunikasi dan Informasi Publik Nasional | I25: Meningkatnya kualitas tata kelola dan penyelenggaraan komunikasi publik | J25: Y | L25: NSPK Bidang Komunikasi Publik | M25: NSPK Bidang Komunikasi Publik | N25: 3 NSPK | O25: Y | P25: Y | Q25: Y | R25: Y | T25: Y | U25: Y | V25: Y | W25: Y | X25: Sesuai
A26: 19 | B26: Meningkatnya efektivitas penyelenggaraan informasi dan komunikasi publik | D26: Program Komunikasi Publik dan Media | E26: Meningkatnya efektivitas penyelenggaraan komunikasi publik nasional | G26: Direktorat Komunikasi Publik | H26: Penguatan Komunikasi dan Informasi Publik Nasional | I26: Meningkatnya kualitas tata kelola dan penyelenggaraan komunikasi publik | J26: Y | L26: Rencana Komunikasi Strategis Pemerintah Tahunan | M26: Rencana Komunikasi Strategis Pemerintah Tahunan | N26: 8 Dokumen | O26: Y | P26: Y | Q26: Y | R26: Y | T26: Y | U26: Y | V26: Y | W26: Y | X26: sesuai
A27: 20 | B27: Meningkatnya efektivitas penyelenggaraan informasi dan komunikasi publik | D27: Program Komunikasi Publik dan Media | E27: Meningkatnya efektivitas penyelenggaraan komunikasi publik nasional | G27: Direktorat Komunikasi Publik | H27: Penguatan Komunikasi dan Informasi Publik Nasional | I27: Meningkatnya kualitas tata kelola dan penyelenggaraan komunikasi publik | J27: Y | L27: Bimbingan Teknis Implementasi Sub Urusan Komunikasi dan Informasi | M27: Bimbingan Teknis Implementasi Sub Urusan Komunikasi dan Informasi | N27: 2000 Orang | O27: Y | P27: Y | Q27: Y | R27: Y | T27: Y | U27: Y | V27: Y | W27: Y | X27: sesuai
A28: 21 | B28: Meningkatnya efektivitas penyelenggaraan informasi dan komunikasi publik | D28: Program Komunikasi Publik dan Media | E28: Meningkatnya efektivitas penyelenggaraan komunikasi publik nasional | G28: Direktorat Komunikasi Publik | H28: Penguatan Komunikasi dan Informasi Publik Nasional | I28: Meningkatnya kualitas tata kelola dan penyelenggaraan komunikasi publik | J28: Y | L28: Pengelolaan Komunikasi Strategis Pemerintah | M28: Pengelolaan Komunikasi Strategis Pemerintah | N28: 12 Kegiatan | O28: Y | P28: Y | Q28: Y | R28: Y | T28: Y | U28: Y | V28: Y | W28: Y
A29: 22 | B29: Meningkatnya efektivitas penyelenggaraan informasi dan komunikasi publik | D29: Program Komunikasi Publik dan Media | E29: Meningkatnya efektivitas penyelenggaraan komunikasi publik nasional | G29: Direktorat Komunikasi Publik | H29: Penguatan Komunikasi dan Informasi Publik Nasional | I29: Meningkatnya kualitas tata kelola dan penyelenggaraan komunikasi publik | J29: Y | L29: Pengelolaan Krisis Komunikasi Nasional | M29: Pengelolaan Krisis Komunikasi Nasional | N29: 8 Dokumen | O29: Y | P29: Y | Q29: Y | R29: Y | T29: Y | U29: Y | V29: Y | W29: Y | X29: sesuai
A30: 23 | B30: Meningkatnya efektivitas penyelenggaraan informasi dan komunikasi publik | D30: Program Komunikasi Publik dan Media | E30: Meningkatnya efektivitas penyelenggaraan komunikasi publik nasional | G30: Direktorat Komunikasi Publik | H30: Penguatan Komunikasi dan Informasi Publik Nasional | I30: Meningkatnya kualitas tata kelola dan penyelenggaraan komunikasi publik | J30: Y | L30: Pengelolaan dan Diseminasi Informasi Terkait Makan Siang Bergizi | M30: Pengelolaan dan Diseminasi Informasi Terkait Makan Siang Bergizi | N30: 13818750 Orang | O30: Y | P30: Y | Q30: Y | R30: Y | T30: Y | U30: Y | V30: Y | W30: Y | X30: sesuai
A31: 24 | B31: Meningkatnya efektivitas penyelenggaraan informasi dan komunikasi publik | D31: Program Komunikasi Publik dan Media | E31: Meningkatnya efektivitas penyelenggaraan komunikasi publik nasional | G31: Direktorat Kemitraan Komunikasi Lembaga dan Kehumasan | H31: Pengembangan Ekosistem Media, Kehumasan, dan Kemitraan Komunikasi Publik | I31: Penguatan Kehumasan dan Kemitraan Komunikasi Publik | J31: Y | L31: Pedoman Kemitraan Lembaga Informasi dan Kehumasan | M31: Pedoman Kemitraan Lembaga Informasi dan Kehumasan | N31: 1 Pedoman | O31: Y | P31: Y | Q31: Y | R31: Y | T31: Y | U31: Y | V31: Y | W31: Y | X31: sesuai
A32: 25 | B32: Meningkatnya efektivitas penyelenggaraan informasi dan komunikasi publik | D32: Program Komunikasi Publik dan Media | E32: Meningkatnya efektivitas penyelenggaraan komunikasi publik nasional | G32: Direktorat Kemitraan Komunikasi Lembaga dan Kehumasan | H32: Pengembangan Ekosistem Media, Kehumasan, dan Kemitraan Komunikasi Publik | I32: Penguatan Kehumasan dan Kemitraan Komunikasi Publik | J32: Y | L32: Rancangan Peraturan Menteri Komdigi terkait Pengembangan Kemitraan Kehumasan Pemerintah | M32: Rancangan Peraturan Menteri Komdigi terkait Pengembangan Kemitraan Kehumasan Pemerintah | N32: 1 R. Permen | O32: Y | P32: Y | Q32: Y | R32: Y | T32: Y | U32: Y | V32: Y | W32: Y | X32: sesuai
A33: 26 | B33: Meningkatnya efektivitas penyelenggaraan informasi dan komunikasi publik | D33: Program Komunikasi Publik dan Media | E33: Meningkatnya efektivitas penyelenggaraan komunikasi publik nasional | G33: Direktorat Kemitraan Komunikasi Lembaga dan Kehumasan | H33: Pengembangan Ekosistem Media, Kehumasan, dan Kemitraan Komunikasi Publik | I33: Penguatan Kehumasan dan Kemitraan Komunikasi Publik | J33: Y | L33: Rancangan Peraturan Menteri Komdigi terkait Pengembangan Kemitraan Komunikasi Strategis | M33: Rancangan Peraturan Menteri Komdigi terkait Pengembangan Kemitraan Komunikasi Strategis | N33: 1 R. Permen | O33: Y | P33: Y | Q33: Y | R33: Y | T33: Y | U33: Y | V33: Y | W33: Y
A34: 27 | B34: Meningkatnya efektivitas penyelenggaraan informasi dan komunikasi publik | D34: Program Komunikasi Publik dan Media | E34: Meningkatnya efektivitas penyelenggaraan komunikasi publik nasional | G34: Direktorat Kemitraan Komunikasi Lembaga dan Kehumasan | H34: Pengembangan Ekosistem Media, Kehumasan, dan Kemitraan Komunikasi Publik | I34: Penguatan Kehumasan dan Kemitraan Komunikasi Publik | J34: Y | L34: Kebijakan terkait Pranata Humas | M34: Kebijakan terkait Pranata Humas | N34: 1 Rekomendasi Kebijakan | O34: Y | P34: Y | Q34: Y | R34: Y | T34: Y | U34: Y | V34: Y | W34: Y | X34: sesuai
A35: 28 | B35: Meningkatnya efektivitas penyelenggaraan informasi dan komunikasi publik | D35: Program Komunikasi Publik dan Media | E35: Meningkatnya efektivitas penyelenggaraan komunikasi publik nasional | G35: Direktorat Kemitraan Komunikasi Lembaga dan Kehumasan | H35: Pengembangan Ekosistem Media, Kehumasan, dan Kemitraan Komunikasi Publik | I35: Penguatan Kehumasan dan Kemitraan Komunikasi Publik | J35: Y | L35: Aplikasi Kompetensi dan Karir JF Pranata Humas | M35: Aplikasi Kompetensi dan Karir JF Pranata Humas | N35: 1 Sistem Informasi | O35: Y | P35: Y | Q35: Y | R35: Y | T35: Y | U35: Y | V35: Y | W35: Y | X35: sesuai
A36: 29 | B36: Meningkatnya efektivitas penyelenggaraan informasi dan komunikasi publik | D36: Program Komunikasi Publik dan Media | E36: Meningkatnya efektivitas penyelenggaraan komunikasi publik nasional | G36: Direktorat Kemitraan Komunikasi Lembaga dan Kehumasan | H36: Pengembangan Ekosistem Media, Kehumasan, dan Kemitraan Komunikasi Publik | I36: Penguatan Kehumasan dan Kemitraan Komunikasi Publik | J36: Y | L36: Kemitraan Kelembagaan Kehumasan Pemerintah (K/L/D) | M36: Kemitraan Kelembagaan Kehumasan Pemerintah (K/L/D) | N36: 100 Lembaga | O36: Y | P36: Y | Q36: Y | R36: Y | T36: Y | U36: Y | V36: Y | W36: Y | X36: Sesuai
A37: 30 | B37: Meningkatnya efektivitas penyelenggaraan informasi dan komunikasi publik | D37: Program Komunikasi Publik dan Media | E37: Meningkatnya efektivitas penyelenggaraan komunikasi publik nasional | G37: Direktorat Kemitraan Komunikasi Lembaga dan Kehumasan | H37: Pengembangan Ekosistem Media, Kehumasan, dan Kemitraan Komunikasi Publik | I37: Penguatan Kehumasan dan Kemitraan Komunikasi Publik | J37: Y | L37: Kemitraan Komunikasi Publik dengan Mitra Strategis | M37: Kemitraan Komunikasi Publik dengan Mitra Strategis | N37: 150 Lembaga | O37: Y | P37: Y | Q37: Y | R37: Y | T37: Y | U37: Y | V37: Y | W37: Y | X37: Sesuai
A38: 31 | B38: Meningkatnya efektivitas penyelenggaraan informasi dan komunikasi publik | D38: Program Komunikasi Publik dan Media | E38: Meningkatnya efektivitas penyelenggaraan komunikasi publik nasional | G38: Museum Penerangan (TMII Jakarta) | H38: Penguatan Komunikasi dan Informasi Publik Nasional | I38: Terselenggaranya Layanan Informasi Benda-benda Bersejarah di Bidang Komunikasi dan Informasi | J38: Y | L38: Layanan Informasi Benda - Benda Bersejarah di Bidang Komunikasi dan Informasi | M38: Layanan Informasi Benda - Benda Bersejarah di Bidang Komunikasi dan Informasi | N38: 50000 Orang | O38: Y | P38: Y | Q38: Y | R38: Y | T38: Y | U38: Y | V38: Y | W38: Y | X38: Sesuai
A39: 32 | B39: Meningkatnya efektivitas penyelenggaraan informasi dan komunikasi publik | D39: Program Dukungan Manajemen | E39: Meningkatkan efektivitas dan efisiensi pengelolaan birokrasi di Komdigi untuk mendukung transformasi digital nasional | G39: Sekretariat Ditjen Komunikasi Publik dan Media | H39: Pengelolaan Keuangan, BMN dan Umum Direktorat Jenderal Komunikasi Publik dan Media | I39: Meningkatnya Kualitas Tata Kelola Ditjen KPM yang Bersih dan Efisien | J39: Y | L39: Layanan Manajemen Keuangan | M39: Layanan Manajemen Keuangan | N39: 3 Dokumen | O39: Y | P39: Y | Q39: Y | R39: Y | T39: Y | U39: Y | V39: Y | W39: Y | X39: Sesuai
A40: 33 | B40: Meningkatnya efektivitas penyelenggaraan informasi dan komunikasi publik | D40: Program Dukungan Manajemen | E40: Meningkatkan efektivitas dan efisiensi pengelolaan birokrasi di Komdigi untuk mendukung transformasi digital nasional | G40: Sekretariat Ditjen Komunikasi Publik dan Media | H40: Pengelolaan Keuangan, BMN dan Umum Direktorat Jenderal Komunikasi Publik dan Media | I40: Meningkatnya Kualitas Tata Kelola Ditjen KPM yang Bersih dan Efisien | J40: Y | L40: Layanan BMN | M40: Layanan BMN | N40: 1 Layanan | O40: Y | P40: Y | Q40: Y | R40: Y | T40: Y | U40: Y | V40: Y | W40: Y | X40: Sesuai
A41: 34 | B41: Meningkatnya efektivitas penyelenggaraan informasi dan komunikasi publik | D41: Program Dukungan Manajemen | E41: Meningkatkan efektivitas dan efisiensi pengelolaan birokrasi di Komdigi untuk mendukung transformasi digital nasional | G41: Sekretariat Ditjen Komunikasi Publik dan Media | H41: Pengelolaan Keuangan, BMN dan Umum Direktorat Jenderal Komunikasi Publik dan Media | I41: Meningkatnya Kualitas Tata Kelola Ditjen KPM yang Bersih dan Efisien | J41: Y | L41: Layanan Hukum | M41: Layanan Hukum | N41: 1 Layanan | O41: Y | P41: Y | Q41: Y | R41: Y | T41: Y | U41: Y | V41: Y | W41: Y | X41: Sesuai
A42: 35 | B42: Meningkatnya efektivitas penyelenggaraan informasi dan komunikasi publik | D42: Program Dukungan Manajemen | E42: Meningkatkan efektivitas dan efisiensi pengelolaan birokrasi di Komdigi untuk mendukung transformasi digital nasional | G42: Sekretariat Ditjen Komunikasi Publik dan Media | H42: Pengelolaan Keuangan, BMN dan Umum Direktorat Jenderal Komunikasi Publik dan Media | I42: Meningkatnya Kualitas Tata Kelola Ditjen KPM yang Bersih dan Efisien | J42: Y | L42: Layanan Umum | M42: Layanan Umum | N42: 1 Layanan | O42: Y | P42: Y | Q42: Y | R42: Y | T42: Y | U42: Y | V42: Y | W42: Y | X42: Sesuai
A43: 36 | B43: Meningkatnya efektivitas penyelenggaraan informasi dan komunikasi publik | D43: Program Dukungan Manajemen | E43: Meningkatkan efektivitas dan efisiensi pengelolaan birokrasi di Komdigi untuk mendukung transformasi digital nasional | G43: Sekretariat Ditjen Komunikasi Publik dan Media | H43: Pengelolaan Keuangan, BMN dan Umum Direktorat Jenderal Komunikasi Publik dan Media | I43: Meningkatnya Kualitas Tata Kelola Ditjen KPM yang Bersih dan Efisien | J43: Y | L43: Layanan Perkantoran | M43: Layanan Perkantoran | N43: 1 Layanan | O43: Y | P43: Y | Q43: Y | R43: Y | T43: Y | U43: Y | V43: Y | W43: Y | X43: Sesuai
A44: 37 | B44: Meningkatnya efektivitas penyelenggaraan informasi dan komunikasi publik | D44: Program Dukungan Manajemen | E44: Meningkatkan efektivitas dan efisiensi pengelolaan birokrasi di Komdigi untuk mendukung transformasi digital nasional | G44: Sekretariat Ditjen Komunikasi Publik dan Media | H44: Pengelolaan Keuangan, BMN dan Umum Direktorat Jenderal Komunikasi Publik dan Media | I44: Meningkatnya Kualitas Tata Kelola Ditjen KPM yang Bersih dan Efisien | J44: Y | L44: Layanan Sarana Internal | M44: Layanan Sarana Internal | N44: 76 Unit | O44: Y | P44: Y | Q44: Y | R44: Y | T44: Y | U44: Y | V44: Y | W44: Y | X44: Sesuai
A45: 38 | B45: Meningkatnya efektivitas penyelenggaraan informasi dan komunikasi publik | D45: Program Dukungan Manajemen | E45: Meningkatkan efektivitas dan efisiensi pengelolaan birokrasi di Komdigi untuk mendukung transformasi digital nasional | G45: Sekretariat Ditjen Komunikasi Publik dan Media | H45: Pengelolaan Keuangan, BMN dan Umum Direktorat Jenderal Komunikasi Publik dan Media | I45: Meningkatnya Kualitas Tata Kelola Ditjen KPM yang Bersih dan Efisien | J45: Y | L45: Layanan Manajemen SDM | M45: Layanan Manajemen SDM | N45: 1 Layanan | O45: Y | P45: Y | Q45: Y | R45: Y | T45: Y | U45: Y | V45: Y | W45: Y
A46: 39 | B46: Meningkatnya efektivitas penyelenggaraan informasi dan komunikasi publik | D46: Program Dukungan Manajemen | E46: Meningkatkan efektivitas dan efisiensi pengelolaan birokrasi di Komdigi untuk mendukung transformasi digital nasional | G46: Sekretariat Ditjen Komunikasi Publik dan Media | H46: Pengelolaan Keuangan, BMN dan Umum Direktorat Jenderal Komunikasi Publik dan Media | I46: Meningkatnya Kualitas Tata Kelola Ditjen KPM yang Bersih dan Efisien | J46: Y | L46: Layanan Perencanaan dan Penganggaran | M46: Layanan Perencanaan dan Penganggaran | N46: 2 Dokumen | O46: Y | P46: Y | Q46: Y | R46: Y | T46: Y | U46: Y | V46: Y | W46: Y
A47: 40 | B47: Meningkatnya efektivitas penyelenggaraan informasi dan komunikasi publik | D47: Program Dukungan Manajemen | E47: Meningkatkan efektivitas dan efisiensi pengelolaan birokrasi di Komdigi untuk mendukung transformasi digital nasional | G47: Sekretariat Ditjen Komunikasi Publik dan Media | H47: Pengelolaan Keuangan, BMN dan Umum Direktorat Jenderal Komunikasi Publik dan Media | I47: Meningkatnya Kualitas Tata Kelola Ditjen KPM yang Bersih dan Efisien | J47: Y | L47: Layanan Pemantauan dan Evaluasi | M47: Layanan Pemantauan dan Evaluasi | N47: 3 Dokumen | O47: Y | P47: Y | Q47: Y | R47: Y | T47: Y | U47: Y | V47: Y | W47: Y
A48: 41 | B48: Meningkatnya efektivitas penyelenggaraan informasi dan komunikasi publik | D48: Program Komunikasi Publik dan Media | E48: Meningkatnya kualitas ekosistem media yang terpercaya | G48: Direktorat Ekosistem Media | H48: Pengembangan Ekosistem Media, Kehumasan, dan Kemitraan Komunikasi Publik | I48: Mewujudkan ekosistem media yang sehat di era digital | J48: Y | L48: Kebijakan Pengembangan Ekosistem Media | M48: Kebijakan Pengembangan Ekosistem Media | N48: 1 Rekomendasi Kebijakan | O48: Y | P48: Y | Q48: Y | R48: Y | T48: Y | U48: Y | V48: Y | W48: Y
A49: 42 | B49: Meningkatnya efektivitas penyelenggaraan informasi dan komunikasi publik | D49: Program Komunikasi Publik dan Media | E49: Meningkatnya kualitas ekosistem media yang terpercaya | G49: Direktorat Ekosistem Media | H49: Pengembangan Ekosistem Media, Kehumasan, dan Kemitraan Komunikasi Publik | I49: Mewujudkan ekosistem media yang sehat di era digital | J49: Y | L49: NSPK Pengelolaan Relasi Media | M49: NSPK Pengelolaan Relasi Media | N49: 1 NSPK | O49: Y | P49: Y | Q49: Y | R49: Y | T49: Y | U49: Y | V49: Y | W49: Y
A50: 43 | B50: Meningkatnya efektivitas penyelenggaraan informasi dan komunikasi publik | D50: Program Komunikasi Publik dan Media | E50: Meningkatnya kualitas ekosistem media yang terpercaya | G50: Direktorat Ekosistem Media | H50: Pengembangan Ekosistem Media, Kehumasan, dan Kemitraan Komunikasi Publik | I50: Mewujudkan ekosistem media yang sehat di era digital | J50: Y | L50: Pengelolaan Relasi dan Pengembangan Media | M50: Pengelolaan Relasi dan Pengembangan Media | N50: 0 Kegiatan | O50: Y | P50: Y | Q50: Y | R50: Y | T50: Y | U50: Y | V50: Y | W50: Y
A51: 44 | B51: Meningkatnya efektivitas penyelenggaraan informasi dan komunikasi publik | D51: Program Komunikasi Publik dan Media | E51: Meningkatnya kualitas ekosistem media yang terpercaya | G51: Direktorat Ekosistem Media | H51: Pengembangan Ekosistem Media, Kehumasan, dan Kemitraan Komunikasi Publik | I51: Mewujudkan ekosistem media yang sehat di era digital | J51: Y | L51: Pengelolaan Kerja Sama Media Massa | M51: Pengelolaan Kerja Sama Media Massa | N51: 0 Kegiatan | O51: Y | P51: Y | Q51: Y | R51: Y | T51: Y | U51: Y | V51: Y | W51: Y
A52: 45 | B52: Meningkatnya efektivitas penyelenggaraan informasi dan komunikasi publik | D52: Program Komunikasi Publik dan Media | E52: Meningkatnya kualitas ekosistem media yang terpercaya | G52: Direktorat Ekosistem Media | H52: Pengembangan Ekosistem Media, Kehumasan, dan Kemitraan Komunikasi Publik | I52: Mewujudkan ekosistem media yang sehat di era digital | J52: Y | L52: Pengelolaan Kanal Redaksi Nasional | M52: Pengelolaan Kanal Redaksi Nasional | N52: 0 Kegiatan | O52: Y | P52: Y | Q52: Y | R52: Y | T52: Y | U52: Y | V52: Y | W52: Y
A53: 46 | B53: Meningkatnya efektivitas penyelenggaraan informasi dan komunikasi publik | D53: Program Komunikasi Publik dan Media | E53: Meningkatnya kualitas ekosistem media yang terpercaya | G53: Direktorat Ekosistem Media | H53: Pengembangan Ekosistem Media, Kehumasan, dan Kemitraan Komunikasi Publik | I53: Mewujudkan ekosistem media yang sehat di era digital | J53: Y | L53: Pengelolaan Engagement Publik Melalui Media | M53: Pengelolaan Engagement Publik Melalui Media | N53: 0 Kegiatan | O53: Y | P53: Y | Q53: Y | R53: Y | T53: Y | U53: Y | V53: Y | W53: Y
A54: 47 | B54: Meningkatnya efektivitas penyelenggaraan informasi dan komunikasi publik | D54: Program Komunikasi Publik dan Media | E54: Meningkatnya kualitas ekosistem media yang terpercaya | G54: Direktorat Ekosistem Media | H54: Pengembangan Ekosistem Media, Kehumasan, dan Kemitraan Komunikasi Publik | I54: Mewujudkan ekosistem media yang sehat di era digital | J54: Y | L54: Pengelolaan Penerbitan Izin dan Rekomendasi Kegiatan Jurnalistik Media Asing | M54: Pengelolaan Penerbitan Izin dan Rekomendasi Kegiatan Jurnalistik Media Asing | N54: 50 Lembaga | O54: Y | P54: Y | Q54: Y | R54: Y | T54: Y | U54: Y | V54: Y | W54: Y
A55: 48 | B55: Meningkatnya efektivitas penyelenggaraan informasi dan komunikasi publik | D55: Program Komunikasi Publik dan Media | E55: Meningkatnya kualitas ekosistem media yang terpercaya | G55: Direktorat Ekosistem Media | H55: Pengembangan Ekosistem Media, Kehumasan, dan Kemitraan Komunikasi Publik | I55: Mewujudkan ekosistem media yang sehat di era digital | J55: Y | L55: Pembinaan Jabatan Fungsional Bidang Penyiaran | M55: Pembinaan Jabatan Fungsional Bidang Penyiaran | N55: 3900 Orang | O55: Y | P55: Y | Q55: Y | R55: Y | T55: Y | U55: Y | V55: Y | W55: Y
A56: Direktorat Jenderal Ekosistem Digital
A57: 1 | B57: Mewujudkan Transformasi Internal Manajemen adaptif dan resilien | D57: Program Pengembangan dan Penguatan Ekosistem dan Ruang Digital | E57: Meningkatkan efektivitas dan efisiensi pengelolaan birokrasi di Komdigi untuk mendukung transformasi digital nasional | G57: Sekretariat Ditjen Ekosistem Digital | H57: Pengelolaan Keuangan, BMN dan Umum Direktorat Jenderal Ekosistem Digital | I57: Meningkatnya kualitas tata kelola Ditjen Ekosistem Digital yang transparan,akuntabel, bersih dan efisien | J57: Y | L57: Layanan Organisasi dan Tata Kelola Internal | M57: Layanan Organisasi dan Tata Kelola Internal | N57: 1 Layanan | O57: Y | P57: Y | Q57: Y | R57: Y | S57: - | T57: Y | U57: Y | V57: Y | W57: Y | X57: -
A58: 2 | B58: Mewujudkan Transformasi Internal Manajemen adaptif dan resilien | D58: Program Pengembangan dan Penguatan Ekosistem dan Ruang Digital | E58: Meningkatkan efektivitas dan efisiensi pengelolaan birokrasi di Komdigi untuk mendukung transformasi digital nasional | G58: Sekretariat Ditjen Ekosistem Digital | H58: Pengelolaan Keuangan, BMN dan Umum Direktorat Jenderal Ekosistem Digital | I58: Meningkatnya kualitas tata kelola Ditjen Ekosistem Digital yang transparan,akuntabel, bersih dan efisien | J58: Y | L58: Layanan Data dan Informasi | M58: Layanan Data dan Informasi | N58: 1 Layanan | O58: Y | P58: Y | Q58: Y | R58: Y | S58: - | T58: Y | U58: Y | V58: Y | W58: Y | X58: -
A59: 3 | B59: Mewujudkan Transformasi Internal Manajemen adaptif dan resilien | D59: Program Pengembangan dan Penguatan Ekosistem dan Ruang Digital | E59: Meningkatkan efektivitas dan efisiensi pengelolaan birokrasi di Komdigi untuk mendukung transformasi digital nasional | G59: Sekretariat Ditjen Ekosistem Digital | H59: Pengelolaan Keuangan, BMN dan Umum Direktorat Jenderal Ekosistem Digital | I59: Meningkatnya kualitas tata kelola Ditjen Ekosistem Digital yang transparan,akuntabel, bersih dan efisien | J59: Y | L59: Layanan Hukum | M59: Layanan Hukum | N59: 1 Layanan | O59: Y | P59: Y | Q59: Y | R59: Y | S59: - | T59: Y | U59: Y | V59: Y | W59: Y | X59: -
A60: 4 | B60: Mewujudkan Transformasi Internal Manajemen adaptif dan resilien | D60: Program Pengembangan dan Penguatan Ekosistem dan Ruang Digital | E60: Meningkatkan efektivitas dan efisiensi pengelolaan birokrasi di Komdigi untuk mendukung transformasi digital nasional | G60: Sekretariat Ditjen Ekosistem Digital | H60: Pengelolaan Keuangan, BMN dan Umum Direktorat Jenderal Ekosistem Digital | I60: Meningkatnya kualitas tata kelola Ditjen Ekosistem Digital yang transparan,akuntabel, bersih dan efisien | J60: Y | L60: Layanan Umum | M60: Layanan Umum | N60: 1 Layanan | O60: Y | P60: Y | Q60: Y | R60: Y | S60: - | T60: Y | U60: Y | V60: Y | W60: Y | X60: -
A61: 5 | B61: Mewujudkan Transformasi Internal Manajemen adaptif dan resilien | D61: Program Pengembangan dan Penguatan Ekosistem dan Ruang Digital | E61: Meningkatkan efektivitas dan efisiensi pengelolaan birokrasi di Komdigi untuk mendukung transformasi digital nasional | G61: Sekretariat Ditjen Ekosistem Digital | H61: Pengelolaan Keuangan, BMN dan Umum Direktorat Jenderal Ekosistem Digital | I61: Meningkatnya kualitas tata kelola Ditjen Ekosistem Digital yang transparan,akuntabel, bersih dan efisien | J61: Y | L61: Layanan Perkantoran | M61: Layanan Perkantoran | N61: 2 Layanan | O61: Y | P61: Y | Q61: Y | R61: Y | S61: - | T61: Y | U61: Y | V61: Y | W61: Y | X61: -
A62: 6 | B62: Mewujudkan Transformasi Internal Manajemen adaptif dan resilien | D62: Program Pengembangan dan Penguatan Ekosistem dan Ruang Digital | E62: Meningkatkan efektivitas dan efisiensi pengelolaan birokrasi di Komdigi untuk mendukung transformasi digital nasional | G62: Sekretariat Ditjen Ekosistem Digital | H62: Pengelolaan Keuangan, BMN dan Umum Direktorat Jenderal Ekosistem Digital | I62: Meningkatnya kualitas tata kelola Ditjen Ekosistem Digital yang transparan,akuntabel, bersih dan efisien | J62: Y | L62: Layanan Sarana Internal | M62: Layanan Sarana Internal | N62: 341 Unit | O62: Y | P62: Y | Q62: Y | R62: Y | S62: - | T62: Y | U62: Y | V62: Y | W62: Y | X62: -
A63: 7 | B63: Mewujudkan Transformasi Internal Manajemen adaptif dan resilien | D63: Program Pengembangan dan Penguatan Ekosistem dan Ruang Digital | E63: Meningkatkan efektivitas dan efisiensi pengelolaan birokrasi di Komdigi untuk mendukung transformasi digital nasional | G63: Sekretariat Ditjen Ekosistem Digital | H63: Pengelolaan Keuangan, BMN dan Umum Direktorat Jenderal Ekosistem Digital | I63: Meningkatnya kualitas tata kelola Ditjen Ekosistem Digital yang transparan,akuntabel, bersih dan efisien | J63: Y | L63: Layanan Manajemen SDM | M63: Layanan Manajemen SDM | N63: 1 Layanan | O63: Y | P63: Y | Q63: Y | R63: Y | S63: - | T63: Y | U63: Y | V63: Y | W63: Y | X63: -
A64: 8 | B64: Mewujudkan Transformasi Internal Manajemen adaptif dan resilien | D64: Program Pengembangan dan Penguatan Ekosistem dan Ruang Digital | E64: Meningkatkan efektivitas dan efisiensi pengelolaan birokrasi di Komdigi untuk mendukung transformasi digital nasional | G64: Sekretariat Ditjen Ekosistem Digital | H64: Pengelolaan Keuangan, BMN dan Umum Direktorat Jenderal Ekosistem Digital | I64: Meningkatnya kualitas tata kelola Ditjen Ekosistem Digital yang transparan,akuntabel, bersih dan efisien | J64: Y | L64: Layanan Pemantauan dan Evaluasi | M64: Layanan Pemantauan dan Evaluasi | N64: 13 Dokumen | O64: Y | P64: Y | Q64: Y | R64: Y | S64: - | T64: Y | U64: Y | V64: Y | W64: Y | X64: -
A65: 9 | B65: Mewujudkan Transformasi Internal Manajemen adaptif dan resilien | D65: Program Pengembangan dan Penguatan Ekosistem dan Ruang Digital | E65: Meningkatkan efektivitas dan efisiensi pengelolaan birokrasi di Komdigi untuk mendukung transformasi digital nasional | G65: Sekretariat Ditjen Ekosistem Digital | H65: Pengelolaan Keuangan, BMN dan Umum Direktorat Jenderal Ekosistem Digital | I65: Meningkatnya kualitas tata kelola Ditjen Ekosistem Digital yang transparan,akuntabel, bersih dan efisien | J65: Y | L65: Layanan Manajemen Keuangan | M65: Layanan Manajemen Keuangan | N65: 7 Dokumen | O65: Y | P65: Y | Q65: Y | R65: Y | S65: - | T65: Y | U65: Y | V65: Y | W65: Y | X65: -
A66: 10 | B66: Mewujudkan Transformasi Internal Manajemen adaptif dan resilien | D66: Program Pengembangan dan Penguatan Ekosistem dan Ruang Digital | E66: Meningkatkan efektivitas dan efisiensi pengelolaan birokrasi di Komdigi untuk mendukung transformasi digital nasional | G66: Sekretariat Ditjen Ekosistem Digital | H66: Pengelolaan Keuangan, BMN dan Umum Direktorat Jenderal Ekosistem Digital | I66: Meningkatnya kualitas tata kelola Ditjen Ekosistem Digital yang transparan,akuntabel, bersih dan efisien | J66: Y | L66: Layanan Perencanaan dan Penganggaran | M66: Layanan Perencanaan dan Penganggaran | N66: 17 Dokumen | O66: Y | P66: Y | Q66: Y | R66: Y | S66: - | T66: Y | U66: Y | V66: Y | W66: Y | X66: -
A67: 11 | B67: Mewujudkan Transformasi Internal Manajemen adaptif dan resilien | D67: Program Pengembangan dan Penguatan Ekosistem dan Ruang Digital | E67: Meningkatkan efektivitas dan efisiensi pengelolaan birokrasi di Komdigi untuk mendukung transformasi digital nasional | G67: Sekretariat Ditjen Ekosistem Digital | H67: Pengelolaan Keuangan, BMN dan Umum Direktorat Jenderal Ekosistem Digital | I67: Meningkatnya kualitas tata kelola Ditjen Ekosistem Digital yang transparan,akuntabel, bersih dan efisien | J67: Y | L67: Dukungan Konferensi dan Event Pengembangan Teknologi di Bidang Pos dan Informatika | M67: Dukungan Konferensi dan Event Pengembangan Teknologi di Bidang Pos dan Informatika | N67: 2 Kegiatan | O67: Y | P67: Y | Q67: Y | R67: Y | S67: - | T67: Y | U67: Y | V67: Y | W67: Y | X67: -
A68: 12 | B68: Meningkatnya Pertumbuhan Ekonomi dari Pengembangan Ekosistem Digital Nasional | D68: Program Pengembangan dan Penguatan Ekosistem dan Ruang Digital | E68: Meningkatnya Pertumbuhan Industri Gim dan Startup Digital Nasional | G68: Direktorat Pengembangan Ekosistem Digital | H68: Pengembangan Ekosistem untuk Startup Digital dan Gim Nasional | I68: Meningkatnya Pengembangan Startup Digital | J68: Y | L68: Fasilitasi Digital Technopreneur | M68: Fasilitasi Digital Technopreneur | N68: 5 Start Up | O68: Y | P68: Y | Q68: Y | R68: Y | S68: - | T68: Y | U68: Y | V68: Y | W68: Y | X68: -
... A104: 48 | B104: Meningkatnya Pertumbuhan Ekonomi dari Pengembangan Ekosistem Digital Nasional | D104: Program Pengembangan dan Penguatan Ekosistem dan Ruang Digital | E104: Meningkatnya Pertumbuhan Industri Pos Logistik dan Penyiaran | G104: Direktorat Pos dan Penyiaran | H104: Pengembangan Industri Pos dan Penyiaran | I104: Menguatnya Tata Kelola untuk Mendukung Keberlanjutan Industri Penyiaran | J104: Y | L104: Rekomendasi Kebijakan Terkait Rencana Dasar Teknik Penyiaran | M104: Rekomendasi Kebijakan Terkait Rencana Dasar Teknik Penyiaran | N104: 1 Rekomendasi Kebijakan | O104: Y | P104: Y | Q104: Y | R104: Y | S104: Tidak memiliki Indikator Kinerja Output | T104: Y | U104: Y | V104: Y | W104: Y | X104: Tidak memiliki Indikator Kinerja Output
A105: 49 | B105: Meningkatnya Pertumbuhan Ekonomi dari Pengembangan Ekosistem Digital Nasional | D105: Program Pengembangan dan Penguatan Ekosistem dan Ruang Digital | E105: Meningkatnya Pertumbuhan Industri Pos Logistik dan Penyiaran | G105: Direktorat Pos dan Penyiaran | H105: Pengembangan Industri Pos dan Penyiaran | I105: Menguatnya Tata Kelola untuk Mendukung Keberlanjutan Industri Penyiaran | J105: Y | L105: Fasilitasi Implementasi KBLI Penyiaran | M105: Fasilitasi Implementasi KBLI Penyiaran | O105: Y | P105: Y | Q105: Y | R105: Y | S105: Terdapat update informasi kinerja yang memungkinkan RO ini sudah tidak lagi digunakan, karena tidak ada informasi RO dan Targetnya pada Aplikasi Renja (KRISNA) | T105: Y | U105: Y | V105: Y | W105: Y | X105: Tidak memiliki Indikator Kinerja Output
A106: 50 | B106: Meningkatnya Pertumbuhan Ekonomi dari Pengembangan Ekosistem Digital Nasional | D106: Program Pengembangan dan Penguatan Ekosistem dan Ruang Digital | E106: Meningkatnya Pertumbuhan Industri Pos Logistik dan Penyiaran | G106: Direktorat Pos dan Penyiaran | H106: Pengembangan Industri Pos dan Penyiaran | I106: Menguatnya Tata Kelola untuk Mendukung Keberlanjutan Industri Penyiaran | J106: Y | L106: Fasilitasi Peningkatan Kualitas Lembaga Penyiaran Jasa Penyiaran Radio | M106: Fasilitasi Peningkatan Kualitas Lembaga Penyiaran Jasa Penyiaran Radio | N106: 100 Lembaga | O106: Y | P106: Y | Q106: Y | R106: Y | S106: - | T106: Y | U106: Y | V106: Y | W106: Y | X106: -
A107: 51 | B107: Meningkatnya Pertumbuhan Ekonomi dari Pengembangan Ekosistem Digital Nasional | D107: Program Pengembangan dan Penguatan Ekosistem dan Ruang Digital | E107: Meningkatnya Pertumbuhan Industri Pos Logistik dan Penyiaran | G107: Direktorat Pos dan Penyiaran | H107: Pengembangan Industri Pos dan Penyiaran | I107: Menguatnya Tata Kelola untuk Mendukung Keberlanjutan Industri Penyiaran | J107: Y | L107: Rekomendasi Kebijakan Terkait Model Bisnis Dan Daya Saing Industri Penyiaran | M107: Rekomendasi Kebijakan Terkait Model Bisnis Dan Daya Saing Industri Penyiaran | N107: 2 Rekomendasi Kebijakan | O107: Y | P107: Y | Q107: Y | R107: Y | S107: - | T107: Y | U107: Y | V107: Y | W107: Y | X107: Tidak memiliki Indikator Kinerja Output
A108: 52 | B108: Meningkatnya Pertumbuhan Ekonomi dari Pengembangan Ekosistem Digital Nasional | D108: Program Pengembangan dan Penguatan Ekosistem dan Ruang Digital | E108: Meningkatnya Pertumbuhan Industri Pos Logistik dan Penyiaran | G108: Direktorat Pos dan Penyiaran | H108: Pengembangan Industri Pos dan Penyiaran | I108: Menguatnya Tata Kelola untuk Mendukung Keberlanjutan Industri Penyiaran | J108: Y | L108: OM - Prasarana Digital Broadcasting System | M108: OM - Prasarana Digital Broadcasting System | N108: 31 Titik/Lokasi | O108: Y | P108: Y | Q108: Y | R108: Y | S108: Tidak memiliki Indikator Kinerja Output | T108: Y | U108: Y | V108: Y | W108: Y | X108: Terdapat update informasi kinerja yang memungkinkan RO ini sudah tidak lagi digunakan, karena tidak ada informasi RO dan Targetnya pada Aplikasi Renja (KRISNA)
